Workbook

Sheet INICIO
B6: PRECIO BASE DD: | C6: 1.297 | F6: Cotización Dólar | J6: http://www.bna.com.ar/
B8: PRECIO BASE NEGRA: | C8: 1.14 | F8: Dólar Definido | J8: 1498
B10: FECHA DE ACTUALIZACIÓN: | D10: 45398 | J10: Buscar | L10: Ctrl + B
D12: clientes | F12: BASE DD | L12: BASE NEGRA
B13: CLIENTES: | F13: % Incremento | G13: Base 100 | H13: Coeficiente | I13: Resultado | J13: Base U$S | K13: Base $ | L13: % Incremento | M13: Base 100 | N13: Coeficiente | O13: Resultado | P13: Base U$S | Q13: Base $
B14: 1 | D14: tato/rolando/alpes/javier/bassaro/El roble | F14: 8 | G14: 0.01 | H14: =PRODUCT(F14,G14) -> 0.08 | I14: =PRODUCT(H14,C6) -> 0.10376 | J14: =SUM(C6,I14) -> 1.40076 | K14: =PRODUCT(J8,J14) -> 2098.3385 | L14: 5 | M14: 0.01 | N14: =PRODUCT(L14,M14) -> 0.05 | O14: =PRODUCT(N14,C8) -> 0.057 | P14: =SUM(C8,O14) -> 1.197 | Q14: =PRODUCT(J8,P14) -> 1793.106
B15: 2 | D15: MARTINEZ/pretocom/parrillas omar/gillio | F15: 8 | G15: 0.01 | H15: =PRODUCT(F15,G15) -> 0.08 | I15: =PRODUCT(H15,C6) -> 0.10376 | J15: =SUM(C6,I15) -> 1.40076 | K15: =PRODUCT(J8,J15) -> 2098.3385 | L15: 5 | M15: 0.01 | N15: =PRODUCT(L15,M15) -> 0.05 | O15: =PRODUCT(N15,C8) -> 0.057 | P15: =SUM(C8,O15) -> 1.197 | Q15: =PRODUCT(J8,P15) -> 1793.106
B16: 3 | D16: megacer/esimet/ravi/sonoflex | F16: 15 | G16: 0.01 | H16: =PRODUCT(F16,G16) -> 0.15 | I16: =PRODUCT(H16,C6) -> 0.19455 | J16: =SUM(C6,I16) -> 1.49155 | K16: =PRODUCT(J8,J16) -> 2234.3419 | L16: 10 | M16: 0.01 | N16: =PRODUCT(L16,M16) -> 0.1 | O16: =PRODUCT(N16,C8) -> 0.114 | P16: =SUM(C8,O16) -> 1.254 | Q16: =PRODUCT(J8,P16) -> 1878.492
B17: 4 | D17: FABRICAL | F17: 12 | G17: 0.01 | H17: =PRODUCT(F17,G17) -> 0.12 | I17: =PRODUCT(H17,C6) -> 0.15564 | J17: =SUM(C6,I17) -> 1.45264 | K17: =PRODUCT(J8,J17) -> 2176.0547 | L17: 7 | M17: 0.01 | N17: =PRODUCT(L17,M17) -> 0.07 | O17: =PRODUCT(N17,C8) -> 0.0798 | P17: =SUM(C8,O17) -> 1.2198 | Q17: =PRODUCT(J8,P17) -> 1827.2604
B18: 5 | D18: PLEG HURLINGHAM/tasia/lujan/san nicolas/mesquitq/santodomingo | F18: 7 | G18: 0.01 | H18: =PRODUCT(F18,G18) -> 0.07 | I18: =PRODUCT(H18,C6) -> 0.09079 | J18: =SUM(C6,I18) -> 1.38779 | K18: =PRODUCT(J8,J18) -> 2078.9094 | L18: 5 | M18: 0.01 | N18: =PRODUCT(L18,M18) -> 0.05 | O18: =PRODUCT(N18,C8) -> 0.057 | P18: =SUM(C8,O18) -> 1.197 | Q18: =PRODUCT(J8,P18) -> 1793.106
B19: 6 | D19: OXPANE LASER/milsa/viane | F19: 6 | G19: 0.01 | H19: =PRODUCT(F19,G19) -> 0.06 | I19: =PRODUCT(H19,C6) -> 0.07782 | J19: =SUM(C6,I19) -> 1.37482 | K19: =PRODUCT(J8,J19) -> 2059.4804 | L19: 1 | M19: 0.01 | N19: =PRODUCT(L19,M19) -> 0.01 | O19: =PRODUCT(N19,C8) -> 0.0114 | P19: =SUM(C8,O19) -> 1.1514 | Q19: =PRODUCT(J8,P19) -> 1724.7972
B20: 7 | D20: GOR GRAS/rase/calcor/fabrica de luz/forjan/lagos | F20: 13 | G20: 0.01 | H20: =PRODUCT(F20,G20) -> 0.13 | I20: =PRODUCT(H20,C6) -> 0.16861 | J20: =SUM(C6,I20) -> 1.46561 | K20: =PRODUCT(J8,J20) -> 2195.4838 | L20: 9 | M20: 0.01 | N20: =PRODUCT(L20,M20) -> 0.09 | O20: =PRODUCT(N20,C8) -> 0.1026 | P20: =SUM(C8,O20) -> 1.2426 | Q20: =PRODUCT(J8,P20) -> 1861.4148
B21: 8 | D21: cormot/geluma/merigui/lumak | F21: 12 | G21: 0.01 | H21: =PRODUCT(F21,G21) -> 0.12 | I21: =PRODUCT(H21,C6) -> 0.15564 | J21: =SUM(C6,I21) -> 1.45264 | K21: =PRODUCT(J8,J21) -> 2176.0547 | L21: 9 | M21: 0.01 | N21: =PRODUCT(L21,M21) -> 0.09 | O21: =PRODUCT(N21,C8) -> 0.1026 | P21: =SUM(C8,O21) -> 1.2426 | Q21: =PRODUCT(J8,P21) -> 1861.4148
B22: 9 | D22: int pomp/gustavo carrocero | F22: 12 | G22: 0.01 | H22: =PRODUCT(F22,G22) -> 0.12 | I22: =PRODUCT(H22,C6) -> 0.15564 | J22: =SUM(C6,I22) -> 1.45264 | K22: =PRODUCT(J8,J22) -> 2176.0547 | L22: 8 | M22: 0.01 | N22: =PRODUCT(L22,M22) -> 0.08 | O22: =PRODUCT(N22,C8) -> 0.0912 | P22: =SUM(C8,O22) -> 1.2312 | Q22: =PRODUCT(J8,P22) -> 1844.3376
B23: 10 | D23: DI LORENZO/alico | F23: 12 | G23: 0.01 | H23: =PRODUCT(F23,G23) -> 0.12 | I23: =PRODUCT(H23,C6) -> 0.15564 | J23: =SUM(C6,I23) -> 1.45264 | K23: =PRODUCT(J8,J23) -> 2176.0547 | L23: 9 | M23: 0.01 | N23: =PRODUCT(L23,M23) -> 0.09 | O23: =PRODUCT(N23,C8) -> 0.1026 | P23: =SUM(C8,O23) -> 1.2426 | Q23: =PRODUCT(J8,P23) -> 1861.4148
B24: 11 | D24: buromaik/calterm | F24: 7 | G24: 0.01 | H24: =PRODUCT(F24,G24) -> 0.07 | I24: =PRODUCT(H24,C6) -> 0.09079 | J24: =SUM(C6,I24) -> 1.38779 | K24: =PRODUCT(J8,J24) -> 2078.9094 | L24: 5 | M24: 0.01 | N24: =PRODUCT(L24,M24) -> 0.05 | O24: =PRODUCT(N24,C8) -> 0.057 | P24: =SUM(C8,O24) -> 1.197 | Q24: =PRODUCT(J8,P24) -> 1793.106
B25: 12 | D25: morelli/campana/proyectos/accetub | F25: 6 | G25: 0.01 | H25: =PRODUCT(F25,G25) -> 0.06 | I25: =PRODUCT(H25,C6) -> 0.07782 | J25: =SUM(C6,I25) -> 1.37482 | K25: =PRODUCT(J8,J25) -> 2059.4804 | L25: 1 | M25: 0.01 | N25: =PRODUCT(L25,M25) -> 0.01 | O25: =PRODUCT(N25,C8) -> 0.0114 | P25: =SUM(C8,O25) -> 1.1514 | Q25: =PRODUCT(J8,P25) -> 1724.7972
B26: 13 | D26: HORNOS DEL SUR/carbone/msequipment | F26: 8 | G26: 0.01 | H26: =PRODUCT(F26,G26) -> 0.08 | I26: =PRODUCT(H26,C6) -> 0.10376 | J26: =SUM(C6,I26) -> 1.40076 | K26: =PRODUCT(J8,J26) -> 2098.3385 | L26: 5 | M26: 0.01 | N26: =PRODUCT(L26,M26) -> 0.05 | O26: =PRODUCT(N26,C8) -> 0.057 | P26: =SUM(C8,O26) -> 1.197 | Q26: =PRODUCT(J8,P26) -> 1793.106
B27: 14 | D27: rominic/norberto | F27: 24 | G27: 0.01 | H27: =PRODUCT(F27,G27) -> 0.24 | I27: =PRODUCT(H27,C6) -> 0.31128 | J27: =SUM(C6,I27) -> 1.60828 | K27: =PRODUCT(J8,J27) -> 2409.2034 | L27: 20 | M27: 0.01 | N27: =PRODUCT(L27,M27) -> 0.2 | O27: =PRODUCT(N27,C8) -> 0.228 | P27: =SUM(C8,O27) -> 1.368 | Q27: =PRODUCT(J8,P27) -> 2049.264
B28: 15 | D28: GESTEC/ARLEM/FIGUE/denti | F28: 24 | G28: 0.01 | H28: =PRODUCT(F28,G28) -> 0.24 | I28: =PRODUCT(H28,C6) -> 0.31128 | J28: =SUM(C6,I28) -> 1.60828 | K28: =PRODUCT(J8,J28) -> 2409.2034 | L28: 20 | M28: 0.01 | N28: =PRODUCT(L28,M28) -> 0.2 | O28: =PRODUCT(N28,C8) -> 0.228 | P28: =SUM(C8,O28) -> 1.368 | Q28: =PRODUCT(J8,P28) -> 2049.264
B29: 16 | D29: TECTOOL / fioreti/buero | F29: 6 | G29: 0.01 | H29: =PRODUCT(F29,G29) -> 0.06 | I29: =PRODUCT(H29,C6) -> 0.07782 | J29: =SUM(C6,I29) -> 1.37482 | K29: =PRODUCT(J8,J29) -> 2059.4804 | L29: 1 | M29: 0.01 | N29: =PRODUCT(L29,M29) -> 0.01 | O29: =PRODUCT(N29,C8) -> 0.0114 | P29: =SUM(C8,O29) -> 1.1514 | Q29: =PRODUCT(J8,P29) -> 1724.7972
B30: 17 | D30: TALLERES NAVALES/burner/eqa | F30: 10 | G30: 0.01 | H30: =PRODUCT(F30,G30) -> 0.1 | I30: =PRODUCT(H30,C6) -> 0.1297 | J30: =SUM(C6,I30) -> 1.4267 | K30: =PRODUCT(J8,J30) -> 2137.1966 | L30: 8 | M30: 0.01 | N30: =PRODUCT(L30,M30) -> 0.08 | O30: =PRODUCT(N30,C8) -> 0.0912 | P30: =SUM(C8,O30) -> 1.2312 | Q30: =PRODUCT(J8,P30) -> 1844.3376
B31: 18 | D31: PROVIMAR/PUERTAS/CAMPANA/MULTILIFT//am carrocerias/megaces | F31: 10 | G31: 0.01 | H31: =PRODUCT(F31,G31) -> 0.1 | I31: =PRODUCT(H31,C6) -> 0.1297 | J31: =SUM(C6,I31) -> 1.4267 | K31: =PRODUCT(J8,J31) -> 2137.1966 | L31: 8 | M31: 0.01 | N31: =PRODUCT(L31,M31) -> 0.08 | O31: =PRODUCT(N31,C8) -> 0.0912 | P31: =SUM(C8,O31) -> 1.2312 | Q31: =PRODUCT(J8,P31) -> 1844.3376
B32: 19 | D32: BARRERA/ACEBA/diegez/fitnes | F32: 8 | G32: 0.01 | H32: =PRODUCT(F32,G32) -> 0.08 | I32: =PRODUCT(H32,C6) -> 0.10376 | J32: =SUM(C6,I32) -> 1.40076 | K32: =PRODUCT(J8,J32) -> 2098.3385 | L32: 4 | M32: 0.01 | N32: =PRODUCT(L32,M32) -> 0.04 | O32: =PRODUCT(N32,C8) -> 0.0456 | P32: =SUM(C8,O32) -> 1.1856 | Q32: =PRODUCT(J8,P32) -> 1776.0288
B33: 20 | D33: COVIC/acerotec/frachia/beta | F33: 12 | G33: 0.01 | H33: =PRODUCT(F33,G33) -> 0.12 | I33: =PRODUCT(H33,C6) -> 0.15564 | J33: =SUM(C6,I33) -> 1.45264 | K33: =PRODUCT(J8,J33) -> 2176.0547 | L33: 9 | M33: 0.01 | N33: =PRODUCT(L33,M33) -> 0.09 | O33: =PRODUCT(N33,C8) -> 0.1026 | P33: =SUM(C8,O33) -> 1.2426 | Q33: =PRODUCT(J8,P33) -> 1861.4148
B34: 21 | D34: cromwell/MET GUILLON | F34: 12 | G34: 0.01 | H34: =PRODUCT(F34,G34) -> 0.12 | I34: =PRODUCT(H34,C6) -> 0.15564 | J34: =SUM(C6,I34) -> 1.45264 | K34: =PRODUCT(J8,J34) -> 2176.0547 | L34: 9 | M34: 0.01 | N34: =PRODUCT(L34,M34) -> 0.09 | O34: =PRODUCT(N34,C8) -> 0.1026 | P34: =SUM(C8,O34) -> 1.2426 | Q34: =PRODUCT(J8,P34) -> 1861.4148
B35: 22 | D35: rodel/metic design/servitec | F35: 21 | G35: 0.01 | H35: =PRODUCT(F35,G35) -> 0.21 | I35: =PRODUCT(H35,C6) -> 0.27237 | J35: =SUM(C6,I35) -> 1.56937 | K35: =PRODUCT(J8,J35) -> 2350.9163 | L35: 18 | M35: 0.01 | N35: =PRODUCT(L35,M35) -> 0.18 | O35: =PRODUCT(N35,C8) -> 0.2052 | P35: =SUM(C8,O35) -> 1.3452 | Q35: =PRODUCT(J8,P35) -> 2015.1096
B36: 23 | D36: obregon/peope | F36: 8 | G36: 0.01 | H36: =PRODUCT(F36,G36) -> 0.08 | I36: =PRODUCT(H36,C6) -> 0.10376 | J36: =SUM(C6,I36) -> 1.40076 | K36: =PRODUCT(J8,J36) -> 2098.3385 | L36: 5 | M36: 0.01 | N36: =PRODUCT(L36,M36) -> 0.05 | O36: =PRODUCT(N36,C8) -> 0.057 | P36: =SUM(C8,O36) -> 1.197 | Q36: =PRODUCT(J8,P36) -> 1793.106
B37: 24 | D37: CARPINTERO/oximetal/met gh/rotofrance/calden/brauer | F37: 6 | G37: 0.01 | H37: =PRODUCT(F37,G37) -> 0.06 | I37: =PRODUCT(H37,C6) -> 0.07782 | J37: =SUM(C6,I37) -> 1.37482 | K37: =PRODUCT(J8,J37) -> 2059.4804 | L37: 1 | M37: 0.01 | N37: =PRODUCT(L37,M37) -> 0.01 | O37: =PRODUCT(N37,C8) -> 0.0114 | P37: =SUM(C8,O37) -> 1.1514 | Q37: =PRODUCT(J8,P37) -> 1724.7972
B38: 25 | D38: HIERGATH/GALARZA | F38: 10 | G38: 0.01 | H38: =PRODUCT(F38,G38) -> 0.1 | I38: =PRODUCT(H38,C6) -> 0.1297 | J38: =SUM(C6,I38) -> 1.4267 | K38: =PRODUCT(J8,J38) -> 2137.1966 | L38: 9 | M38: 0.01 | N38: =PRODUCT(L38,M38) -> 0.09 | O38: =PRODUCT(N38,C8) -> 0.1026 | P38: =SUM(C8,O38) -> 1.2426 | Q38: =PRODUCT(J8,P38) -> 1861.4148
B39: 26 | D39: SARRO/lumac/rimauro | F39: 12 | G39: 0.01 | H39: =PRODUCT(F39,G39) -> 0.12 | I39: =PRODUCT(H39,C6) -> 0.15564 | J39: =SUM(C6,I39) -> 1.45264 | K39: =PRODUCT(J8,J39) -> 2176.0547 | L39: 10 | M39: 0.01 | N39: =PRODUCT(L39,M39) -> 0.1 | O39: =PRODUCT(N39,C8) -> 0.114 | P39: =SUM(C8,O39) -> 1.254 | Q39: =PRODUCT(J8,P39) -> 1878.492
B40: 27 | D40: RADICE/DODERO/secaire | F40: 12 | G40: 0.01 | H40: =PRODUCT(F40,G40) -> 0.12 | I40: =PRODUCT(H40,C6) -> 0.15564 | J40: =SUM(C6,I40) -> 1.45264 | K40: =PRODUCT(J8,J40) -> 2176.0547 | L40: 5 | M40: 0.01 | N40: =PRODUCT(L40,M40) -> 0.05 | O40: =PRODUCT(N40,C8) -> 0.057 | P40: =SUM(C8,O40) -> 1.197 | Q40: =PRODUCT(J8,P40) -> 1793.106
B41: 28 | D41: ACEREC/escapes/solomita | F41: 8 | G41: 0.01 | H41: =PRODUCT(F41,G41) -> 0.08 | I41: =PRODUCT(H41,C6) -> 0.10376 | J41: =SUM(C6,I41) -> 1.40076 | K41: =PRODUCT(J8,J41) -> 2098.3385 | L41: 6 | M41: 0.01 | N41: =PRODUCT(L41,M41) -> 0.06 | O41: =PRODUCT(N41,C8) -> 0.0684 | P41: =SUM(C8,O41) -> 1.2084 | Q41: =PRODUCT(J8,P41) -> 1810.1832
B42: 29 | D42: binetti/titanium/carlos | F42: 8 | G42: 0.01 | H42: =PRODUCT(F42,G42) -> 0.08 | I42: =PRODUCT(H42,C6) -> 0.10376 | J42: =SUM(C6,I42) -> 1.40076 | K42: =PRODUCT(J8,J42) -> 2098.3385 | L42: 5 | M42: 0.01 | N42: =PRODUCT(L42,M42) -> 0.05 | O42: =PRODUCT(N42,C8) -> 0.057 | P42: =SUM(C8,O42) -> 1.197 | Q42: =PRODUCT(J8,P42) -> 1793.106
B43: 30 | D43: CUATRO ASES/secaire/petenelo/maresca | F43: 8 | G43: 0.01 | H43: =PRODUCT(F43,G43) -> 0.08 | I43: =PRODUCT(H43,C6) -> 0.10376 | J43: =SUM(C6,I43) -> 1.40076 | K43: =PRODUCT(J8,J43) -> 2098.3385 | L43: 5 | M43: 0.01 | N43: =PRODUCT(L43,M43) -> 0.05 | O43: =PRODUCT(N43,C8) -> 0.057 | P43: =SUM(C8,O43) -> 1.197 | Q43: =PRODUCT(J8,P43) -> 1793.106
B44: 31 | D44: colo | F44: 6 | G44: 0.01 | H44: =PRODUCT(F44,G44) -> 0.06 | I44: =PRODUCT(H44,C6) -> 0.07782 | J44: =SUM(C6,I44) -> 1.37482 | K44: =PRODUCT(J8,J44) -> 2059.4804 | L44: 2 | M44: 0.01 | N44: =PRODUCT(L44,M44) -> 0.02 | O44: =PRODUCT(N44,C8) -> 0.0228 | P44: =SUM(C8,O44) -> 1.1628 | Q44: =PRODUCT(J8,P44) -> 1741.8744
B45: 32 | D45: DALMA/fornari | F45: 12 | G45: 0.01 | H45: =PRODUCT(F45,G45) -> 0.12 | I45: =PRODUCT(H45,C6) -> 0.15564 | J45: =SUM(C6,I45) -> 1.45264 | K45: =PRODUCT(J8,J45) -> 2176.0547 | L45: 9 | M45: 0.01 | N45: =PRODUCT(L45,M45) -> 0.09 | O45: =PRODUCT(N45,C8) -> 0.1026 | P45: =SUM(C8,O45) -> 1.2426 | Q45: =PRODUCT(J8,P45) -> 1861.4148
B46: 33 | D46: ITEXA | F46: 8 | G46: 0.01 | H46: =PRODUCT(F46,G46) -> 0.08 | I46: =PRODUCT(H46,C6) -> 0.10376 | J46: =SUM(C6,I46) -> 1.40076 | K46: =PRODUCT(J8,J46) -> 2098.3385 | L46: 5 | M46: 0.01 | N46: =PRODUCT(L46,M46) -> 0.05 | O46: =PRODUCT(N46,C8) -> 0.057 | P46: =SUM(C8,O46) -> 1.197 | Q46: =PRODUCT(J8,P46) -> 1793.106
B47: 34 | D47: CB ACCESORIOS/fursan/casasco | F47: 8 | G47: 0.01 | H47: =PRODUCT(F47,G47) -> 0.08 | I47: =PRODUCT(H47,C6) -> 0.10376 | J47: =SUM(C6,I47) -> 1.40076 | K47: =PRODUCT(J8,J47) -> 2098.3385 | L47: 5 | M47: 0.01 | N47: =PRODUCT(L47,M47) -> 0.05 | O47: =PRODUCT(N47,C8) -> 0.057 | P47: =SUM(C8,O47) -> 1.197 | Q47: =PRODUCT(J8,P47) -> 1793.106
B48: 35 | D48: BRIMPEX | F48: 14 | G48: 0.01 | H48: =PRODUCT(F48,G48) -> 0.14 | I48: =PRODUCT(H48,C6) -> 0.18158 | J48: =SUM(C6,I48) -> 1.47858 | K48: =PRODUCT(J8,J48) -> 2214.9128 | L48: 12 | M48: 0.01 | N48: =PRODUCT(L48,M48) -> 0.12 | O48: =PRODUCT(N48,C8) -> 0.1368 | P48: =SUM(C8,O48) -> 1.2768 | Q48: =PRODUCT(J8,P48) -> 1912.6464
B49: 36 | D49: EIMETAR/bepanor | F49: 8 | G49: 0.01 | H49: =PRODUCT(F49,G49) -> 0.08 | I49: =PRODUCT(H49,C6) -> 0.10376 | J49: =SUM(C6,I49) -> 1.40076 | K49: =PRODUCT(J8,J49) -> 2098.3385 | L49: 6 | M49: 0.01 | N49: =PRODUCT(L49,M49) -> 0.06 | O49: =PRODUCT(N49,C8) -> 0.0684 | P49: =SUM(C8,O49) -> 1.2084 | Q49: =PRODUCT(J8,P49) -> 1810.1832
B50: 37 | D50: ruta 7/diamet | F50: 12 | G50: 0.01 | H50: =PRODUCT(F50,G50) -> 0.12 | I50: =PRODUCT(H50,C6) -> 0.15564 | J50: =SUM(C6,I50) -> 1.45264 | K50: =PRODUCT(J8,J50) -> 2176.0547 | L50: 9 | M50: 0.01 | N50: =PRODUCT(L50,M50) -> 0.09 | O50: =PRODUCT(N50,C8) -> 0.1026 | P50: =SUM(C8,O50) -> 1.2426 | Q50: =PRODUCT(J8,P50) -> 1861.4148
B51: 38 | D51: THEGOS | F51: 12 | G51: 0.01 | H51: =PRODUCT(F51,G51) -> 0.12 | I51: =PRODUCT(H51,C6) -> 0.15564 | J51: =SUM(C6,I51) -> 1.45264 | K51: =PRODUCT(J8,J51) -> 2176.0547 | L51: 10 | M51: 0.01 | N51: =PRODUCT(L51,M51) -> 0.1 | O51: =PRODUCT(N51,C8) -> 0.114 | P51: =SUM(C8,O51) -> 1.254 | Q51: =PRODUCT(J8,P51) -> 1878.492
B52: 39 | D52: CALDERAS MACCIO/gomez/metalcor | F52: 8 | G52: 0.01 | H52: =PRODUCT(F52,G52) -> 0.08 | I52: =PRODUCT(H52,C6) -> 0.10376 | J52: =SUM(C6,I52) -> 1.40076 | K52: =PRODUCT(J8,J52) -> 2098.3385 | L52: 5 | M52: 0.01 | N52: =PRODUCT(L52,M52) -> 0.05 | O52: =PRODUCT(N52,C8) -> 0.057 | P52: =SUM(C8,O52) -> 1.197 | Q52: =PRODUCT(J8,P52) -> 1793.106
B53: 40 | D53: hurlinmet/la plata /secaire | F53: 12 | G53: 0.01 | H53: =PRODUCT(F53,G53) -> 0.12 | I53: =PRODUCT(H53,C6) -> 0.15564 | J53: =SUM(C6,I53) -> 1.45264 | K53: =PRODUCT(J8,J53) -> 2176.0547 | L53: 10 | M53: 0.01 | N53: =PRODUCT(L53,M53) -> 0.1 | O53: =PRODUCT(N53,C8) -> 0.114 | P53: =SUM(C8,O53) -> 1.254 | Q53: =PRODUCT(J8,P53) -> 1878.492
B54: 41 | D54: GASER/tecnicorte | F54: 8 | G54: 0.01 | H54: =PRODUCT(F54,G54) -> 0.08 | I54: =PRODUCT(H54,C6) -> 0.10376 | J54: =SUM(C6,I54) -> 1.40076 | K54: =PRODUCT(J8,J54) -> 2098.3385 | L54: 6 | M54: 0.01 | N54: =PRODUCT(L54,M54) -> 0.06 | O54: =PRODUCT(N54,C8) -> 0.0684 | P54: =SUM(C8,O54) -> 1.2084 | Q54: =PRODUCT(J8,P54) -> 1810.1832
B55: 42 | D55: vascos | F55: 12 | G55: 0.01 | H55: =PRODUCT(F55,G55) -> 0.12 | I55: =PRODUCT(H55,C6) -> 0.15564 | J55: =SUM(C6,I55) -> 1.45264 | K55: =PRODUCT(J8,J55) -> 2176.0547 | L55: 9 | M55: 0.01 | N55: =PRODUCT(L55,M55) -> 0.09 | O55: =PRODUCT(N55,C8) -> 0.1026 | P55: =SUM(C8,O55) -> 1.2426 | Q55: =PRODUCT(J8,P55) -> 1861.4148
B56: 43 | D56: GUTIERREZ | F56: 10 | G56: 0.01 | H56: =PRODUCT(F56,G56) -> 0.1 | I56: =PRODUCT(H56,C6) -> 0.1297 | J56: =SUM(C6,I56) -> 1.4267 | K56: =PRODUCT(J8,J56) -> 2137.1966 | L56: 7 | M56: 0.01 | N56: =PRODUCT(L56,M56) -> 0.07 | O56: =PRODUCT(N56,C8) -> 0.0798 | P56: =SUM(C8,O56) -> 1.2198 | Q56: =PRODUCT(J8,P56) -> 1827.2604
B57: 44 | D57: MASTRICCHIO/diegez | F57: 12 | G57: 0.01 | H57: =PRODUCT(F57,G57) -> 0.12 | I57: =PRODUCT(H57,C6) -> 0.15564 | J57: =SUM(C6,I57) -> 1.45264 | K57: =PRODUCT(J8,J57) -> 2176.0547 | L57: 11 | M57: 0.01 | N57: =PRODUCT(L57,M57) -> 0.11 | O57: =PRODUCT(N57,C8) -> 0.1254 | P57: =SUM(C8,O57) -> 1.2654 | Q57: =PRODUCT(J8,P57) -> 1895.5692
B58: 45 | D58: anahi | F58: 12 | G58: 0.01 | H58: =PRODUCT(F58,G58) -> 0.12 | I58: =PRODUCT(H58,C6) -> 0.15564 | J58: =SUM(C6,I58) -> 1.45264 | K58: =PRODUCT(J8,J58) -> 2176.0547 | L58: 10 | M58: 0.01 | N58: =PRODUCT(L58,M58) -> 0.1 | O58: =PRODUCT(N58,C8) -> 0.114 | P58: =SUM(C8,O58) -> 1.254 | Q58: =PRODUCT(J8,P58) -> 1878.492
B59: 46 | D59: TORAL/tover/blasevich | F59: 10 | G59: 0.01 | H59: =PRODUCT(F59,G59) -> 0.1 | I59: =PRODUCT(H59,C6) -> 0.1297 | J59: =SUM(C6,I59) -> 1.4267 | K59: =PRODUCT(J8,J59) -> 2137.1966 | L59: 8 | M59: 0.01 | N59: =PRODUCT(L59,M59) -> 0.08 | O59: =PRODUCT(N59,C8) -> 0.0912 | P59: =SUM(C8,O59) -> 1.2312 | Q59: =PRODUCT(J8,P59) -> 1844.3376
B60: 47 | D60: KAPPA/ALYCO | F60: 8 | G60: 0.01 | H60: =PRODUCT(F60,G60) -> 0.08 | I60: =PRODUCT(H60,C6) -> 0.10376 | J60: =SUM(C6,I60) -> 1.40076 | K60: =PRODUCT(J8,J60) -> 2098.3385 | L60: 5 | M60: 0.01 | N60: =PRODUCT(L60,M60) -> 0.05 | O60: =PRODUCT(N60,C8) -> 0.057 | P60: =SUM(C8,O60) -> 1.197 | Q60: =PRODUCT(J8,P60) -> 1793.106
B61: 48 | D61: BOTTA/dediago | F61: 10 | G61: 0.01 | H61: =PRODUCT(F61,G61) -> 0.1 | I61: =PRODUCT(H61,C6) -> 0.1297 | J61: =SUM(C6,I61) -> 1.4267 | K61: =PRODUCT(J8,J61) -> 2137.1966 | L61: 7 | M61: 0.01 | N61: =PRODUCT(L61,M61) -> 0.07 | O61: =PRODUCT(N61,C8) -> 0.0798 | P61: =SUM(C8,O61) -> 1.2198 | Q61: =PRODUCT(J8,P61) -> 1827.2604
B62: 49 | D62: CONDORCOC/tecnocort | F62: 6 | G62: 0.01 | H62: =PRODUCT(F62,G62) -> 0.06 | I62: =PRODUCT(H62,C6) -> 0.07782 | J62: =SUM(C6,I62) -> 1.37482 | K62: =PRODUCT(J8,J62) -> 2059.4804 | L62: 1 | M62: 0.01 | N62: =PRODUCT(L62,M62) -> 0.01 | O62: =PRODUCT(N62,C8) -> 0.0114 | P62: =SUM(C8,O62) -> 1.1514 | Q62: =PRODUCT(J8,P62) -> 1724.7972
B63: 50 | D63: ZARATE/martino/ocho block/seguridad hm/monaco | F63: 6 | G63: 0.01 | H63: =PRODUCT(F63,G63) -> 0.06 | I63: =PRODUCT(H63,C6) -> 0.07782 | J63: =SUM(C6,I63) -> 1.37482 | K63: =PRODUCT(J8,J63) -> 2059.4804 | L63: 3 | M63: 0.01 | N63: =PRODUCT(L63,M63) -> 0.03 | O63: =PRODUCT(N63,C8) -> 0.0342 | P63: =SUM(C8,O63) -> 1.1742 | Q63: =PRODUCT(J8,P63) -> 1758.9516
B64: 51 | D64: IMP/cocuchi | F64: 8 | G64: 0.01 | H64: =PRODUCT(F64,G64) -> 0.08 | I64: =PRODUCT(H64,C6) -> 0.10376 | J64: =SUM(C6,I64) -> 1.40076 | K64: =PRODUCT(J8,J64) -> 2098.3385 | L64: 6 | M64: 0.01 | N64: =PRODUCT(L64,M64) -> 0.06 | O64: =PRODUCT(N64,C8) -> 0.0684 | P64: =SUM(C8,O64) -> 1.2084 | Q64: =PRODUCT(J8,P64) -> 1810.1832
B65: 52 | D65: CHAPET/anibal/suepet//met lonchamps | F65: 6 | G65: 0.01 | H65: =PRODUCT(F65,G65) -> 0.06 | I65: =PRODUCT(H65,C6) -> 0.07782 | J65: =SUM(C6,I65) -> 1.37482 | K65: =PRODUCT(J8,J65) -> 2059.4804 | L65: 4 | M65: 0.01 | N65: =PRODUCT(L65,M65) -> 0.04 | O65: =PRODUCT(N65,C8) -> 0.0456 | P65: =SUM(C8,O65) -> 1.1856 | Q65: =PRODUCT(J8,P65) -> 1776.0288
B66: 53 | D66: CONSOLI /galvanizados saenz/soldani | F66: 9 | G66: 0.01 | H66: =PRODUCT(F66,G66) -> 0.09 | I66: =PRODUCT(H66,C6) -> 0.11673 | J66: =SUM(C6,I66) -> 1.41373 | K66: =PRODUCT(J8,J66) -> 2117.7675 | L66: 6 | M66: 0.01 | N66: =PRODUCT(L66,M66) -> 0.06 | O66: =PRODUCT(N66,C8) -> 0.0684 | P66: =SUM(C8,O66) -> 1.2084 | Q66: =PRODUCT(J8,P66) -> 1810.1832
B67: 54 | D67: CAMSI/numasol/imsatermis | F67: 8 | G67: 0.01 | H67: =PRODUCT(F67,G67) -> 0.08 | I67: =PRODUCT(H67,C6) -> 0.10376 | J67: =SUM(C6,I67) -> 1.40076 | K67: =PRODUCT(J8,J67) -> 2098.3385 | L67: 5 | M67: 0.01 | N67: =PRODUCT(L67,M67) -> 0.05 | O67: =PRODUCT(N67,C8) -> 0.057 | P67: =SUM(C8,O67) -> 1.197 | Q67: =PRODUCT(J8,P67) -> 1793.106
B68: 55 | D68: ACERBO | F68: 13.8 | G68: 0.01 | H68: =PRODUCT(F68,G68) -> 0.138 | I68: =PRODUCT(H68,C6) -> 0.178986 | J68: =SUM(C6,I68) -> 1.475986 | K68: =PRODUCT(J8,J68) -> 2211.027 | L68: 22 | M68: 0.01 | N68: =PRODUCT(L68,M68) -> 0.22 | O68: =PRODUCT(N68,C8) -> 0.2508 | P68: =SUM(C8,O68) -> 1.3908 | Q68: =PRODUCT(J8,P68) -> 2083.4184
B69: 56 | D69: FZ | F69: 8 | G69: 0.01 | H69: =PRODUCT(F69,G69) -> 0.08 | I69: =PRODUCT(H69,C6) -> 0.10376 | J69: =SUM(C6,I69) -> 1.40076 | K69: =PRODUCT(J8,J69) -> 2098.3385 | L69: 5 | M69: 0.01 | N69: =PRODUCT(L69,M69) -> 0.05 | O69: =PRODUCT(N69,C8) -> 0.057 | P69: =SUM(C8,O69) -> 1.197 | Q69: =PRODUCT(J8,P69) -> 1793.106
B70: 57 | D70: TUBOCHAP/ROCA/calvo | F70: 15 | G70: 0.01 | H70: =PRODUCT(F70,G70) -> 0.15 | I70: =PRODUCT(H70,C6) -> 0.19455 | J70: =SUM(C6,I70) -> 1.49155 | K70: =PRODUCT(J8,J70) -> 2234.3419 | L70: 9 | M70: 0.01 | N70: =PRODUCT(L70,M70) -> 0.09 | O70: =PRODUCT(N70,C8) -> 0.1026 | P70: =SUM(C8,O70) -> 1.2426 | Q70: =PRODUCT(J8,P70) -> 1861.4148
B71: 58 | D71: lisy | F71: 6 | G71: 0.01 | H71: =PRODUCT(F71,G71) -> 0.06 | I71: =PRODUCT(H71,C6) -> 0.07782 | J71: =SUM(C6,I71) -> 1.37482 | K71: =PRODUCT(J8,J71) -> 2059.4804 | L71: 3 | M71: 0.01 | N71: =PRODUCT(L71,M71) -> 0.03 | O71: =PRODUCT(N71,C8) -> 0.0342 | P71: =SUM(C8,O71) -> 1.1742 | Q71: =PRODUCT(J8,P71) -> 1758.9516
B72: 59 | D72: BARRA | F72: 6 | G72: 0.01 | H72: =PRODUCT(F72,G72) -> 0.06 | I72: =PRODUCT(H72,C6) -> 0.07782 | J72: =SUM(C6,I72) -> 1.37482 | K72: =PRODUCT(J8,J72) -> 2059.4804 | L72: 3 | M72: 0.01 | N72: =PRODUCT(L72,M72) -> 0.03 | O72: =PRODUCT(N72,C8) -> 0.0342 | P72: =SUM(C8,O72) -> 1.1742 | Q72: =PRODUCT(J8,P72) -> 1758.9516
B73: 60 | D73: VACAREZA/algema | F73: 6 | G73: 0.01 | H73: =PRODUCT(F73,G73) -> 0.06 | I73: =PRODUCT(H73,C6) -> 0.07782 | J73: =SUM(C6,I73) -> 1.37482 | K73: =PRODUCT(J8,J73) -> 2059.4804 | L73: 5 | M73: 0.01 | N73: =PRODUCT(L73,M73) -> 0.05 | O73: =PRODUCT(N73,C8) -> 0.057 | P73: =SUM(C8,O73) -> 1.197 | Q73: =PRODUCT(J8,P73) -> 1793.106
B74: 61 | D74: DEMIQUIELI | F74: 14 | G74: 0.01 | H74: =PRODUCT(F74,G74) -> 0.14 | I74: =PRODUCT(H74,C6) -> 0.18158 | J74: =SUM(C6,I74) -> 1.47858 | K74: =PRODUCT(J8,J74) -> 2214.9128 | L74: 11 | M74: 0.01 | N74: =PRODUCT(L74,M74) -> 0.11 | O74: =PRODUCT(N74,C8) -> 0.1254 | P74: =SUM(C8,O74) -> 1.2654 | Q74: =PRODUCT(J8,P74) -> 1895.5692
B75: 62 | D75: BOERO REYNOX | F75: 8 | G75: 0.01 | H75: =PRODUCT(F75,G75) -> 0.08 | I75: =PRODUCT(H75,C6) -> 0.10376 | J75: =SUM(C6,I75) -> 1.40076 | K75: =PRODUCT(J8,J75) -> 2098.3385 | L75: 5 | M75: 0.01 | N75: =PRODUCT(L75,M75) -> 0.05 | O75: =PRODUCT(N75,C8) -> 0.057 | P75: =SUM(C8,O75) -> 1.197 | Q75: =PRODUCT(J8,P75) -> 1793.106
B76: 63 | D76: SERVIPROD | F76: 8 | G76: 0.01 | H76: =PRODUCT(F76,G76) -> 0.08 | I76: =PRODUCT(H76,C6) -> 0.10376 | J76: =SUM(C6,I76) -> 1.40076 | K76: =PRODUCT(J8,J76) -> 2098.3385 | L76: 5 | M76: 0.01 | N76: =PRODUCT(L76,M76) -> 0.05 | O76: =PRODUCT(N76,C8) -> 0.057 | P76: =SUM(C8,O76) -> 1.197 | Q76: =PRODUCT(J8,P76) -> 1793.106
B77: 64 | D77: COMPLEMENTOS DEP | F77: 7 | G77: 0.01 | H77: =PRODUCT(F77,G77) -> 0.07 | I77: =PRODUCT(H77,C6) -> 0.09079 | J77: =SUM(C6,I77) -> 1.38779 | K77: =PRODUCT(J8,J77) -> 2078.9094 | L77: 5 | M77: 0.01 | N77: =PRODUCT(L77,M77) -> 0.05 | O77: =PRODUCT(N77,C8) -> 0.057 | P77: =SUM(C8,O77) -> 1.197 | Q77: =PRODUCT(J8,P77) -> 1793.106
B78: 65 | D78: SCAGLIONE/CAJDA/palumieri | F78: 6 | G78: 0.01 | H78: =PRODUCT(F78,G78) -> 0.06 | I78: =PRODUCT(H78,C6) -> 0.07782 | J78: =SUM(C6,I78) -> 1.37482 | K78: =PRODUCT(J8,J78) -> 2059.4804 | L78: 2 | M78: 0.01 | N78: =PRODUCT(L78,M78) -> 0.02 | O78: =PRODUCT(N78,C8) -> 0.0228 | P78: =SUM(C8,O78) -> 1.1628 | Q78: =PRODUCT(J8,P78) -> 1741.8744
B79: 66 | D79: INDUMETALES | F79: 10 | G79: 0.01 | H79: =PRODUCT(F79,G79) -> 0.1 | I79: =PRODUCT(H79,C6) -> 0.1297 | J79: =SUM(C6,I79) -> 1.4267 | K79: =PRODUCT(J8,J79) -> 2137.1966 | L79: 6 | M79: 0.01 | N79: =PRODUCT(L79,M79) -> 0.06 | O79: =PRODUCT(N79,C8) -> 0.0684 | P79: =SUM(C8,O79) -> 1.2084 | Q79: =PRODUCT(J8,P79) -> 1810.1832
B80: 67 | D80: DUILIO QUEVEDO/LURASCHI | F80: 12 | G80: 0.01 | H80: =PRODUCT(F80,G80) -> 0.12 | I80: =PRODUCT(H80,C6) -> 0.15564 | J80: =SUM(C6,I80) -> 1.45264 | K80: =PRODUCT(J8,J80) -> 2176.0547 | L80: 8 | M80: 0.01 | N80: =PRODUCT(L80,M80) -> 0.08 | O80: =PRODUCT(N80,C8) -> 0.0912 | P80: =SUM(C8,O80) -> 1.2312 | Q80: =PRODUCT(J8,P80) -> 1844.3376
B81: 68 | D81: VISSIO | F81: 8 | G81: 0.01 | H81: =PRODUCT(F81,G81) -> 0.08 | I81: =PRODUCT(H81,C6) -> 0.10376 | J81: =SUM(C6,I81) -> 1.40076 | K81: =PRODUCT(J8,J81) -> 2098.3385 | L81: 5 | M81: 0.01 | N81: =PRODUCT(L81,M81) -> 0.05 | O81: =PRODUCT(N81,C8) -> 0.057 | P81: =SUM(C8,O81) -> 1.197 | Q81: =PRODUCT(J8,P81) -> 1793.106
B82: 69 | D82: ACERBRIL | F82: 23 | G82: 0.01 | H82: =PRODUCT(F82,G82) -> 0.23 | I82: =PRODUCT(H82,C6) -> 0.29831 | J82: =SUM(C6,I82) -> 1.59531 | K82: =PRODUCT(J8,J82) -> 2389.7744 | L82: 19 | M82: 0.01 | N82: =PRODUCT(L82,M82) -> 0.19 | O82: =PRODUCT(N82,C8) -> 0.2166 | P82: =SUM(C8,O82) -> 1.3566 | Q82: =PRODUCT(J8,P82) -> 2032.1868
B83: 70 | D83: ULISES/renar/proyect | F83: 10 | G83: 0.01 | H83: =PRODUCT(F83,G83) -> 0.1 | I83: =PRODUCT(H83,C6) -> 0.1297 | J83: =SUM(C6,I83) -> 1.4267 | K83: =PRODUCT(J8,J83) -> 2137.1966 | L83: 6 | M83: 0.01 | N83: =PRODUCT(L83,M83) -> 0.06 | O83: =PRODUCT(N83,C8) -> 0.0684 | P83: =SUM(C8,O83) -> 1.2084 | Q83: =PRODUCT(J8,P83) -> 1810.1832
B84: 71 | D84: CALPSA | F84: 8 | G84: 0.01 | H84: =PRODUCT(F84,G84) -> 0.08 | I84: =PRODUCT(H84,C6) -> 0.10376 | J84: =SUM(C6,I84) -> 1.40076 | K84: =PRODUCT(J8,J84) -> 2098.3385 | L84: 6 | M84: 0.01 | N84: =PRODUCT(L84,M84) -> 0.06 | O84: =PRODUCT(N84,C8) -> 0.0684 | P84: =SUM(C8,O84) -> 1.2084 | Q84: =PRODUCT(J8,P84) -> 1810.1832
B85: 72 | D85: DOLTZ | F85: 12 | G85: 0.01 | H85: =PRODUCT(F85,G85) -> 0.12 | I85: =PRODUCT(H85,C6) -> 0.15564 | J85: =SUM(C6,I85) -> 1.45264 | K85: =PRODUCT(J8,J85) -> 2176.0547 | L85: 9 | M85: 0.01 | N85: =PRODUCT(L85,M85) -> 0.09 | O85: =PRODUCT(N85,C8) -> 0.1026 | P85: =SUM(C8,O85) -> 1.2426 | Q85: =PRODUCT(J8,P85) -> 1861.4148
B86: 73 | D86: MICROFILTER | F86: 8 | G86: 0.01 | H86: =PRODUCT(F86,G86) -> 0.08 | I86: =PRODUCT(H86,C6) -> 0.10376 | J86: =SUM(C6,I86) -> 1.40076 | K86: =PRODUCT(J8,J86) -> 2098.3385 | L86: 5 | M86: 0.01 | N86: =PRODUCT(L86,M86) -> 0.05 | O86: =PRODUCT(N86,C8) -> 0.057 | P86: =SUM(C8,O86) -> 1.197 | Q86: =PRODUCT(J8,P86) -> 1793.106
B87: 74 | D87: accetub | F87: 10 | G87: 0.01 | H87: =PRODUCT(F87,G87) -> 0.1 | I87: =PRODUCT(H87,C6) -> 0.1297 | J87: =SUM(C6,I87) -> 1.4267 | K87: =PRODUCT(J8,J87) -> 2137.1966 | L87: 6 | M87: 0.01 | N87: =PRODUCT(L87,M87) -> 0.06 | O87: =PRODUCT(N87,C8) -> 0.0684 | P87: =SUM(C8,O87) -> 1.2084 | Q87: =PRODUCT(J8,P87) -> 1810.1832
B88: 75 | D88: METALCON | F88: 24 | G88: 0.01 | H88: =PRODUCT(F88,G88) -> 0.24 | I88: =PRODUCT(H88,C6) -> 0.31128 | J88: =SUM(C6,I88) -> 1.60828 | K88: =PRODUCT(J8,J88) -> 2409.2034 | L88: 20 | M88: 0.01 | N88: =PRODUCT(L88,M88) -> 0.2 | O88: =PRODUCT(N88,C8) -> 0.228 | P88: =SUM(C8,O88) -> 1.368 | Q88: =PRODUCT(J8,P88) -> 2049.264
B89: 76 | D89: mangueras flex | F89: 12 | G89: 0.01 | H89: =PRODUCT(F89,G89) -> 0.12 | I89: =PRODUCT(H89,C6) -> 0.15564 | J89: =SUM(C6,I89) -> 1.45264 | K89: =PRODUCT(J8,J89) -> 2176.0547 | L89: 8 | M89: 0.01 | N89: =PRODUCT(L89,M89) -> 0.08 | O89: =PRODUCT(N89,C8) -> 0.0912 | P89: =SUM(C8,O89) -> 1.2312 | Q89: =PRODUCT(J8,P89) -> 1844.3376
B90: 77 | F90: 23 | G90: 0.01 | H90: =PRODUCT(F90,G90) -> 0.23 | I90: =PRODUCT(H90,C6) -> 0.29831 | J90: =SUM(C6,I90) -> 1.59531 | K90: =PRODUCT(J8,J90) -> 2389.7744 | L90: 20 | M90: 0.01 | N90: =PRODUCT(L90,M90) -> 0.2 | O90: =PRODUCT(N90,C8) -> 0.228 | P90: =SUM(C8,O90) -> 1.368 | Q90: =PRODUCT(J8,P90) -> 2049.264
B91: 78 | D91: ACEROS SAE | F91: 19.5 | G91: 0.01 | H91: =PRODUCT(F91,G91) -> 0.195 | I91: =PRODUCT(H91,C6) -> 0.252915 | J91: =SUM(C6,I91) -> 1.549915 | K91: =PRODUCT(J8,J91) -> 2321.7727 | L91: 17 | M91: 0.01 | N91: =PRODUCT(L91,M91) -> 0.17 | O91: =PRODUCT(N91,C8) -> 0.1938 | P91: =SUM(C8,O91) -> 1.3338 | Q91: =PRODUCT(J8,P91) -> 1998.0324
B92: 79 | D92: MOM/reynoso/mirta torres | F92: 7 | G92: 0.01 | H92: =PRODUCT(F92,G92) -> 0.07 | I92: =PRODUCT(H92,C6) -> 0.09079 | J92: =SUM(C6,I92) -> 1.38779 | K92: =PRODUCT(J8,J92) -> 2078.9094 | L92: 5 | M92: 0.01 | N92: =PRODUCT(L92,M92) -> 0.05 | O92: =PRODUCT(N92,C8) -> 0.057 | P92: =SUM(C8,O92) -> 1.197 | Q92: =PRODUCT(J8,P92) -> 1793.106
B93: 80 | F93: 23 | G93: 0.01 | H93: =PRODUCT(F93,G93) -> 0.23 | I93: =PRODUCT(H93,C6) -> 0.29831 | J93: =SUM(C6,I93) -> 1.59531 | K93: =PRODUCT(J8,J93) -> 2389.7744 | L93: 19 | M93: 0.01 | N93: =PRODUCT(L93,M93) -> 0.19 | O93: =PRODUCT(N93,C8) -> 0.2166 | P93: =SUM(C8,O93) -> 1.3566 | Q93: =PRODUCT(J8,P93) -> 2032.1868
B94: 81 | D94: corte por agua/almametal | F94: 8 | G94: 0.01 | H94: =PRODUCT(F94,G94) -> 0.08 | I94: =PRODUCT(H94,C6) -> 0.10376 | J94: =SUM(C6,I94) -> 1.40076 | K94: =PRODUCT(J8,J94) -> 2098.3385 | L94: 3 | M94: 0.01 | N94: =PRODUCT(L94,M94) -> 0.03 | O94: =PRODUCT(N94,C8) -> 0.0342 | P94: =SUM(C8,O94) -> 1.1742 | Q94: =PRODUCT(J8,P94) -> 1758.9516
B95: 82 | D95: PUGELJ | F95: 23 | G95: 0.01 | H95: =PRODUCT(F95,G95) -> 0.23 | I95: =PRODUCT(H95,C6) -> 0.29831 | J95: =SUM(C6,I95) -> 1.59531 | K95: =PRODUCT(J8,J95) -> 2389.7744 | L95: 19 | M95: 0.01 | N95: =PRODUCT(L95,M95) -> 0.19 | O95: =PRODUCT(N95,C8) -> 0.2166 | P95: =SUM(C8,O95) -> 1.3566 | Q95: =PRODUCT(J8,P95) -> 2032.1868
B96: 83 | F96: 22 | G96: 0.01 | H96: =PRODUCT(F96,G96) -> 0.22 | I96: =PRODUCT(H96,C6) -> 0.28534 | J96: =SUM(C6,I96) -> 1.58234 | K96: =PRODUCT(J8,J96) -> 2370.3453 | L96: 19 | M96: 0.01 | N96: =PRODUCT(L96,M96) -> 0.19 | O96: =PRODUCT(N96,C8) -> 0.2166 | P96: =SUM(C8,O96) -> 1.3566 | Q96: =PRODUCT(J8,P96) -> 2032.1868
B97: 84 | D97: all gasquet | F97: 8 | G97: 0.01 | H97: =PRODUCT(F97,G97) -> 0.08 | I97: =PRODUCT(H97,C6) -> 0.10376 | J97: =SUM(C6,I97) -> 1.40076 | K97: =PRODUCT(J8,J97) -> 2098.3385 | L97: 5 | M97: 0.01 | N97: =PRODUCT(L97,M97) -> 0.05 | O97: =PRODUCT(N97,C8) -> 0.057 | P97: =SUM(C8,O97) -> 1.197 | Q97: =PRODUCT(J8,P97) -> 1793.106
B98: 85 | D98: IMAGEN/shulman | F98: 22 | G98: 0.01 | H98: =PRODUCT(F98,G98) -> 0.22 | I98: =PRODUCT(H98,C6) -> 0.28534 | J98: =SUM(C6,I98) -> 1.58234 | K98: =PRODUCT(J8,J98) -> 2370.3453 | L98: 21 | M98: 0.01 | N98: =PRODUCT(L98,M98) -> 0.21 | O98: =PRODUCT(N98,C8) -> 0.2394 | P98: =SUM(C8,O98) -> 1.3794 | Q98: =PRODUCT(J8,P98) -> 2066.3412
B99: 86 | D99: RICAMBI | F99: 8 | G99: 0.01 | H99: =PRODUCT(F99,G99) -> 0.08 | I99: =PRODUCT(H99,C6) -> 0.10376 | J99: =SUM(C6,I99) -> 1.40076 | K99: =PRODUCT(J8,J99) -> 2098.3385 | L99: 6 | M99: 0.01 | N99: =PRODUCT(L99,M99) -> 0.06 | O99: =PRODUCT(N99,C8) -> 0.0684 | P99: =SUM(C8,O99) -> 1.2084 | Q99: =PRODUCT(J8,P99) -> 1810.1832
B100: 87 | D100: PANTECNICA | F100: 12 | G100: 0.01 | H100: =PRODUCT(F100,G100) -> 0.12 | I100: =PRODUCT(H100,C6) -> 0.15564 | J100: =SUM(C6,I100) -> 1.45264 | K100: =PRODUCT(J8,J100) -> 2176.0547 | L100: 9 | M100: 0.01 | N100: =PRODUCT(L100,M100) -> 0.09 | O100: =PRODUCT(N100,C8) -> 0.1026 | P100: =SUM(C8,O100) -> 1.2426 | Q100: =PRODUCT(J8,P100) -> 1861.4148
B101: 88 | D101: LINEA DE ILUMINACION | F101: 10 | G101: 0.01 | H101: =PRODUCT(F101,G101) -> 0.1 | I101: =PRODUCT(H101,C6) -> 0.1297 | J101: =SUM(C6,I101) -> 1.4267 | K101: =PRODUCT(J8,J101) -> 2137.1966 | L101: 8 | M101: 0.01 | N101: =PRODUCT(L101,M101) -> 0.08 | O101: =PRODUCT(N101,C8) -> 0.0912 | P101: =SUM(C8,O101) -> 1.2312 | Q101: =PRODUCT(J8,P101) -> 1844.3376
B102: 89 | D102: BERTA | F102: 25 | G102: 0.01 | H102: =PRODUCT(F102,G102) -> 0.25 | I102: =PRODUCT(H102,C6) -> 0.32425 | J102: =SUM(C6,I102) -> 1.62125 | K102: =PRODUCT(J8,J102) -> 2428.6325 | L102: 19 | M102: 0.01 | N102: =PRODUCT(L102,M102) -> 0.19 | O102: =PRODUCT(N102,C8) -> 0.2166 | P102: =SUM(C8,O102) -> 1.3566 | Q102: =PRODUCT(J8,P102) -> 2032.1868
B103: 90 | D103: GRUPO QUIERO/puertas | F103: 10 | G103: 0.01 | H103: =PRODUCT(F103,G103) -> 0.1 | I103: =PRODUCT(H103,C6) -> 0.1297 | J103: =SUM(C6,I103) -> 1.4267 | K103: =PRODUCT(J8,J103) -> 2137.1966 | L103: 8 | M103: 0.01 | N103: =PRODUCT(L103,M103) -> 0.08 | O103: =PRODUCT(N103,C8) -> 0.0912 | P103: =SUM(C8,O103) -> 1.2312 | Q103: =PRODUCT(J8,P103) -> 1844.3376
B104: 91 | D104: servichap/permetal | F104: 7 | G104: 0.01 | H104: =PRODUCT(F104,G104) -> 0.07 | I104: =PRODUCT(H104,C6) -> 0.09079 | J104: =SUM(C6,I104) -> 1.38779 | K104: =PRODUCT(J8,J104) -> 2078.9094 | L104: 5 | M104: 0.01 | N104: =PRODUCT(L104,M104) -> 0.05 | O104: =PRODUCT(N104,C8) -> 0.057 | P104: =SUM(C8,O104) -> 1.197 | Q104: =PRODUCT(J8,P104) -> 1793.106
B105: 92 | D105: TEA/indumetales | F105: 12 | G105: 0.01 | H105: =PRODUCT(F105,G105) -> 0.12 | I105: =PRODUCT(H105,C6) -> 0.15564 | J105: =SUM(C6,I105) -> 1.45264 | K105: =PRODUCT(J8,J105) -> 2176.0547 | L105: 7 | M105: 0.01 | N105: =PRODUCT(L105,M105) -> 0.07 | O105: =PRODUCT(N105,C8) -> 0.0798 | P105: =SUM(C8,O105) -> 1.2198 | Q105: =PRODUCT(J8,P105) -> 1827.2604
B106: 93 | D106: SIMAT | F106: 18.5 | G106: 0.01 | H106: =PRODUCT(F106,G106) -> 0.185 | I106: =PRODUCT(H106,C6) -> 0.239945 | J106: =SUM(C6,I106) -> 1.536945 | K106: =PRODUCT(J8,J106) -> 2302.3436 | L106: 12 | M106: 0.01 | N106: =PRODUCT(L106,M106) -> 0.12 | O106: =PRODUCT(N106,C8) -> 0.1368 | P106: =SUM(C8,O106) -> 1.2768 | Q106: =PRODUCT(J8,P106) -> 1912.6464
B107: 94 | D107: SANCHEZ | F107: 8 | G107: 0.01 | H107: =PRODUCT(F107,G107) -> 0.08 | I107: =PRODUCT(H107,C6) -> 0.10376 | J107: =SUM(C6,I107) -> 1.40076 | K107: =PRODUCT(J8,J107) -> 2098.3385 | L107: 3 | M107: 0.01 | N107: =PRODUCT(L107,M107) -> 0.03 | O107: =PRODUCT(N107,C8) -> 0.0342 | P107: =SUM(C8,O107) -> 1.1742 | Q107: =PRODUCT(J8,P107) -> 1758.9516
B108: 95 | D108: minoli | F108: 15 | G108: 0.01 | H108: =PRODUCT(F108,G108) -> 0.15 | I108: =PRODUCT(H108,C6) -> 0.19455 | J108: =SUM(C6,I108) -> 1.49155 | K108: =PRODUCT(J8,J108) -> 2234.3419 | L108: 13 | M108: 0.01 | N108: =PRODUCT(L108,M108) -> 0.13 | O108: =PRODUCT(N108,C8) -> 0.1482 | P108: =SUM(C8,O108) -> 1.2882 | Q108: =PRODUCT(J8,P108) -> 1929.7236
...

Sheet 1
D2: =PROPER(INICIO!D14) -> Tato/Rolando/Alpes/Javier/Bassaro/El Roble
B4: LISTA DE PRECIOS EN PESOS
B5: DD | C5: 1000 | D5: 1220 | E5: 1500 | G5: NEGRA | H5: 1000 | I5: 1245 | J5: 1500
B6: 16 | C6: =SUM(C16*0.07)+C16 -> 2245.2222 | D6: =SUM(C16*0.04)+C16 -> 2182.272 | E6: =SUM(C16*0.04)+C16 -> 2182.272 | G6: 1.6 | H6: =SUM(H16*0.14)+H16 -> 2044.1408 | I6: XXX | J6: XXX
B7: 18 | C7: =SUM(C16*0.07)+C16 -> 2245.2222 | D7: =SUM(C16*0.04)+C16 -> 2182.272 | E7: =SUM(C16*0.04)+C16 -> 2182.272 | G7: 2 | H7: =SUM(H16*0.143)+H16 -> 2049.5202 | I7: =SUM(H16*0.11)+H16 -> 1990.3477 | J7: XXX
B8: 12,14 y 20 | C8: =SUM(C16*0.08)+C16 -> 2266.2056 | D8: =SUM(C16*0.05)+C16 -> 2203.2554 | E8: =SUM(C16*0.05)+C16 -> 2203.2554 | G8: 2.5 | H8: =SUM(H16*0.12)+H16 -> 2008.2787 | I8: =SUM(H16*0.09)+H16 -> 1954.4855 | J8: XXX
B9: 22 | C9: =SUM(C16*0.1)+C16 -> 2308.1723 | D9: =SUM(C16*0.07)+C16 -> 2245.2222 | E9: =SUM(C16*0.07)+C16 -> 2245.2222 | G9: 3.17 | H9: =SUM(H16*0.11)+H16 -> 1990.3477 | I9: =SUM(H16*0.08)+H16 -> 1936.5545 | J9: =SUM(H16*0.08)+H16 -> 1936.5545
B10: 0.65 | C10: =SUM(C16*0.12)+C16 -> 2350.1391 | D10: =SUM(C16*0.09)+C16 -> 2287.1889 | E10: XXX | G10: 4,75 Y 4.00 | H10: =SUM(H16*0.1)+H16 -> 1972.4166 | I10: =SUM(H16*0.07+H16) -> 1918.6234 | J10: =SUM(H16*0.07)+H16 -> 1918.6234
B11: 24 | C11: =SUM(C16*0.16)+C16 -> 2434.0726 | D11: =SUM(C16*0.13)+C16 -> 2371.1225 | E11: XXX | G11: 6.35 | H11: =SUM(H16*0.11)+H16 -> 1990.3477 | I11: =SUM(H16*0.08)+H16 -> 1936.5545 | J11: =SUM(H16*0.08)+H16 -> 1936.5545
B12: 26 | C12: =SUM(C16*0.2)+C16 -> 2518.0062 | D12: =SUM(C16*0.15)+C16 -> 2413.0893 | E12: XXX | G12: 8 | H12: =SUM(H16*0.11)+H16 -> 1990.3477 | I12: =SUM(H16*0.08)+H16 -> 1936.5545 | J12: =SUM(H16*0.08)+H16 -> 1936.5545
B13: 27 | C13: =SUM(C16*0.26)+C16 -> 2643.9065 | D13: XXX | E13: XXX | G13: 9.52 | H13: =SUM(H16*0.12)+H16 -> 2008.2787 | I13: =SUM(H16*0.09)+H16 -> 1954.4855 | J13: =SUM(H16*0.09)+H16 -> 1954.4855
B14: 30 | C14: =SUM(C16*0.32)+C16 -> 2769.8068 | D14: XXX | E14: XXX | G14: 12.7 | H14: =SUM(H16*0.12)+H16 -> 2008.2787 | I14: =SUM(H16*0.09)+H16 -> 1954.4855 | J14: =SUM(H16*0.09)+H16 -> 1954.4855
B16: BASE | C16: =SUM(INICIO!K14) -> 2098.3385 | G16: BASE | H16: =SUM(INICIO!Q14) -> 1793.106 | J16: herrero 10%
J17: pagola 10%
B18: 3.17 | C18: 1245 | D18: S/MEL | E18: =SUM(I9*0.1)+I9 -> 2130.2099 | I18: CALIDAD | J18: el roble 10% | K18: micro -12
B19: 4.75 | C19: 1500 | D19: S/MEL | E19: =SUM(J10*0.1)+J10 -> 2110.4858 | I19: ANCHO | J19: tato10%
B20: 6.35 | C20: 1500 | D20: S/MEL | E20: =SUM(J11*0.1)+J11 -> 2130.2099 | I20: ESPESOR
B22: LISTA DE PRECIOS EN DÓLARES
B23: DD | C23: 1000 | D23: 1220 | E23: 1500 | G23: NEGRA | H23: 1000 | I23: 1245 | J23: 1500
B24: 16 | C24: =SUM(C34*0.07)+C34 -> 1.4988132 | D24: =SUM(C34*0.04)+C34 -> 1.4567904 | E24: =SUM(C34*0.04)+C34 -> 1.4567904 | G24: 1.6 | H24: =SUM(H34*0.2)+H34 -> 1.4364 | I24: XXX | J24: XXX
B25: 18 | C25: =SUM(C34*0.07)+C34 -> 1.4988132 | D25: =SUM(C34*0.04)+C34 -> 1.4567904 | E25: =SUM(C34*0.04)+C34 -> 1.4567904 | G25: 2 | H25: =SUM(H34*0.14)+H34 -> 1.36458 | I25: =SUM(H34*0.11)+H34 -> 1.32867 | J25: XXX
B26: 12,14 y 20 | C26: =SUM(C34*0.08)+C34 -> 1.5128208 | D26: =SUM(C34*0.05)+C34 -> 1.470798 | E26: =SUM(C34*0.05)+C34 -> 1.470798 | G26: 2.5 | H26: =SUM(H34*0.12)+H34 -> 1.34064 | I26: =SUM(H34*0.09)+H34 -> 1.30473 | J26: XXX
B27: 22 | C27: =SUM(C34*0.1)+C34 -> 1.540836 | D27: =SUM(C34*0.07)+C34 -> 1.4988132 | E27: =SUM(C34*0.07)+C34 -> 1.4988132 | G27: 3.17 | H27: =SUM(H34*0.11)+H34 -> 1.32867 | I27: =SUM(H34*0.08)+H34 -> 1.29276 | J27: =SUM(H34*0.08)+H34 -> 1.29276
B28: 0.65 | C28: =SUM(C34*0.12)+C34 -> 1.5688512 | D28: =SUM(C34*0.09)+C34 -> 1.5268284 | E28: XXX | G28: 4,75 Y 4.00 | H28: =SUM(H34*0.1)+H34 -> 1.3167 | I28: =SUM(H34*0.07+H34) -> 1.28079 | J28: =SUM(H34*0.07)+H34 -> 1.28079
B29: 24 | C29: =SUM(C34*0.16)+C34 -> 1.6248816 | D29: =SUM(C34*0.13)+C34 -> 1.5828588 | E29: XXX | G29: 6.35 | H29: =SUM(H34*0.11)+H34 -> 1.32867 | I29: =SUM(H34*0.08)+H34 -> 1.29276 | J29: =SUM(H34*0.08)+H34 -> 1.29276
B30: 26 | C30: =SUM(C34*0.2)+C34 -> 1.680912 | D30: =SUM(C34*0.15)+C34 -> 1.610874 | E30: XXX | G30: 8 | H30: =SUM(H34*0.11)+H34 -> 1.32867 | I30: =SUM(H34*0.08)+H34 -> 1.29276 | J30: =SUM(H34*0.08)+H34 -> 1.29276
B31: 27 | C31: =SUM(C34*0.26)+C34 -> 1.7649576 | D31: XXX | E31: XXX | G31: 9.52 | H31: =SUM(H34*0.12)+H34 -> 1.34064 | I31: =SUM(H34*0.09)+H34 -> 1.30473 | J31: =SUM(H34*0.09)+H34 -> 1.30473
B32: 30 | C32: =SUM(C34*0.32)+C34 -> 1.8490032 | D32: XXX | E32: XXX | G32: 12.7 | H32: =SUM(H34*0.12)+H34 -> 1.34064 | I32: =SUM(H34*0.09)+H34 -> 1.30473 | J32: =SUM(H34*0.09)+H34 -> 1.30473
B34: BASE | C34: =SUM(INICIO!J14) -> 1.40076 | G34: BASE | H34: =SUM(INICIO!P14) -> 1.197
B36: 3.17 | C36: 1245 | D36: S/MEL | E36: =SUM(I27*0.1)+I27 -> 1.422036 | I36: CALIDAD
B37: 4.75 | C37: 1500 | D37: S/MEL | E37: =SUM(J28*0.1)+J28 -> 1.408869 | I37: ANCHO
B38: 6.35 | C38: 1500 | D38: S/MEL | E38: =SUM(J29*0.1)+J29 -> 1.422036 | I38: ESPESOR
B41: galv | C41: 1000 | D41: 1220
B42: 16 14
B43: 18
B44: 20
B45: 22
B46: 24
B47: 25
B48: 26

Sheet 2
B2: CLIENTE: | D2: =PROPER(INICIO!D15) -> Martinez/Pretocom/Parrillas Omar/Gillio
B4: LISTA DE PRECIOS EN PESOS
B5: DD | C5: 1000 | D5: 1220 | E5: 1500 | G5: NEGRA | H5: 1000 | I5: 1245 | J5: 1500
B6: 16 | C6: =SUM(C16*0.07)+C16 -> 2245.2222 | D6: =SUM(C16*0.04)+C16 -> 2182.272 | E6: =SUM(C16*0.04)+C16 -> 2182.272 | G6: 1.6 | H6: XXX | I6: XXX | J6: XXX
B7: 18 | C7: =SUM(C16*0.07)+C16 -> 2245.2222 | D7: =SUM(C16*0.04)+C16 -> 2182.272 | E7: =SUM(C16*0.04)+C16 -> 2182.272 | G7: 2 | H7: =SUM(H16*0.14)+H16 -> 2044.1408 | I7: =SUM(H16*0.11)+H16 -> 1990.3477 | J7: XXX
B8: 12,14 y 20 | C8: =SUM(C16*0.08)+C16 -> 2266.2056 | D8: =SUM(C16*0.05)+C16 -> 2203.2554 | E8: =SUM(C16*0.05)+C16 -> 2203.2554 | G8: 2.5 | H8: =SUM(H16*0.12)+H16 -> 2008.2787 | I8: =SUM(H16*0.09)+H16 -> 1954.4855 | J8: XXX
B9: 22 | C9: =SUM(C16*0.1)+C16 -> 2308.1723 | D9: =SUM(C16*0.07)+C16 -> 2245.2222 | E9: =SUM(C16*0.07)+C16 -> 2245.2222 | G9: 3.17 | H9: =SUM(H16*0.11)+H16 -> 1990.3477 | I9: =SUM(H16*0.08)+H16 -> 1936.5545 | J9: =SUM(H16*0.08)+H16 -> 1936.5545
B10: 0.65 | C10: =SUM(C16*0.12)+C16 -> 2350.1391 | D10: =SUM(C16*0.09)+C16 -> 2287.1889 | E10: XXX | G10: 4,75 Y 4.00 | H10: =SUM(H16*0.1)+H16 -> 1972.4166 | I10: =SUM(H16*0.07+H16) -> 1918.6234 | J10: =SUM(H16*0.07)+H16 -> 1918.6234
B11: 24 | C11: =SUM(C16*0.16)+C16 -> 2434.0726 | D11: =SUM(C16*0.13)+C16 -> 2371.1225 | E11: XXX | G11: 6.35 | H11: =SUM(H16*0.11)+H16 -> 1990.3477 | I11: =SUM(H16*0.08)+H16 -> 1936.5545 | J11: =SUM(H16*0.08)+H16 -> 1936.5545
B12: 26 | C12: =SUM(C16*0.2)+C16 -> 2518.0062 | D12: =SUM(C16*0.15)+C16 -> 2413.0893 | E12: XXX | G12: 8 | H12: =SUM(H16*0.11)+H16 -> 1990.3477 | I12: =SUM(H16*0.08)+H16 -> 1936.5545 | J12: =SUM(H16*0.08)+H16 -> 1936.5545
B13: 27 | C13: =SUM(C16*0.26)+C16 -> 2643.9065 | D13: XXX | E13: XXX | G13: 9.52 | H13: =SUM(H16*0.12)+H16 -> 2008.2787 | I13: =SUM(H16*0.09)+H16 -> 1954.4855 | J13: =SUM(H16*0.1)+H16 -> 1972.4166 | L13: brauer8
B14: 30 | C14: =SUM(C16*0.32)+C16 -> 2769.8068 | D14: XXX | E14: XXX | G14: 12.7 | H14: =SUM(H16*0.12)+H16 -> 2008.2787 | I14: =SUM(H16*0.09)+H16 -> 1954.4855 | J14: =SUM(H16*0.1)+H16 -> 1972.4166
B16: BASE | C16: =SUM(INICIO!K15) -> 2098.3385 | G16: BASE | H16: =SUM(INICIO!Q15) -> 1793.106 | I16: dec 2,6 | J16: 1.16 | K16: 45386
J17: elbio -6% | K17: lonc 8%
B18: 3.17 | C18: 1245 | D18: S/MEL | E18: =SUM(I9*0.1)+I9 -> 2130.2099 | I18: CALIDAD | J18: cal 1/4 3/16-12
B19: 4.75 | C19: 1500 | D19: S/MEL | E19: =SUM(J10*0.1)+J10 -> 2110.4858 | I19: ANCHO
B20: 6.35 | C20: 1500 | D20: S/MEL | E20: =SUM(J11*0.1)+J11 -> 2130.2099 | I20: ESPESOR
B22: LISTA DE PRECIOS EN DÓLARES
B23: DD | C23: 1000 | D23: 1220 | E23: 1500 | G23: NEGRA | H23: 1000 | I23: 1245 | J23: 1500
B24: 16 | C24: =SUM(C34*0.07)+C34 -> 1.4988132 | D24: =SUM(C34*0.04)+C34 -> 1.4567904 | E24: =SUM(C34*0.04)+C34 -> 1.4567904 | G24: 1.6 | H24: XXX | I24: XXX | J24: XXX
B25: 18 | C25: =SUM(C34*0.07)+C34 -> 1.4988132 | D25: =SUM(C34*0.04)+C34 -> 1.4567904 | E25: =SUM(C34*0.04)+C34 -> 1.4567904 | G25: 2 | H25: =SUM(H34*0.14)+H34 -> 1.36458 | I25: =SUM(H34*0.11)+H34 -> 1.32867 | J25: XXX
B26: 12,14 y 20 | C26: =SUM(C34*0.08)+C34 -> 1.5128208 | D26: =SUM(C34*0.05)+C34 -> 1.470798 | E26: =SUM(C34*0.05)+C34 -> 1.470798 | G26: 2.5 | H26: =SUM(H34*0.12)+H34 -> 1.34064 | I26: =SUM(H34*0.09)+H34 -> 1.30473 | J26: XXX
B27: 22 | C27: =SUM(C34*0.1)+C34 -> 1.540836 | D27: =SUM(C34*0.07)+C34 -> 1.4988132 | E27: =SUM(C34*0.07)+C34 -> 1.4988132 | G27: 3.17 | H27: =SUM(H34*0.11)+H34 -> 1.32867 | I27: =SUM(H34*0.08)+H34 -> 1.29276 | J27: =SUM(H34*0.08)+H34 -> 1.29276
B28: 0.65 | C28: =SUM(C34*0.12)+C34 -> 1.5688512 | D28: =SUM(C34*0.09)+C34 -> 1.5268284 | E28: XXX | G28: 4,75 Y 4.00 | H28: =SUM(H34*0.1)+H34 -> 1.3167 | I28: =SUM(H34*0.07+H34) -> 1.28079 | J28: =SUM(H34*0.07)+H34 -> 1.28079
B29: 24 | C29: =SUM(C34*0.16)+C34 -> 1.6248816 | D29: =SUM(C34*0.13)+C34 -> 1.5828588 | E29: XXX | G29: 6.35 | H29: =SUM(H34*0.11)+H34 -> 1.32867 | I29: =SUM(H34*0.08)+H34 -> 1.29276 | J29: =SUM(H34*0.08)+H34 -> 1.29276
B30: 26 | C30: =SUM(C34*0.2)+C34 -> 1.680912 | D30: =SUM(C34*0.15)+C34 -> 1.610874 | E30: XXX | G30: 8 | H30: =SUM(H34*0.11)+H34 -> 1.32867 | I30: =SUM(H34*0.08)+H34 -> 1.29276 | J30: =SUM(H34*0.08)+H34 -> 1.29276
B31: 27 | C31: =SUM(C34*0.26)+C34 -> 1.7649576 | D31: XXX | E31: XXX | G31: 9.52 | H31: =SUM(H34*0.12)+H34 -> 1.34064 | I31: =SUM(H34*0.09)+H34 -> 1.30473 | J31: =SUM(H34*0.09)+H34 -> 1.30473
B32: 30 | C32: =SUM(C34*0.32)+C34 -> 1.8490032 | D32: XXX | E32: XXX | G32: 12.7 | H32: =SUM(H34*0.12)+H34 -> 1.34064 | I32: =SUM(H34*0.09)+H34 -> 1.30473 | J32: =SUM(H34*0.09)+H34 -> 1.30473
B34: BASE | C34: =SUM(INICIO!J15) -> 1.40076 | G34: BASE | H34: =SUM(INICIO!P15) -> 1.197
B36: 3.17 | C36: 1245 | D36: S/MEL | E36: =SUM(I27*0.1)+I27 -> 1.422036 | I36: CALIDAD
B37: 4.75 | C37: 1500 | D37: S/MEL | E37: =SUM(J28*0.1)+J28 -> 1.408869 | I37: ANCHO
B38: 6.35 | C38: 1500 | D38: S/MEL | E38: =SUM(J29*0.1)+J29 -> 1.422036 | I38: ESPESOR
B42: caño | C42: elbio
B43: 40x60x2 | C43: 0
B44: 40x60x1,6
C45: =SUM(C53*0.08)+C53 -> 0

Sheet 3
B2: CLIENTE: | D2: =PROPER(INICIO!D16) -> Megacer/Esimet/Ravi/Sonoflex
B4: LISTA DE PRECIOS EN PESOS
B5: DD | C5: 1000 | D5: 1220 | E5: 1500 | G5: NEGRA | H5: 1000 | I5: 1245 | J5: 1500
B6: 16 | C6: =SUM(C16*0.07)+C16 -> 2390.7458 | D6: =SUM(C16*0.04)+C16 -> 2323.7156 | E6: =SUM(C16*0.04)+C16 -> 2323.7156 | G6: 1.6 | H6: XXX | I6: XXX | J6: XXX
B7: 18 | C7: =SUM(C16*0.07)+C16 -> 2390.7458 | D7: =SUM(C16*0.04)+C16 -> 2323.7156 | E7: =SUM(C16*0.04)+C16 -> 2323.7156 | G7: 2 | H7: =SUM(H16*0.14)+H16 -> 2141.4809 | I7: =SUM(H16*0.11)+H16 -> 2085.1261 | J7: XXX
B8: 12,14 y 20 | C8: =SUM(C16*0.08)+C16 -> 2413.0893 | D8: =SUM(C16*0.05)+C16 -> 2346.059 | E8: =SUM(C16*0.05)+C16 -> 2346.059 | G8: 2.5 | H8: =SUM(H16*0.12)+H16 -> 2103.911 | I8: =SUM(H16*0.09)+H16 -> 2047.5563 | J8: XXX
B9: 22 | C9: =SUM(C16*0.1)+C16 -> 2457.7761 | D9: =SUM(C16*0.07)+C16 -> 2390.7458 | E9: =SUM(C16*0.07)+C16 -> 2390.7458 | G9: 3.17 | H9: =SUM(H16*0.11)+H16 -> 2085.1261 | I9: =SUM(H16*0.08)+H16 -> 2028.7714 | J9: =SUM(H16*0.08)+H16 -> 2028.7714
B10: 0.65 | C10: =SUM(C16*0.12)+C16 -> 2502.4629 | D10: =SUM(C16*0.09)+C16 -> 2435.4327 | E10: XXX | G10: 4,75 Y 4.00 | H10: =SUM(H16*0.1)+H16 -> 2066.3412 | I10: =SUM(H16*0.07+H16) -> 2009.9864 | J10: =SUM(H16*0.07)+H16 -> 2009.9864
B11: 24 | C11: =SUM(C16*0.16)+C16 -> 2591.8366 | D11: =SUM(C16*0.13)+C16 -> 2524.8063 | E11: XXX | G11: 6.35 | H11: =SUM(H16*0.11)+H16 -> 2085.1261 | I11: =SUM(H16*0.08)+H16 -> 2028.7714 | J11: =SUM(H16*0.08)+H16 -> 2028.7714
B12: 26 | C12: =SUM(C16*0.2)+C16 -> 2681.2103 | D12: =SUM(C16*0.15)+C16 -> 2569.4932 | E12: XXX | G12: 8 | H12: =SUM(H16*0.11)+H16 -> 2085.1261 | I12: =SUM(H16*0.08)+H16 -> 2028.7714 | J12: =SUM(H16*0.08)+H16 -> 2028.7714
B13: 27 | C13: =SUM(C16*0.26)+C16 -> 2815.2708 | D13: XXX | E13: XXX | G13: 9.52 | H13: =SUM(H16*0.12)+H16 -> 2103.911 | I13: =SUM(H16*0.09)+H16 -> 2047.5563 | J13: =SUM(H16*0.09)+H16 -> 2047.5563
B14: 30 | C14: =SUM(C16*0.32)+C16 -> 2949.3313 | D14: XXX | E14: XXX | G14: 12.7 | H14: =SUM(H16*0.12)+H16 -> 2103.911 | I14: =SUM(H16*0.09)+H16 -> 2047.5563 | J14: =SUM(H16*0.09)+H16 -> 2047.5563
B16: BASE | C16: =SUM(INICIO!K16) -> 2234.3419 | G16: BASE | H16: =SUM(INICIO!Q16) -> 1878.492
B18: 3.17 | C18: 1245 | D18: S/MEL | E18: =SUM(I9*0.1)+I9 -> 2231.6485 | I18: CALIDAD
B19: 4.75 | C19: 1500 | D19: S/MEL | E19: =SUM(J10*0.1)+J10 -> 2210.9851 | I19: ANCHO
B20: 6.35 | C20: 1500 | D20: S/MEL | E20: =SUM(J11*0.1)+J11 -> 2231.6485 | I20: ESPESOR
B22: LISTA DE PRECIOS EN DÓLARES
B23: DD | C23: 1000 | D23: 1220 | E23: 1500 | G23: NEGRA | H23: 1000 | I23: 1245 | J23: 1500
B24: 16 | C24: =SUM(C34*0.07)+C34 -> 1.5959585 | D24: =SUM(C34*0.04)+C34 -> 1.551212 | E24: =SUM(C34*0.04)+C34 -> 1.551212 | G24: 1.6 | H24: XXX | I24: XXX | J24: XXX
B25: 18 | C25: =SUM(C34*0.07)+C34 -> 1.5959585 | D25: =SUM(C34*0.04)+C34 -> 1.551212 | E25: =SUM(C34*0.04)+C34 -> 1.551212 | G25: 2 | H25: =SUM(H34*0.14)+H34 -> 1.42956 | I25: =SUM(H34*0.11)+H34 -> 1.39194 | J25: XXX
B26: 12,14 y 20 | C26: =SUM(C34*0.08)+C34 -> 1.610874 | D26: =SUM(C34*0.05)+C34 -> 1.5661275 | E26: =SUM(C34*0.05)+C34 -> 1.5661275 | G26: 2.5 | H26: =SUM(H34*0.12)+H34 -> 1.40448 | I26: =SUM(H34*0.09)+H34 -> 1.36686 | J26: XXX
B27: 22 | C27: =SUM(C34*0.1)+C34 -> 1.640705 | D27: =SUM(C34*0.07)+C34 -> 1.5959585 | E27: =SUM(C34*0.07)+C34 -> 1.5959585 | G27: 3.17 | H27: =SUM(H34*0.11)+H34 -> 1.39194 | I27: =SUM(H34*0.08)+H34 -> 1.35432 | J27: =SUM(H34*0.08)+H34 -> 1.35432
B28: 0.65 | C28: =SUM(C34*0.12)+C34 -> 1.670536 | D28: =SUM(C34*0.09)+C34 -> 1.6257895 | E28: XXX | G28: 4,75 Y 4.00 | H28: =SUM(H34*0.1)+H34 -> 1.3794 | I28: =SUM(H34*0.07+H34) -> 1.34178 | J28: =SUM(H34*0.07)+H34 -> 1.34178
B29: 24 | C29: =SUM(C34*0.16)+C34 -> 1.730198 | D29: =SUM(C34*0.13)+C34 -> 1.6854515 | E29: XXX | G29: 6.35 | H29: =SUM(H34*0.11)+H34 -> 1.39194 | I29: =SUM(H34*0.08)+H34 -> 1.35432 | J29: =SUM(H34*0.08)+H34 -> 1.35432
B30: 26 | C30: =SUM(C34*0.2)+C34 -> 1.78986 | D30: =SUM(C34*0.15)+C34 -> 1.7152825 | E30: XXX | G30: 8 | H30: =SUM(H34*0.11)+H34 -> 1.39194 | I30: =SUM(H34*0.08)+H34 -> 1.35432 | J30: =SUM(H34*0.08)+H34 -> 1.35432
B31: 27 | C31: =SUM(C34*0.26)+C34 -> 1.879353 | D31: XXX | E31: XXX | G31: 9.52 | H31: =SUM(H34*0.12)+H34 -> 1.40448 | I31: =SUM(H34*0.09)+H34 -> 1.36686 | J31: =SUM(H34*0.09)+H34 -> 1.36686
B32: 30 | C32: =SUM(C34*0.32)+C34 -> 1.968846 | D32: XXX | E32: XXX | G32: 12.7 | H32: =SUM(H34*0.12)+H34 -> 1.40448 | I32: =SUM(H34*0.09)+H34 -> 1.36686 | J32: =SUM(H34*0.09)+H34 -> 1.36686
B34: BASE | C34: =SUM(INICIO!J16) -> 1.49155 | G34: BASE | H34: =SUM(INICIO!P16) -> 1.254
B36: 3.17 | C36: 1245 | D36: S/MEL | E36: =SUM(I27*0.1)+I27 -> 1.489752 | I36: CALIDAD
B37: 4.75 | C37: 1500 | D37: S/MEL | E37: =SUM(J28*0.1)+J28 -> 1.475958 | I37: ANCHO
B38: 6.35 | C38: 1500 | D38: S/MEL | E38: =SUM(J29*0.1)+J29 -> 1.489752 | I38: ESPESOR
B43: galv | C43: 1000 | D43: 1220
B44: 16 14
B45: 18
B46: 20
B47: 22
B48: 24
B49: 25
B50: 26

Sheet 4
B2: CLIENTE: | D2: =PROPER(INICIO!D17) -> Fabrical
B4: LISTA DE PRECIOS EN PESOS
B5: DD | C5: 1000 | D5: 1220 | E5: 1500 | G5: NEGRA | H5: 1000 | I5: 1245 | J5: 1500
B6: 16 | C6: =SUM(C16*0.07)+C16 -> 2328.3786 | D6: =SUM(C16*0.04)+C16 -> 2263.0969 | E6: =SUM(C16*0.04)+C16 -> 2263.0969 | G6: 1.6 | H6: XXX | I6: XXX | J6: XXX
B7: 18 | C7: =SUM(C16*0.07)+C16 -> 2328.3786 | D7: =SUM(C16*0.04)+C16 -> 2263.0969 | E7: =SUM(C16*0.04)+C16 -> 2263.0969 | G7: 2 | H7: =SUM(H16*0.14)+H16 -> 2083.0769 | I7: =SUM(H16*0.11)+H16 -> 2028.259 | J7: XXX
B8: 12,14 y 20 | C8: =SUM(C16*0.08)+C16 -> 2350.1391 | D8: =SUM(C16*0.05)+C16 -> 2284.8575 | E8: =SUM(C16*0.05)+C16 -> 2284.8575 | G8: 2.5 | H8: =SUM(H16*0.12)+H16 -> 2046.5316 | I8: =SUM(H16*0.09)+H16 -> 1991.7138 | J8: XXX
B9: 22 | C9: =SUM(C16*0.1)+C16 -> 2393.6602 | D9: =SUM(C16*0.07)+C16 -> 2328.3786 | E9: =SUM(C16*0.07)+C16 -> 2328.3786 | G9: 3.17 | H9: =SUM(H16*0.11)+H16 -> 2028.259 | I9: =SUM(H16*0.08)+H16 -> 1973.4412 | J9: =SUM(H16*0.08)+H16 -> 1973.4412
B10: 0.65 | C10: =SUM(C16*0.12)+C16 -> 2437.1813 | D10: =SUM(C16*0.09)+C16 -> 2371.8996 | E10: XXX | G10: 4,75 Y 4.00 | H10: =SUM(H16*0.11)+H16 -> 2028.259 | I10: =SUM(H16*0.08+H16) -> 1973.4412 | J10: =SUM(H16*0.08)+H16 -> 1973.4412
B11: 24 | C11: =SUM(C16*0.16)+C16 -> 2524.2235 | D11: =SUM(C16*0.13)+C16 -> 2458.9418 | E11: XXX | G11: 6.35 | H11: =SUM(H16*0.11)+H16 -> 2028.259 | I11: =SUM(H16*0.08)+H16 -> 1973.4412 | J11: =SUM(H16*0.08)+H16 -> 1973.4412
B12: 26 | C12: =SUM(C16*0.2)+C16 -> 2611.2657 | D12: =SUM(C16*0.15)+C16 -> 2502.4629 | E12: XXX | G12: 8 | H12: =SUM(H16*0.11)+H16 -> 2028.259 | I12: =SUM(H16*0.08)+H16 -> 1973.4412 | J12: =SUM(H16*0.08)+H16 -> 1973.4412
B13: 27 | C13: =SUM(C16*0.26)+C16 -> 2741.8289 | D13: XXX | E13: XXX | G13: 9.52 | H13: =SUM(H16*0.12)+H16 -> 2046.5316 | I13: =SUM(H16*0.09)+H16 -> 1991.7138 | J13: =SUM(H16*0.09)+H16 -> 1991.7138
B14: 30 | C14: =SUM(C16*0.32)+C16 -> 2872.3922 | D14: XXX | E14: XXX | G14: 12.7 | H14: =SUM(H16*0.12)+H16 -> 2046.5316 | I14: =SUM(H16*0.09)+H16 -> 1991.7138 | J14: =SUM(H16*0.09)+H16 -> 1991.7138
B16: BASE | C16: =SUM(INICIO!K17) -> 2176.0547 | G16: BASE | H16: =SUM(INICIO!Q17) -> 1827.2604 | I16: f24-- 5 | J16: 0.1
B18: 3.17 | C18: 1245 | D18: S/MEL | E18: =SUM(I9*0.1)+I9 -> 2170.7854 | I18: CALIDAD
B19: 4.75 | C19: 1500 | D19: S/MEL | E19: =SUM(J10*0.1)+J10 -> 2170.7854 | I19: ANCHO
B20: 6.35 | C20: 1500 | D20: S/MEL | E20: =SUM(J11*0.1)+J11 -> 2170.7854 | I20: ESPESOR
B23: LISTA DE PRECIOS EN DÓLARES
B24: DD | C24: 1000 | D24: 1220 | E24: 1500 | G24: NEGRA | H24: 1000 | I24: 1245 | J24: 1500
B25: 16 | C25: =SUM(C35*0.07)+C35 -> 1.5543248 | D25: =SUM(C35*0.04)+C35 -> 1.5107456 | E25: =SUM(C35*0.04)+C35 -> 1.5107456 | G25: 1.6 | H25: XXX | I25: XXX | J25: XXX
B26: 18 | C26: =SUM(C35*0.07)+C35 -> 1.5543248 | D26: =SUM(C35*0.04)+C35 -> 1.5107456 | E26: =SUM(C35*0.04)+C35 -> 1.5107456 | G26: 2 | H26: =SUM(H35*0.14)+H35 -> 1.390572 | I26: =SUM(H35*0.11)+H35 -> 1.353978 | J26: XXX
B27: 12,14 y 20 | C27: =SUM(C35*0.08)+C35 -> 1.5688512 | D27: =SUM(C35*0.05)+C35 -> 1.525272 | E27: =SUM(C35*0.05)+C35 -> 1.525272 | G27: 2.5 | H27: =SUM(H35*0.12)+H35 -> 1.366176 | I27: =SUM(H35*0.09)+H35 -> 1.329582 | J27: XXX
B28: 22 | C28: =SUM(C35*0.1)+C35 -> 1.597904 | D28: =SUM(C35*0.07)+C35 -> 1.5543248 | E28: =SUM(C35*0.07)+C35 -> 1.5543248 | G28: 3.17 | H28: =SUM(H35*0.11)+H35 -> 1.353978 | I28: =SUM(H35*0.08)+H35 -> 1.317384 | J28: =SUM(H35*0.08)+H35 -> 1.317384
B29: 0.65 | C29: =SUM(C35*0.12)+C35 -> 1.6269568 | D29: =SUM(C35*0.09)+C35 -> 1.5833776 | E29: XXX | G29: 4,75 Y 4.00 | H29: =SUM(H35*0.11)+H35 -> 1.353978 | I29: =SUM(H35*0.08+H35) -> 1.317384 | J29: =SUM(H35*0.08)+H35 -> 1.317384
B30: 24 | C30: =SUM(C35*0.16)+C35 -> 1.6850624 | D30: =SUM(C35*0.13)+C35 -> 1.6414832 | E30: XXX | G30: 6.35 | H30: =SUM(H35*0.11)+H35 -> 1.353978 | I30: =SUM(H35*0.08)+H35 -> 1.317384 | J30: =SUM(H35*0.08)+H35 -> 1.317384
B31: 26 | C31: =SUM(C35*0.2)+C35 -> 1.743168 | D31: =SUM(C35*0.15)+C35 -> 1.670536 | E31: XXX | G31: 8 | H31: =SUM(H35*0.11)+H35 -> 1.353978 | I31: =SUM(H35*0.08)+H35 -> 1.317384 | J31: =SUM(H35*0.08)+H35 -> 1.317384
B32: 27 | C32: =SUM(C35*0.26)+C35 -> 1.8303264 | D32: XXX | E32: XXX | G32: 9.52 | H32: =SUM(H35*0.12)+H35 -> 1.366176 | I32: =SUM(H35*0.09)+H35 -> 1.329582 | J32: =SUM(H35*0.09)+H35 -> 1.329582
B33: 30 | C33: =SUM(C35*0.32)+C35 -> 1.9174848 | D33: XXX | E33: XXX | G33: 12.7 | H33: =SUM(H35*0.12)+H35 -> 1.366176 | I33: =SUM(H35*0.09)+H35 -> 1.329582 | J33: =SUM(H35*0.09)+H35 -> 1.329582
B35: BASE | C35: =SUM(INICIO!J17) -> 1.45264 | G35: BASE | H35: =SUM(INICIO!P17) -> 1.2198
B37: 3.17 | C37: 1245 | D37: S/MEL | E37: =SUM(I28*0.1)+I28 -> 1.4491224 | I37: CALIDAD
B38: 4.75 | C38: 1500 | D38: S/MEL | E38: =SUM(J29*0.1)+J29 -> 1.4491224 | I38: ANCHO
B39: 6.35 | C39: 1500 | D39: S/MEL | E39: =SUM(J30*0.1)+J30 -> 1.4491224 | I39: ESPESOR
B43: galv | C43: 1000 | D43: 1220
B44: 12 | C44: 0 | D44: 1.4
B45: 16-14 | C45: =SUM(C55*0.07)+C55 -> 0 | D45: 1.422
B46: 18 | C46: 1.473 | D46: 1.43
B47: 20 | C47: =SUM(C55*0.08)+C55 -> 0 | D47: 1.463
B48: 22 | C48: =SUM(C57*0.07)+C57 -> 0 | D48: 1.48
B49: 25 | C49: =SUM(C57*0.08)+C57 -> 0 | D49: 1.492

Sheet 5
B2: CLIENTE: | D2: =PROPER(INICIO!D18) -> Pleg Hurlingham/Tasia/Lujan/San Nicolas/Mesquitq/Santodomingo
B4: LISTA DE PRECIOS EN PESOS
B5: DD | C5: 1000 | D5: 1220 | E5: 1500 | G5: NEGRA | H5: 1000 | I5: 1245 | J5: 1500
B6: 16 | C6: =SUM(C16*0.07)+C16 -> 2224.4331 | D6: =SUM(C16*0.04)+C16 -> 2162.0658 | E6: =SUM(C16*0.04)+C16 -> 2162.0658 | G6: 1.6 | H6: XXX | I6: XXX | J6: XXX
B7: 18 | C7: =SUM(C16*0.07)+C16 -> 2224.4331 | D7: =SUM(C16*0.04)+C16 -> 2162.0658 | E7: =SUM(C16*0.04)+C16 -> 2162.0658 | G7: 2 | H7: =SUM(H16*0.14)+H16 -> 2044.1408 | I7: =SUM(H16*0.11)+H16 -> 1990.3477 | J7: XXX
B8: 12,14 y 20 | C8: =SUM(C16*0.08)+C16 -> 2245.2222 | D8: =SUM(C16*0.05)+C16 -> 2182.8549 | E8: =SUM(C16*0.05)+C16 -> 2182.8549 | G8: 2.5 | H8: =SUM(H16*0.12)+H16 -> 2008.2787 | I8: =SUM(H16*0.09)+H16 -> 1954.4855 | J8: XXX
B9: 22 | C9: =SUM(C16*0.1)+C16 -> 2286.8004 | D9: =SUM(C16*0.07)+C16 -> 2224.4331 | E9: =SUM(C16*0.07)+C16 -> 2224.4331 | G9: 3.17 | H9: =SUM(H16*0.11)+H16 -> 1990.3477 | I9: =SUM(H16*0.08)+H16 -> 1936.5545 | J9: =SUM(H16*0.08)+H16 -> 1936.5545
B10: 0.65 | C10: =SUM(C16*0.12)+C16 -> 2328.3786 | D10: =SUM(C16*0.09)+C16 -> 2266.0113 | E10: XXX | G10: 4,75 Y 4.00 | H10: =SUM(H16*0.11)+H16 -> 1990.3477 | I10: =SUM(H16*0.08+H16) -> 1936.5545 | J10: =SUM(H16*0.07)+H16 -> 1918.6234
B11: 24 | C11: =SUM(C16*0.16)+C16 -> 2411.5349 | D11: =SUM(C16*0.13)+C16 -> 2349.1676 | E11: XXX | G11: 6.35 | H11: =SUM(H16*0.11)+H16 -> 1990.3477 | I11: =SUM(H16*0.08)+H16 -> 1936.5545 | J11: =SUM(H16*0.08)+H16 -> 1936.5545
B12: 26 | C12: =SUM(C16*0.2)+C16 -> 2494.6913 | D12: =SUM(C16*0.15)+C16 -> 2390.7458 | E12: XXX | G12: 8 | H12: =SUM(H16*0.11)+H16 -> 1990.3477 | I12: =SUM(H16*0.08)+H16 -> 1936.5545 | J12: =SUM(H16*0.08)+H16 -> 1936.5545
B13: 27 | C13: =SUM(C16*0.26)+C16 -> 2619.4259 | D13: XXX | E13: XXX | G13: 9.52 | H13: =SUM(H16*0.12)+H16 -> 2008.2787 | I13: =SUM(H16*0.09)+H16 -> 1954.4855 | J13: =SUM(H16*0.1)+H16 -> 1972.4166
B14: 30 | C14: =SUM(C16*0.32)+C16 -> 2744.1604 | D14: XXX | E14: XXX | G14: 12.7 | H14: =SUM(H16*0.12)+H16 -> 2008.2787 | I14: =SUM(H16*0.09)+H16 -> 1954.4855 | J14: =SUM(H16*0.1)+H16 -> 1972.4166
B16: BASE | C16: =SUM(INICIO!K18) -> 2078.9094 | G16: BASE | H16: =SUM(INICIO!Q18) -> 1793.106 | I16: mequi -8 | J16: pasc -11
J17: lujan -10
B18: 3.17 | C18: 1245 | D18: S/MEL | E18: =SUM(I9*0.1)+I9 -> 2130.2099 | I18: CALIDAD | J18: santo -10
B19: 4.75 | C19: 1500 | D19: S/MEL | E19: =SUM(J10*0.1)+J10 -> 2110.4858 | I19: ANCHO
B20: 6.35 | C20: 1500 | D20: S/MEL | E20: =SUM(J11*0.1)+J11 -> 2130.2099 | I20: ESPESOR
B23: LISTA DE PRECIOS EN DÓLARES
B24: DD | C24: 1000 | D24: 1220 | E24: 1500 | G24: NEGRA | H24: 1000 | I24: 1245 | J24: 1500
B25: 16 | C25: =SUM(C35*0.07)+C35 -> 1.4849353 | D25: =SUM(C35*0.04)+C35 -> 1.4433016 | E25: =SUM(C35*0.04)+C35 -> 1.4433016 | G25: 1.6 | H25: XXX | I25: XXX | J25: XXX
B26: 18 | C26: =SUM(C35*0.07)+C35 -> 1.4849353 | D26: =SUM(C35*0.04)+C35 -> 1.4433016 | E26: =SUM(C35*0.04)+C35 -> 1.4433016 | G26: 2 | H26: =SUM(H35*0.14)+H35 -> 1.36458 | I26: =SUM(H35*0.11)+H35 -> 1.32867 | J26: XXX
B27: 12,14 y 20 | C27: =SUM(C35*0.08)+C35 -> 1.4988132 | D27: =SUM(C35*0.05)+C35 -> 1.4571795 | E27: =SUM(C35*0.05)+C35 -> 1.4571795 | G27: 2.5 | H27: =SUM(H35*0.12)+H35 -> 1.34064 | I27: =SUM(H35*0.09)+H35 -> 1.30473 | J27: XXX
B28: 22 | C28: =SUM(C35*0.1)+C35 -> 1.526569 | D28: =SUM(C35*0.07)+C35 -> 1.4849353 | E28: =SUM(C35*0.07)+C35 -> 1.4849353 | G28: 3.17 | H28: =SUM(H35*0.11)+H35 -> 1.32867 | I28: =SUM(H35*0.08)+H35 -> 1.29276 | J28: =SUM(H35*0.08)+H35 -> 1.29276
B29: 0.65 | C29: =SUM(C35*0.12)+C35 -> 1.5543248 | D29: =SUM(C35*0.09)+C35 -> 1.5126911 | E29: XXX | G29: 4,75 Y 4.00 | H29: =SUM(H35*0.1)+H35 -> 1.3167 | I29: =SUM(H35*0.07+H35) -> 1.28079 | J29: =SUM(H35*0.07)+H35 -> 1.28079
B30: 24 | C30: =SUM(C35*0.16)+C35 -> 1.6098364 | D30: =SUM(C35*0.13)+C35 -> 1.5682027 | E30: XXX | G30: 6.35 | H30: =SUM(H35*0.11)+H35 -> 1.32867 | I30: =SUM(H35*0.08)+H35 -> 1.29276 | J30: =SUM(H35*0.08)+H35 -> 1.29276
B31: 26 | C31: =SUM(C35*0.2)+C35 -> 1.665348 | D31: =SUM(C35*0.15)+C35 -> 1.5959585 | E31: XXX | G31: 8 | H31: =SUM(H35*0.11)+H35 -> 1.32867 | I31: =SUM(H35*0.08)+H35 -> 1.29276 | J31: =SUM(H35*0.08)+H35 -> 1.29276
B32: 27 | C32: =SUM(C35*0.26)+C35 -> 1.7486154 | D32: XXX | E32: XXX | G32: 9.52 | H32: =SUM(H35*0.12)+H35 -> 1.34064 | I32: =SUM(H35*0.09)+H35 -> 1.30473 | J32: =SUM(H35*0.1)+H35 -> 1.3167
B33: 30 | C33: =SUM(C35*0.32)+C35 -> 1.8318828 | D33: XXX | E33: XXX | G33: 12.7 | H33: =SUM(H35*0.12)+H35 -> 1.34064 | I33: =SUM(H35*0.09)+H35 -> 1.30473 | J33: =SUM(H35*0.1)+H35 -> 1.3167
B35: BASE | C35: =SUM(INICIO!J18) -> 1.38779 | G35: BASE | H35: =SUM(INICIO!P18) -> 1.197
B37: 3.17 | C37: 1245 | D37: S/MEL | E37: =SUM(I28*0.1)+I28 -> 1.422036 | I37: CALIDAD
B38: 4.75 | C38: 1500 | D38: S/MEL | E38: =SUM(J29*0.1)+J29 -> 1.408869 | I38: ANCHO
B39: 6.35 | C39: 1500 | D39: S/MEL | E39: =SUM(J30*0.1)+J30 -> 1.422036 | I39: ESPESOR

Sheet 6
B2: CLIENTE: | D2: =PROPER(INICIO!D19) -> Oxpane Laser/Milsa/Viane
B4: LISTA DE PRECIOS EN PESOS
B5: DD | C5: 1000 | D5: 1220 | E5: 1500 | G5: NEGRA | H5: 1000 | I5: 1245 | J5: 1500
B6: 16 | C6: =SUM(C16*0.07)+C16 -> 2203.644 | D6: =SUM(C16*0.04)+C16 -> 2141.8596 | E6: =SUM(C16*0.04)+C16 -> 2141.8596 | G6: 1.6 | H6: XXX | I6: XXX | J6: XXX
B7: 18 | C7: =SUM(C16*0.07)+C16 -> 2203.644 | D7: =SUM(C16*0.04)+C16 -> 2141.8596 | E7: =SUM(C16*0.04)+C16 -> 2141.8596 | G7: 2 | H7: =SUM(H16*0.14)+H16 -> 1966.2688 | I7: =SUM(H16*0.11)+H16 -> 1914.5249 | J7: XXX
B8: 12,14 y 20 | C8: =SUM(C16*0.08)+C16 -> 2224.2388 | D8: =SUM(C16*0.05)+C16 -> 2162.4544 | E8: =SUM(C16*0.05)+C16 -> 2162.4544 | G8: 2.5 | H8: =SUM(H16*0.12)+H16 -> 1931.7729 | I8: =SUM(H16*0.09)+H16 -> 1880.0289 | J8: XXX
B9: 22 | C9: =SUM(C16*0.1)+C16 -> 2265.4284 | D9: =SUM(C16*0.07)+C16 -> 2203.644 | E9: =SUM(C16*0.07)+C16 -> 2203.644 | G9: 3.17 | H9: =SUM(H16*0.11)+H16 -> 1914.5249 | I9: =SUM(H16*0.08)+H16 -> 1862.781 | J9: =SUM(H16*0.08)+H16 -> 1862.781
B10: 0.65 | C10: =SUM(C16*0.12)+C16 -> 2306.618 | D10: =SUM(C16*0.09)+C16 -> 2244.8336 | E10: XXX | G10: 4,75 Y 4.00 | H10: =SUM(H16*0.11)+H16 -> 1914.5249 | I10: =SUM(H16*0.08+H16) -> 1862.781 | J10: =SUM(H16*0.08)+H16 -> 1862.781
B11: 24 | C11: =SUM(C16*0.16)+C16 -> 2388.9972 | D11: =SUM(C16*0.13)+C16 -> 2327.2128 | E11: XXX | G11: 6.35 | H11: =SUM(H16*0.11)+H16 -> 1914.5249 | I11: =SUM(H16*0.08)+H16 -> 1862.781 | J11: =SUM(H16*0.08)+H16 -> 1862.781
B12: 26 | C12: =SUM(C16*0.2)+C16 -> 2471.3764 | D12: =SUM(C16*0.15)+C16 -> 2368.4024 | E12: XXX | G12: 8 | H12: =SUM(H16*0.11)+H16 -> 1914.5249 | I12: =SUM(H16*0.08)+H16 -> 1862.781 | J12: =SUM(H16*0.08)+H16 -> 1862.781
B13: 27 | C13: =SUM(C16*0.26)+C16 -> 2594.9453 | D13: XXX | E13: XXX | G13: 9.52 | H13: =SUM(H16*0.12)+H16 -> 1931.7729 | I13: =SUM(H16*0.09)+H16 -> 1880.0289 | J13: =SUM(H16*0.09)+H16 -> 1880.0289
B14: 30 | C14: =SUM(C16*0.32)+C16 -> 2718.5141 | D14: XXX | E14: XXX | G14: 12.7 | H14: =SUM(H16*0.12)+H16 -> 1931.7729 | I14: =SUM(H16*0.09)+H16 -> 1880.0289 | J14: =SUM(H16*0.09)+H16 -> 1880.0289
B16: BASE | C16: =SUM(INICIO!K19) -> 2059.4804 | G16: BASE | H16: =SUM(INICIO!Q19) -> 1724.7972 | J16: decapada 8,5
J17: oxp-11% | K17: angosta 915
B18: 3.17 | C18: 1245 | D18: S/MEL | E18: =SUM(I9*0.1)+I9 -> 2049.0591 | I18: CALIDAD | J18: milsa -8
B19: 4.75 | C19: 1500 | D19: S/MEL | E19: =SUM(J10*0.1)+J10 -> 2049.0591 | I19: ANCHO | J19: viane
B20: 6.35 | C20: 1500 | D20: S/MEL | E20: =SUM(J11*0.1)+J11 -> 2049.0591 | I20: ESPESOR
B23: LISTA DE PRECIOS EN DÓLARES
B24: DD | C24: 1000 | D24: 1220 | E24: 1500 | G24: NEGRA | H24: 1000 | I24: 1245 | J24: 1500
B25: 16 | C25: =SUM(C35*0.07)+C35 -> 1.4710574 | D25: =SUM(C35*0.04)+C35 -> 1.4298128 | E25: =SUM(C35*0.04)+C35 -> 1.4298128 | G25: 1.6 | H25: XXX | I25: XXX | J25: XXX
B26: 18 | C26: =SUM(C35*0.07)+C35 -> 1.4710574 | D26: =SUM(C35*0.04)+C35 -> 1.4298128 | E26: =SUM(C35*0.04)+C35 -> 1.4298128 | G26: 2 | H26: =SUM(H35*0.14)+H35 -> 1.312596 | I26: =SUM(H35*0.11)+H35 -> 1.278054 | J26: XXX
B27: 12,14 y 20 | C27: =SUM(C35*0.08)+C35 -> 1.4848056 | D27: =SUM(C35*0.05)+C35 -> 1.443561 | E27: =SUM(C35*0.05)+C35 -> 1.443561 | G27: 2.5 | H27: =SUM(H35*0.12)+H35 -> 1.289568 | I27: =SUM(H35*0.09)+H35 -> 1.255026 | J27: XXX
B28: 22 | C28: =SUM(C35*0.1)+C35 -> 1.512302 | D28: =SUM(C35*0.07)+C35 -> 1.4710574 | E28: =SUM(C35*0.07)+C35 -> 1.4710574 | G28: 3.17 | H28: =SUM(H35*0.11)+H35 -> 1.278054 | I28: =SUM(H35*0.08)+H35 -> 1.243512 | J28: =SUM(H35*0.08)+H35 -> 1.243512
B29: 0.65 | C29: =SUM(C35*0.12)+C35 -> 1.5397984 | D29: =SUM(C35*0.09)+C35 -> 1.4985538 | E29: XXX | G29: 4,75 Y 4.00 | H29: =SUM(H35*0.1)+H35 -> 1.26654 | I29: =SUM(H35*0.07+H35) -> 1.231998 | J29: =SUM(H35*0.07)+H35 -> 1.231998
B30: 24 | C30: =SUM(C35*0.16)+C35 -> 1.5947912 | D30: =SUM(C35*0.13)+C35 -> 1.5535466 | E30: XXX | G30: 6.35 | H30: =SUM(H35*0.11)+H35 -> 1.278054 | I30: =SUM(H35*0.08)+H35 -> 1.243512 | J30: =SUM(H35*0.08)+H35 -> 1.243512
B31: 26 | C31: =SUM(C35*0.2)+C35 -> 1.649784 | D31: =SUM(C35*0.15)+C35 -> 1.581043 | E31: XXX | G31: 8 | H31: =SUM(H35*0.11)+H35 -> 1.278054 | I31: =SUM(H35*0.08)+H35 -> 1.243512 | J31: =SUM(H35*0.08)+H35 -> 1.243512
B32: 27 | C32: =SUM(C35*0.26)+C35 -> 1.7322732 | D32: XXX | E32: XXX | G32: 9.52 | H32: =SUM(H35*0.12)+H35 -> 1.289568 | I32: =SUM(H35*0.09)+H35 -> 1.255026 | J32: =SUM(H35*0.09)+H35 -> 1.255026
B33: 30 | C33: =SUM(C35*0.32)+C35 -> 1.8147624 | D33: XXX | E33: XXX | G33: 12.7 | H33: =SUM(H35*0.12)+H35 -> 1.289568 | I33: =SUM(H35*0.09)+H35 -> 1.255026 | J33: =SUM(H35*0.09)+H35 -> 1.255026
B35: BASE | C35: =SUM(INICIO!J19) -> 1.37482 | G35: BASE | H35: =SUM(INICIO!P19) -> 1.1514
B37: 3.17 | C37: 1245 | D37: S/MEL | E37: =SUM(I28*0.1)+I28 -> 1.3678632 | I37: CALIDAD
B38: 4.75 | C38: 1500 | D38: S/MEL | E38: =SUM(J29*0.1)+J29 -> 1.3551978 | I38: ANCHO
B39: 6.35 | C39: 1500 | D39: S/MEL | E39: =SUM(J30*0.1)+J30 -> 1.3678632 | I39: ESPESOR

Sheet 8
B2: CLIENTE: | D2: =PROPER(INICIO!D21) -> Cormot/Geluma/Merigui/Lumak
B4: LISTA DE PRECIOS EN PESOS
B5: DD | C5: 1000 | D5: 1220 | E5: 1500 | G5: NEGRA | H5: 1000 | I5: 1245 | J5: 1500
B6: 16 | C6: =SUM(C16*0.07)+C16 -> 2328.3786 | D6: =SUM(C16*0.04)+C16 -> 2263.0969 | E6: =SUM(C16*0.04)+C16 -> 2263.0969 | G6: 1.6 | H6: XXX | I6: XXX | J6: XXX
B7: 18 | C7: =SUM(C16*0.07)+C16 -> 2328.3786 | D7: =SUM(C16*0.04)+C16 -> 2263.0969 | E7: =SUM(C16*0.04)+C16 -> 2263.0969 | G7: 2 | H7: =SUM(H16*0.14)+H16 -> 2122.0129 | I7: =SUM(H16*0.11)+H16 -> 2066.1704 | J7: XXX
B8: 12,14 y 20 | C8: =SUM(C16*0.08)+C16 -> 2350.1391 | D8: =SUM(C16*0.05)+C16 -> 2284.8575 | E8: =SUM(C16*0.05)+C16 -> 2284.8575 | G8: 2.5 | H8: =SUM(H16*0.12)+H16 -> 2084.7846 | I8: =SUM(H16*0.09)+H16 -> 2028.9421 | J8: XXX
B9: 22 | C9: =SUM(C16*0.1)+C16 -> 2393.6602 | D9: =SUM(C16*0.07)+C16 -> 2328.3786 | E9: =SUM(C16*0.07)+C16 -> 2328.3786 | G9: 3.17 | H9: =SUM(H16*0.11)+H16 -> 2066.1704 | I9: =SUM(H16*0.08)+H16 -> 2010.328 | J9: =SUM(H16*0.08)+H16 -> 2010.328
B10: 0.65 | C10: =SUM(C16*0.12)+C16 -> 2437.1813 | D10: =SUM(C16*0.09)+C16 -> 2371.8996 | E10: XXX | G10: 4,75 Y 4.00 | H10: =SUM(H16*0.1)+H16 -> 2047.5563 | I10: =SUM(H16*0.07+H16) -> 1991.7138 | J10: =SUM(H16*0.07)+H16 -> 1991.7138
B11: 24 | C11: =SUM(C16*0.16)+C16 -> 2524.2235 | D11: =SUM(C16*0.13)+C16 -> 2458.9418 | E11: XXX | G11: 6.35 | H11: =SUM(H16*0.11)+H16 -> 2066.1704 | I11: =SUM(H16*0.08)+H16 -> 2010.328 | J11: =SUM(H16*0.08)+H16 -> 2010.328
B12: 26 | C12: =SUM(C16*0.2)+C16 -> 2611.2657 | D12: =SUM(C16*0.15)+C16 -> 2502.4629 | E12: XXX | G12: 8 | H12: =SUM(H16*0.11)+H16 -> 2066.1704 | I12: =SUM(H16*0.08)+H16 -> 2010.328 | J12: =SUM(H16*0.08)+H16 -> 2010.328
B13: 27 | C13: =SUM(C16*0.26)+C16 -> 2741.8289 | D13: XXX | E13: XXX | G13: 9.52 | H13: =SUM(H16*0.12)+H16 -> 2084.7846 | I13: =SUM(H16*0.09)+H16 -> 2028.9421 | J13: =SUM(H16*0.1)+H16 -> 2047.5563
B14: 30 | C14: =SUM(C16*0.32)+C16 -> 2872.3922 | D14: XXX | E14: XXX | G14: 12.7 | H14: =SUM(H16*0.12)+H16 -> 2084.7846 | I14: =SUM(H16*0.09)+H16 -> 2028.9421 | J14: =SUM(H16*0.1)+H16 -> 2047.5563
B16: BASE | C16: =SUM(INICIO!K21) -> 2176.0547 | G16: BASE | H16: =SUM(INICIO!Q21) -> 1861.4148 | J16: cormot -5
B18: 3.17 | C18: 1245 | D18: S/MEL | E18: =SUM(I9*0.1)+I9 -> 2211.3608 | I18: CALIDAD
B19: 4.75 | C19: 1500 | D19: S/MEL | E19: =SUM(J10*0.1)+J10 -> 2190.8852 | I19: ANCHO
B20: 6.35 | C20: 1500 | D20: S/MEL | E20: =SUM(J11*0.1)+J11 -> 2211.3608 | I20: ESPESOR
B23: LISTA DE PRECIOS EN DÓLARES
B24: DD | C24: 1000 | D24: 1220 | E24: 1500 | G24: NEGRA | H24: 1000 | I24: 1245 | J24: 1500
B25: 16 | C25: =SUM(C35*0.07)+C35 -> 1.5543248 | D25: =SUM(C35*0.04)+C35 -> 1.5107456 | E25: =SUM(C35*0.04)+C35 -> 1.5107456 | G25: 1.6 | H25: XXX | I25: XXX | J25: XXX
B26: 18 | C26: =SUM(C35*0.07)+C35 -> 1.5543248 | D26: =SUM(C35*0.04)+C35 -> 1.5107456 | E26: =SUM(C35*0.04)+C35 -> 1.5107456 | G26: 2 | H26: =SUM(H35*0.14)+H35 -> 1.416564 | I26: =SUM(H35*0.11)+H35 -> 1.379286 | J26: XXX
B27: 12,14 y 20 | C27: =SUM(C35*0.08)+C35 -> 1.5688512 | D27: =SUM(C35*0.05)+C35 -> 1.525272 | E27: =SUM(C35*0.05)+C35 -> 1.525272 | G27: 2.5 | H27: =SUM(H35*0.12)+H35 -> 1.391712 | I27: =SUM(H35*0.09)+H35 -> 1.354434 | J27: XXX
B28: 22 | C28: =SUM(C35*0.1)+C35 -> 1.597904 | D28: =SUM(C35*0.07)+C35 -> 1.5543248 | E28: =SUM(C35*0.07)+C35 -> 1.5543248 | G28: 3.17 | H28: =SUM(H35*0.11)+H35 -> 1.379286 | I28: =SUM(H35*0.08)+H35 -> 1.342008 | J28: =SUM(H35*0.08)+H35 -> 1.342008
B29: 0.65 | C29: =SUM(C35*0.12)+C35 -> 1.6269568 | D29: =SUM(C35*0.09)+C35 -> 1.5833776 | E29: XXX | G29: 4,75 Y 4.00 | H29: =SUM(H35*0.1)+H35 -> 1.36686 | I29: =SUM(H35*0.07+H35) -> 1.329582 | J29: =SUM(H35*0.07)+H35 -> 1.329582
B30: 24 | C30: =SUM(C35*0.16)+C35 -> 1.6850624 | D30: =SUM(C35*0.13)+C35 -> 1.6414832 | E30: XXX | G30: 6.35 | H30: =SUM(H35*0.11)+H35 -> 1.379286 | I30: =SUM(H35*0.08)+H35 -> 1.342008 | J30: =SUM(H35*0.08)+H35 -> 1.342008
B31: 26 | C31: =SUM(C35*0.2)+C35 -> 1.743168 | D31: =SUM(C35*0.15)+C35 -> 1.670536 | E31: XXX | G31: 8 | H31: =SUM(H35*0.11)+H35 -> 1.379286 | I31: =SUM(H35*0.08)+H35 -> 1.342008 | J31: =SUM(H35*0.08)+H35 -> 1.342008
B32: 27 | C32: =SUM(C35*0.26)+C35 -> 1.8303264 | D32: XXX | E32: XXX | G32: 9.52 | H32: =SUM(H35*0.12)+H35 -> 1.391712 | I32: =SUM(H35*0.09)+H35 -> 1.354434 | J32: =SUM(H35*0.1)+H35 -> 1.36686
B33: 30 | C33: =SUM(C35*0.32)+C35 -> 1.9174848 | D33: XXX | E33: XXX | G33: 12.7 | H33: =SUM(H35*0.12)+H35 -> 1.391712 | I33: =SUM(H35*0.09)+H35 -> 1.354434 | J33: =SUM(H35*0.1)+H35 -> 1.36686
B35: BASE | C35: =SUM(INICIO!J21) -> 1.45264 | G35: BASE | H35: =SUM(INICIO!P21) -> 1.2426 | I35: sae 1045 | J35: 1.4
B37: 3.17 | C37: 1245 | D37: S/MEL | E37: =SUM(I28*0.1)+I28 -> 1.4762088 | I37: CALIDAD
B38: 4.75 | C38: 1500 | D38: S/MEL | E38: =SUM(J29*0.1)+J29 -> 1.4625402 | I38: ANCHO
B39: 6.35 | C39: 1500 | D39: S/MEL | E39: =SUM(J30*0.1)+J30 -> 1.4762088 | I39: ESPESOR

Sheet 7
B2: CLIENTE: | D2: =PROPER(INICIO!D20) -> Gor Gras/Rase/Calcor/Fabrica De Luz/Forjan/Lagos
B4: LISTA DE PRECIOS EN PESOS
B5: DD | C5: 1000 | D5: 1220 | E5: 1500 | G5: NEGRA | H5: 1000 | I5: 1245 | J5: 1500
B6: 16 | C6: =SUM(C16*0.07)+C16 -> 2349.1676 | D6: =SUM(C16*0.04)+C16 -> 2283.3031 | E6: =SUM(C16*0.04)+C16 -> 2283.3031 | G6: 1.6 | H6: XXX | I6: XXX | J6: XXX
B7: 18 | C7: =SUM(C16*0.07)+C16 -> 2349.1676 | D7: =SUM(C16*0.04)+C16 -> 2283.3031 | E7: =SUM(C16*0.04)+C16 -> 2283.3031 | G7: 2 | H7: =SUM(H16*0.14)+H16 -> 2122.0129 | I7: =SUM(H16*0.11)+H16 -> 2066.1704 | J7: XXX
B8: 12,14 y 20 | C8: =SUM(C16*0.08)+C16 -> 2371.1225 | D8: =SUM(C16*0.05)+C16 -> 2305.258 | E8: =SUM(C16*0.05)+C16 -> 2305.258 | G8: 2.5 | H8: =SUM(H16*0.12)+H16 -> 2084.7846 | I8: =SUM(H16*0.09)+H16 -> 2028.9421 | J8: XXX
B9: 22 | C9: =SUM(C16*0.1)+C16 -> 2415.0322 | D9: =SUM(C16*0.07)+C16 -> 2349.1676 | E9: =SUM(C16*0.07)+C16 -> 2349.1676 | G9: 3.17 | H9: =SUM(H16*0.11)+H16 -> 2066.1704 | I9: =SUM(H16*0.08)+H16 -> 2010.328 | J9: =SUM(H16*0.08)+H16 -> 2010.328
B10: 0.65 | C10: =SUM(C16*0.12)+C16 -> 2458.9418 | D10: =SUM(C16*0.09)+C16 -> 2393.0773 | E10: XXX | G10: 4,75 Y 4.00 | H10: =SUM(H16*0.1)+H16 -> 2047.5563 | I10: =SUM(H16*0.07+H16) -> 1991.7138 | J10: =SUM(H16*0.07)+H16 -> 1991.7138
B11: 24 | C11: =SUM(C16*0.16)+C16 -> 2546.7612 | D11: =SUM(C16*0.13)+C16 -> 2480.8967 | E11: XXX | G11: 6.35 | H11: =SUM(H16*0.11)+H16 -> 2066.1704 | I11: =SUM(H16*0.08)+H16 -> 2010.328 | J11: =SUM(H16*0.08)+H16 -> 2010.328
B12: 26 | C12: =SUM(C16*0.2)+C16 -> 2634.5805 | D12: =SUM(C16*0.15)+C16 -> 2524.8063 | E12: XXX | G12: 8 | H12: =SUM(H16*0.11)+H16 -> 2066.1704 | I12: =SUM(H16*0.08)+H16 -> 2010.328 | J12: =SUM(H16*0.08)+H16 -> 2010.328
B13: 27 | C13: =SUM(C16*0.26)+C16 -> 2766.3096 | D13: XXX | E13: XXX | G13: 9.52 | H13: =SUM(H16*0.12)+H16 -> 2084.7846 | I13: =SUM(H16*0.09)+H16 -> 2028.9421 | J13: =SUM(H16*0.09)+H16 -> 2028.9421
B14: 30 | C14: =SUM(C16*0.32)+C16 -> 2898.0386 | D14: XXX | E14: XXX | G14: 12.7 | H14: =SUM(H16*0.12)+H16 -> 2084.7846 | I14: =SUM(H16*0.09)+H16 -> 2028.9421 | J14: =SUM(H16*0.09)+H16 -> 2028.9421
B16: BASE | C16: =SUM(INICIO!K20) -> 2195.4838 | G16: BASE | H16: =SUM(INICIO!Q20) -> 1861.4148 | J16: -0.1
B18: 3.17 | C18: 1245 | D18: S/MEL | E18: =SUM(I9*0.1)+I9 -> 2211.3608 | I18: CALIDAD
B19: 4.75 | C19: 1500 | D19: S/MEL | E19: =SUM(J10*0.1)+J10 -> 2190.8852 | I19: ANCHO
B20: 6.35 | C20: 1500 | D20: S/MEL | E20: =SUM(J11*0.1)+J11 -> 2211.3608 | I20: ESPESOR
B24: LISTA DE PRECIOS EN DÓLARES
B25: DD | C25: 1000 | D25: 1220 | E25: 1500 | G25: NEGRA | H25: 1000 | I25: 1245 | J25: 1500
B26: 16 | C26: =SUM(C36*0.07)+C36 -> 1.5682027 | D26: =SUM(C36*0.04)+C36 -> 1.5242344 | E26: =SUM(C36*0.04)+C36 -> 1.5242344 | G26: 1.6 | H26: XXX | I26: XXX | J26: XXX
B27: 18 | C27: =SUM(C36*0.07)+C36 -> 1.5682027 | D27: =SUM(C36*0.04)+C36 -> 1.5242344 | E27: =SUM(C36*0.04)+C36 -> 1.5242344 | G27: 2 | H27: =SUM(H36*0.14)+H36 -> 1.416564 | I27: =SUM(H36*0.11)+H36 -> 1.379286 | J27: XXX
B28: 12,14 y 20 | C28: =SUM(C36*0.08)+C36 -> 1.5828588 | D28: =SUM(C36*0.05)+C36 -> 1.5388905 | E28: =SUM(C36*0.05)+C36 -> 1.5388905 | G28: 2.5 | H28: =SUM(H36*0.12)+H36 -> 1.391712 | I28: =SUM(H36*0.09)+H36 -> 1.354434 | J28: XXX
B29: 22 | C29: =SUM(C36*0.1)+C36 -> 1.612171 | D29: =SUM(C36*0.07)+C36 -> 1.5682027 | E29: =SUM(C36*0.07)+C36 -> 1.5682027 | G29: 3.17 | H29: =SUM(H36*0.11)+H36 -> 1.379286 | I29: =SUM(H36*0.08)+H36 -> 1.342008 | J29: =SUM(H36*0.08)+H36 -> 1.342008
B30: 0.65 | C30: =SUM(C36*0.12)+C36 -> 1.6414832 | D30: =SUM(C36*0.09)+C36 -> 1.5975149 | E30: XXX | G30: 4,75 Y 4.00 | H30: =SUM(H36*0.1)+H36 -> 1.36686 | I30: =SUM(H36*0.07+H36) -> 1.329582 | J30: =SUM(H36*0.07)+H36 -> 1.329582
B31: 24 | C31: =SUM(C36*0.16)+C36 -> 1.7001076 | D31: =SUM(C36*0.13)+C36 -> 1.6561393 | E31: XXX | G31: 6.35 | H31: =SUM(H36*0.11)+H36 -> 1.379286 | I31: =SUM(H36*0.08)+H36 -> 1.342008 | J31: =SUM(H36*0.08)+H36 -> 1.342008
B32: 26 | C32: =SUM(C36*0.2)+C36 -> 1.758732 | D32: =SUM(C36*0.15)+C36 -> 1.6854515 | E32: XXX | G32: 8 | H32: =SUM(H36*0.11)+H36 -> 1.379286 | I32: =SUM(H36*0.08)+H36 -> 1.342008 | J32: =SUM(H36*0.08)+H36 -> 1.342008
B33: 27 | C33: =SUM(C36*0.26)+C36 -> 1.8466686 | D33: XXX | E33: XXX | G33: 9.52 | H33: =SUM(H36*0.12)+H36 -> 1.391712 | I33: =SUM(H36*0.09)+H36 -> 1.354434 | J33: =SUM(H36*0.09)+H36 -> 1.354434
B34: 30 | C34: =SUM(C36*0.32)+C36 -> 1.9346052 | D34: XXX | E34: XXX | G34: 12.7 | H34: =SUM(H36*0.12)+H36 -> 1.391712 | I34: =SUM(H36*0.09)+H36 -> 1.354434 | J34: =SUM(H36*0.09)+H36 -> 1.354434
B36: BASE | C36: =SUM(INICIO!J20) -> 1.46561 | G36: BASE | H36: =SUM(INICIO!P20) -> 1.2426
B38: 3.17 | C38: 1245 | D38: S/MEL | E38: =SUM(I29*0.1)+I29 -> 1.4762088 | I38: CALIDAD
B39: 4.75 | C39: 1500 | D39: S/MEL | E39: =SUM(J30*0.1)+J30 -> 1.4625402 | I39: ANCHO
B40: 6.35 | C40: 1500 | D40: S/MEL | E40: =SUM(J31*0.1)+J31 -> 1.4762088 | I40: ESPESOR

Sheet 9
B2: CLIENTE: | D2: =PROPER(INICIO!D22) -> Int Pomp/Gustavo Carrocero
B4: LISTA DE PRECIOS EN PESOS
B5: DD | C5: 1000 | D5: 1220 | E5: 1500 | G5: NEGRA | H5: 1000 | I5: 1245 | J5: 1500
B6: 16 | C6: =SUM(C16*0.07)+C16 -> 2328.3786 | D6: =SUM(C16*0.04)+C16 -> 2263.0969 | E6: =SUM(C16*0.04)+C16 -> 2263.0969 | G6: 1.6 | H6: XXX | I6: XXX | J6: XXX
B7: 18 | C7: =SUM(C16*0.07)+C16 -> 2328.3786 | D7: =SUM(C16*0.04)+C16 -> 2263.0969 | E7: =SUM(C16*0.04)+C16 -> 2263.0969 | G7: 2 | H7: =SUM(H16*0.14)+H16 -> 2102.5449 | I7: =SUM(H16*0.11)+H16 -> 2047.2147 | J7: XXX
B8: 12,14 y 20 | C8: =SUM(C16*0.08)+C16 -> 2350.1391 | D8: =SUM(C16*0.05)+C16 -> 2284.8575 | E8: =SUM(C16*0.05)+C16 -> 2284.8575 | G8: 2.5 | H8: =SUM(H16*0.12)+H16 -> 2065.6581 | I8: =SUM(H16*0.09)+H16 -> 2010.328 | J8: XXX
B9: 22 | C9: =SUM(C16*0.1)+C16 -> 2393.6602 | D9: =SUM(C16*0.07)+C16 -> 2328.3786 | E9: =SUM(C16*0.07)+C16 -> 2328.3786 | G9: 3.17 | H9: =SUM(H16*0.11)+H16 -> 2047.2147 | I9: =SUM(H16*0.08)+H16 -> 1991.8846 | J9: =SUM(H16*0.08)+H16 -> 1991.8846
B10: 0.65 | C10: =SUM(C16*0.12)+C16 -> 2437.1813 | D10: =SUM(C16*0.09)+C16 -> 2371.8996 | E10: XXX | G10: 4,75 Y 4.00 | H10: =SUM(H16*0.1)+H16 -> 2028.7714 | I10: =SUM(H16*0.07+H16) -> 1973.4412 | J10: =SUM(H16*0.07)+H16 -> 1973.4412
B11: 24 | C11: =SUM(C16*0.16)+C16 -> 2524.2235 | D11: =SUM(C16*0.13)+C16 -> 2458.9418 | E11: XXX | G11: 6.35 | H11: =SUM(H16*0.11)+H16 -> 2047.2147 | I11: =SUM(H16*0.08)+H16 -> 1991.8846 | J11: =SUM(H16*0.08)+H16 -> 1991.8846
B12: 26 | C12: =SUM(C16*0.2)+C16 -> 2611.2657 | D12: =SUM(C16*0.15)+C16 -> 2502.4629 | E12: XXX | G12: 8 | H12: =SUM(H16*0.11)+H16 -> 2047.2147 | I12: =SUM(H16*0.08)+H16 -> 1991.8846 | J12: =SUM(H16*0.08)+H16 -> 1991.8846
B13: 27 | C13: =SUM(C16*0.26)+C16 -> 2741.8289 | D13: XXX | E13: XXX | G13: 9.52 | H13: =SUM(H16*0.12)+H16 -> 2065.6581 | I13: =SUM(H16*0.09)+H16 -> 2010.328 | J13: =SUM(H16*0.1)+H16 -> 2028.7714
B14: 30 | C14: =SUM(C16*0.32)+C16 -> 2872.3922 | D14: XXX | E14: XXX | G14: 12.7 | H14: =SUM(H16*0.12)+H16 -> 2065.6581 | I14: =SUM(H16*0.09)+H16 -> 2010.328 | J14: =SUM(H16*0.1)+H16 -> 2028.7714
B16: BASE | C16: =SUM(INICIO!K22) -> 2176.0547 | G16: BASE | H16: =SUM(INICIO!Q22) -> 1844.3376 | I16: DEC
B18: 3.17 | C18: 1245 | D18: S/MEL | E18: =SUM(I9*0.1)+I9 -> 2191.0731 | I18: CALIDAD
B19: 4.75 | C19: 1500 | D19: S/MEL | E19: =SUM(J10*0.1)+J10 -> 2170.7854 | I19: ANCHO
B20: 6.35 | C20: 1500 | D20: S/MEL | E20: =SUM(J11*0.1)+J11 -> 2191.0731 | I20: ESPESOR
B22: LISTA DE PRECIOS EN DÓLARES
B23: DD | C23: 1000 | D23: 1220 | E23: 1500 | G23: NEGRA | H23: 1000 | I23: 1245 | J23: 1500
B24: 16 | C24: =SUM(C34*0.07)+C34 -> 1.5543248 | D24: =SUM(C34*0.04)+C34 -> 1.5107456 | E24: =SUM(C34*0.04)+C34 -> 1.5107456 | G24: 1.6 | H24: XXX | I24: XXX | J24: XXX
B25: 18 | C25: =SUM(C34*0.07)+C34 -> 1.5543248 | D25: =SUM(C34*0.04)+C34 -> 1.5107456 | E25: =SUM(C34*0.04)+C34 -> 1.5107456 | G25: 2 | H25: =SUM(H34*0.14)+H34 -> 1.403568 | I25: =SUM(H34*0.11)+H34 -> 1.366632 | J25: XXX
B26: 12,14 y 20 | C26: =SUM(C34*0.08)+C34 -> 1.5688512 | D26: =SUM(C34*0.05)+C34 -> 1.525272 | E26: =SUM(C34*0.05)+C34 -> 1.525272 | G26: 2.5 | H26: =SUM(H34*0.12)+H34 -> 1.378944 | I26: =SUM(H34*0.09)+H34 -> 1.342008 | J26: XXX
B27: 22 | C27: =SUM(C34*0.1)+C34 -> 1.597904 | D27: =SUM(C34*0.07)+C34 -> 1.5543248 | E27: =SUM(C34*0.07)+C34 -> 1.5543248 | G27: 3.17 | H27: =SUM(H34*0.11)+H34 -> 1.366632 | I27: =SUM(H34*0.08)+H34 -> 1.329696 | J27: =SUM(H34*0.08)+H34 -> 1.329696
B28: 0.65 | C28: =SUM(C34*0.12)+C34 -> 1.6269568 | D28: =SUM(C34*0.09)+C34 -> 1.5833776 | E28: XXX | G28: 4,75 Y 4.00 | H28: =SUM(H34*0.1)+H34 -> 1.35432 | I28: =SUM(H34*0.07+H34) -> 1.317384 | J28: =SUM(H34*0.07)+H34 -> 1.317384
B29: 24 | C29: =SUM(C34*0.16)+C34 -> 1.6850624 | D29: =SUM(C34*0.13)+C34 -> 1.6414832 | E29: XXX | G29: 6.35 | H29: =SUM(H34*0.11)+H34 -> 1.366632 | I29: =SUM(H34*0.08)+H34 -> 1.329696 | J29: =SUM(H34*0.08)+H34 -> 1.329696
B30: 26 | C30: =SUM(C34*0.2)+C34 -> 1.743168 | D30: =SUM(C34*0.15)+C34 -> 1.670536 | E30: XXX | G30: 8 | H30: =SUM(H34*0.11)+H34 -> 1.366632 | I30: =SUM(H34*0.08)+H34 -> 1.329696 | J30: =SUM(H34*0.08)+H34 -> 1.329696
B31: 27 | C31: =SUM(C34*0.26)+C34 -> 1.8303264 | D31: XXX | E31: XXX | G31: 9.52 | H31: =SUM(H34*0.12)+H34 -> 1.378944 | I31: =SUM(H34*0.09)+H34 -> 1.342008 | J31: =SUM(H34*0.1)+H34 -> 1.35432
B32: 30 | C32: =SUM(C34*0.32)+C34 -> 1.9174848 | D32: XXX | E32: XXX | G32: 12.7 | H32: =SUM(H34*0.12)+H34 -> 1.378944 | I32: =SUM(H34*0.09)+H34 -> 1.342008 | J32: =SUM(H34*0.1)+H34 -> 1.35432
B34: BASE | C34: =SUM(INICIO!J22) -> 1.45264 | G34: BASE | H34: =SUM(INICIO!P22) -> 1.2312
B36: 3.17 | C36: 1245 | D36: S/MEL | E36: =SUM(I27*0.1)+I27 -> 1.4626656 | I36: CALIDAD
B37: 4.75 | C37: 1500 | D37: S/MEL | E37: =SUM(J28*0.1)+J28 -> 1.4491224 | I37: ANCHO
B38: 6.35 | C38: 1500 | D38: S/MEL | E38: =SUM(J29*0.1)+J29 -> 1.4626656 | I38: ESPESOR

Sheet 10
B2: CLIENTE: | D2: =PROPER(INICIO!D23) -> Di Lorenzo/Alico
B4: LISTA DE PRECIOS EN PESOS
B5: DD | C5: 1000 | D5: 1220 | E5: 1500 | G5: NEGRA | H5: 1000 | I5: 1245 | J5: 1500
B6: 16 | C6: =SUM(C16*0.07)+C16 -> 2328.3786 | D6: =SUM(C16*0.04)+C16 -> 2263.0969 | E6: =SUM(C16*0.04)+C16 -> 2263.0969 | G6: 1.6 | H6: XXX | I6: XXX | J6: XXX
B7: 18 | C7: =SUM(C16*0.07)+C16 -> 2328.3786 | D7: =SUM(C16*0.04)+C16 -> 2263.0969 | E7: =SUM(C16*0.04)+C16 -> 2263.0969 | G7: 2 | H7: =SUM(H16*0.14)+H16 -> 2122.0129 | I7: =SUM(H16*0.11)+H16 -> 2066.1704 | J7: XXX
B8: 12,14 y 20 | C8: =SUM(C16*0.08)+C16 -> 2350.1391 | D8: =SUM(C16*0.05)+C16 -> 2284.8575 | E8: =SUM(C16*0.05)+C16 -> 2284.8575 | G8: 2.5 | H8: =SUM(H16*0.12)+H16 -> 2084.7846 | I8: =SUM(H16*0.09)+H16 -> 2028.9421 | J8: XXX
B9: 22 | C9: =SUM(C16*0.1)+C16 -> 2393.6602 | D9: =SUM(C16*0.07)+C16 -> 2328.3786 | E9: =SUM(C16*0.07)+C16 -> 2328.3786 | G9: 3.17 | H9: =SUM(H16*0.11)+H16 -> 2066.1704 | I9: =SUM(H16*0.08)+H16 -> 2010.328 | J9: =SUM(H16*0.08)+H16 -> 2010.328
B10: 0.65 | C10: =SUM(C16*0.12)+C16 -> 2437.1813 | D10: =SUM(C16*0.09)+C16 -> 2371.8996 | E10: XXX | G10: 4,75 Y 4.00 | H10: =SUM(H16*0.1)+H16 -> 2047.5563 | I10: =SUM(H16*0.07+H16) -> 1991.7138 | J10: =SUM(H16*0.07)+H16 -> 1991.7138
B11: 24 | C11: =SUM(C16*0.16)+C16 -> 2524.2235 | D11: =SUM(C16*0.13)+C16 -> 2458.9418 | E11: XXX | G11: 6.35 | H11: =SUM(H16*0.11)+H16 -> 2066.1704 | I11: =SUM(H16*0.08)+H16 -> 2010.328 | J11: =SUM(H16*0.08)+H16 -> 2010.328
B12: 26 | C12: =SUM(C16*0.2)+C16 -> 2611.2657 | D12: =SUM(C16*0.15)+C16 -> 2502.4629 | E12: XXX | G12: 8 | H12: =SUM(H16*0.11)+H16 -> 2066.1704 | I12: =SUM(H16*0.08)+H16 -> 2010.328 | J12: =SUM(H16*0.08)+H16 -> 2010.328
B13: 27 | C13: =SUM(C16*0.26)+C16 -> 2741.8289 | D13: XXX | E13: XXX | G13: 9.52 | H13: =SUM(H16*0.12)+H16 -> 2084.7846 | I13: =SUM(H16*0.09)+H16 -> 2028.9421 | J13: =SUM(H16*0.1)+H16 -> 2047.5563
B14: 30 | C14: =SUM(C16*0.32)+C16 -> 2872.3922 | D14: XXX | E14: XXX | G14: 12.7 | H14: =SUM(H16*0.12)+H16 -> 2084.7846 | I14: =SUM(H16*0.09)+H16 -> 2028.9421 | J14: =SUM(H16*0.1)+H16 -> 2047.5563
B16: BASE | C16: =SUM(INICIO!K23) -> 2176.0547 | G16: BASE | H16: =SUM(INICIO!Q23) -> 1861.4148
B18: 3.17 | C18: 1245 | D18: S/MEL | E18: =SUM(I9*0.1)+I9 -> 2211.3608 | I18: CALIDAD
B19: 4.75 | C19: 1500 | D19: S/MEL | E19: =SUM(J10*0.1)+J10 -> 2190.8852 | I19: ANCHO
B20: 6.35 | C20: 1500 | D20: S/MEL | E20: =SUM(J11*0.1)+J11 -> 2211.3608 | I20: ESPESOR
B22: LISTA DE PRECIOS EN DÓLARES
B23: DD | C23: 1000 | D23: 1220 | E23: 1500 | G23: NEGRA | H23: 1000 | I23: 1245 | J23: 1500
B24: 16 | C24: =SUM(C34*0.07)+C34 -> 1.5543248 | D24: =SUM(C34*0.04)+C34 -> 1.5107456 | E24: =SUM(C34*0.04)+C34 -> 1.5107456 | G24: 1.6 | H24: XXX | I24: XXX | J24: XXX
B25: 18 | C25: =SUM(C34*0.07)+C34 -> 1.5543248 | D25: =SUM(C34*0.04)+C34 -> 1.5107456 | E25: =SUM(C34*0.04)+C34 -> 1.5107456 | G25: 2 | H25: =SUM(H34*0.14)+H34 -> 1.416564 | I25: =SUM(H34*0.11)+H34 -> 1.379286 | J25: XXX
B26: 12,14 y 20 | C26: =SUM(C34*0.08)+C34 -> 1.5688512 | D26: =SUM(C34*0.05)+C34 -> 1.525272 | E26: =SUM(C34*0.05)+C34 -> 1.525272 | G26: 2.5 | H26: =SUM(H34*0.12)+H34 -> 1.391712 | I26: =SUM(H34*0.09)+H34 -> 1.354434 | J26: XXX
B27: 22 | C27: =SUM(C34*0.1)+C34 -> 1.597904 | D27: =SUM(C34*0.07)+C34 -> 1.5543248 | E27: =SUM(C34*0.07)+C34 -> 1.5543248 | G27: 3.17 | H27: =SUM(H34*0.11)+H34 -> 1.379286 | I27: =SUM(H34*0.08)+H34 -> 1.342008 | J27: =SUM(H34*0.08)+H34 -> 1.342008
B28: 0.65 | C28: =SUM(C34*0.12)+C34 -> 1.6269568 | D28: =SUM(C34*0.09)+C34 -> 1.5833776 | E28: XXX | G28: 4,75 Y 4.00 | H28: =SUM(H34*0.1)+H34 -> 1.36686 | I28: =SUM(H34*0.07+H34) -> 1.329582 | J28: =SUM(H34*0.07)+H34 -> 1.329582
B29: 24 | C29: =SUM(C34*0.16)+C34 -> 1.6850624 | D29: =SUM(C34*0.13)+C34 -> 1.6414832 | E29: XXX | G29: 6.35 | H29: =SUM(H34*0.11)+H34 -> 1.379286 | I29: =SUM(H34*0.08)+H34 -> 1.342008 | J29: =SUM(H34*0.08)+H34 -> 1.342008
B30: 26 | C30: =SUM(C34*0.2)+C34 -> 1.743168 | D30: =SUM(C34*0.15)+C34 -> 1.670536 | E30: XXX | G30: 8 | H30: =SUM(H34*0.11)+H34 -> 1.379286 | I30: =SUM(H34*0.08)+H34 -> 1.342008 | J30: =SUM(H34*0.08)+H34 -> 1.342008
B31: 27 | C31: =SUM(C34*0.26)+C34 -> 1.8303264 | D31: XXX | E31: XXX | G31: 9.52 | H31: =SUM(H34*0.12)+H34 -> 1.391712 | I31: =SUM(H34*0.09)+H34 -> 1.354434 | J31: =SUM(H34*0.1)+H34 -> 1.36686
B32: 30 | C32: =SUM(C34*0.32)+C34 -> 1.9174848 | D32: XXX | E32: XXX | G32: 12.7 | H32: =SUM(H34*0.12)+H34 -> 1.391712 | I32: =SUM(H34*0.09)+H34 -> 1.354434 | J32: =SUM(H34*0.1)+H34 -> 1.36686
B34: BASE | C34: =SUM(INICIO!J23) -> 1.45264 | G34: BASE | H34: =SUM(INICIO!P23) -> 1.2426
B36: 3.17 | C36: 1245 | D36: S/MEL | E36: =SUM(I27*0.1)+I27 -> 1.4762088 | I36: CALIDAD
B37: 4.75 | C37: 1500 | D37: S/MEL | E37: =SUM(J28*0.1)+J28 -> 1.4625402 | I37: ANCHO
B38: 6.35 | C38: 1500 | D38: S/MEL | E38: =SUM(J29*0.1)+J29 -> 1.4762088 | I38: ESPESOR

Sheet 11
B2: CLIENTE: | D2: =PROPER(INICIO!D24) -> Buromaik/Calterm
B4: LISTA DE PRECIOS EN PESOS
B5: DD | C5: 1000 | D5: 1220 | E5: 1500 | G5: NEGRA | H5: 1000 | I5: 1245 | J5: 1500
B6: 16 | C6: =SUM(C16*0.07)+C16 -> 2224.4331 | D6: =SUM(C16*0.04)+C16 -> 2162.0658 | E6: =SUM(C16*0.04)+C16 -> 2162.0658 | G6: 1.6 | H6: XXX | I6: XXX | J6: XXX
B7: 18 | C7: =SUM(C16*0.07)+C16 -> 2224.4331 | D7: =SUM(C16*0.04)+C16 -> 2162.0658 | E7: =SUM(C16*0.04)+C16 -> 2162.0658 | G7: 2 | H7: =SUM(H16*0.14)+H16 -> 2044.1408 | I7: =SUM(H16*0.11)+H16 -> 1990.3477 | J7: XXX
B8: 12,14 y 20 | C8: =SUM(C16*0.08)+C16 -> 2245.2222 | D8: =SUM(C16*0.05)+C16 -> 2182.8549 | E8: =SUM(C16*0.05)+C16 -> 2182.8549 | G8: 2.5 | H8: =SUM(H16*0.12)+H16 -> 2008.2787 | I8: =SUM(H16*0.09)+H16 -> 1954.4855 | J8: XXX
B9: 22 | C9: =SUM(C16*0.1)+C16 -> 2286.8004 | D9: =SUM(C16*0.07)+C16 -> 2224.4331 | E9: =SUM(C16*0.07)+C16 -> 2224.4331 | G9: 3.17 | H9: =SUM(H16*0.11)+H16 -> 1990.3477 | I9: =SUM(H16*0.08)+H16 -> 1936.5545 | J9: =SUM(H16*0.08)+H16 -> 1936.5545
B10: 0.65 | C10: =SUM(C16*0.12)+C16 -> 2328.3786 | D10: =SUM(C16*0.09)+C16 -> 2266.0113 | E10: XXX | G10: 4,75 Y 4.00 | H10: =SUM(H16*0.1)+H16 -> 1972.4166 | I10: =SUM(H16*0.07+H16) -> 1918.6234 | J10: =SUM(H16*0.07)+H16 -> 1918.6234
B11: 24 | C11: =SUM(C16*0.16)+C16 -> 2411.5349 | D11: =SUM(C16*0.13)+C16 -> 2349.1676 | E11: XXX | G11: 6.35 | H11: =SUM(H16*0.11)+H16 -> 1990.3477 | I11: =SUM(H16*0.08)+H16 -> 1936.5545 | J11: =SUM(H16*0.08)+H16 -> 1936.5545
B12: 26 | C12: =SUM(C16*0.2)+C16 -> 2494.6913 | D12: =SUM(C16*0.15)+C16 -> 2390.7458 | E12: XXX | G12: 8 | H12: =SUM(H16*0.11)+H16 -> 1990.3477 | I12: =SUM(H16*0.08)+H16 -> 1936.5545 | J12: =SUM(H16*0.08)+H16 -> 1936.5545
B13: 27 | C13: =SUM(C16*0.26)+C16 -> 2619.4259 | D13: XXX | E13: XXX | G13: 9.52 | H13: =SUM(H16*0.12)+H16 -> 2008.2787 | I13: =SUM(H16*0.09)+H16 -> 1954.4855 | J13: =SUM(H16*0.1)+H16 -> 1972.4166
B14: 30 | C14: =SUM(C16*0.32)+C16 -> 2744.1604 | D14: XXX | E14: XXX | G14: 12.7 | H14: =SUM(H16*0.12)+H16 -> 2008.2787 | I14: =SUM(H16*0.09)+H16 -> 1954.4855 | J14: =SUM(H16*0.1)+H16 -> 1972.4166
B16: BASE | C16: =SUM(INICIO!K24) -> 2078.9094 | G16: BASE | H16: =SUM(INICIO!Q24) -> 1793.106
J17: cañterm 10
B18: 3.17 | C18: 1245 | D18: S/MEL | E18: =SUM(I9*0.1)+I9 -> 2130.2099 | I18: CALIDAD
B19: 4.75 | C19: 1500 | D19: S/MEL | E19: =SUM(J10*0.1)+J10 -> 2110.4858 | I19: ANCHO
B20: 6.35 | C20: 1500 | D20: S/MEL | E20: =SUM(J11*0.1)+J11 -> 2130.2099 | I20: ESPESOR
B22: LISTA DE PRECIOS EN DÓLARES
B23: DD | C23: 1000 | D23: 1220 | E23: 1500 | G23: NEGRA | H23: 1000 | I23: 1245 | J23: 1500
B24: 16 | C24: =SUM(C34*0.07)+C34 -> 1.4849353 | D24: =SUM(C34*0.04)+C34 -> 1.4433016 | E24: =SUM(C34*0.04)+C34 -> 1.4433016 | G24: 1.6 | H24: XXX | I24: XXX | J24: XXX
B25: 18 | C25: =SUM(C34*0.07)+C34 -> 1.4849353 | D25: =SUM(C34*0.04)+C34 -> 1.4433016 | E25: =SUM(C34*0.04)+C34 -> 1.4433016 | G25: 2 | H25: =SUM(H34*0.14)+H34 -> 1.36458 | I25: =SUM(H34*0.11)+H34 -> 1.32867 | J25: XXX
B26: 12,14 y 20 | C26: =SUM(C34*0.08)+C34 -> 1.4988132 | D26: =SUM(C34*0.05)+C34 -> 1.4571795 | E26: =SUM(C34*0.05)+C34 -> 1.4571795 | G26: 2.5 | H26: =SUM(H34*0.12)+H34 -> 1.34064 | I26: =SUM(H34*0.09)+H34 -> 1.30473 | J26: XXX
B27: 22 | C27: =SUM(C34*0.1)+C34 -> 1.526569 | D27: =SUM(C34*0.07)+C34 -> 1.4849353 | E27: =SUM(C34*0.07)+C34 -> 1.4849353 | G27: 3.17 | H27: =SUM(H34*0.11)+H34 -> 1.32867 | I27: =SUM(H34*0.08)+H34 -> 1.29276 | J27: =SUM(H34*0.08)+H34 -> 1.29276
B28: 0.65 | C28: =SUM(C34*0.12)+C34 -> 1.5543248 | D28: =SUM(C34*0.09)+C34 -> 1.5126911 | E28: XXX | G28: 4,75 Y 4.00 | H28: =SUM(H34*0.1)+H34 -> 1.3167 | I28: =SUM(H34*0.07+H34) -> 1.28079 | J28: =SUM(H34*0.07)+H34 -> 1.28079
B29: 24 | C29: =SUM(C34*0.16)+C34 -> 1.6098364 | D29: =SUM(C34*0.13)+C34 -> 1.5682027 | E29: XXX | G29: 6.35 | H29: =SUM(H34*0.11)+H34 -> 1.32867 | I29: =SUM(H34*0.08)+H34 -> 1.29276 | J29: =SUM(H34*0.08)+H34 -> 1.29276
B30: 26 | C30: =SUM(C34*0.2)+C34 -> 1.665348 | D30: =SUM(C34*0.15)+C34 -> 1.5959585 | E30: XXX | G30: 8 | H30: =SUM(H34*0.11)+H34 -> 1.32867 | I30: =SUM(H34*0.08)+H34 -> 1.29276 | J30: =SUM(H34*0.08)+H34 -> 1.29276
B31: 27 | C31: =SUM(C34*0.26)+C34 -> 1.7486154 | D31: XXX | E31: XXX | G31: 9.52 | H31: =SUM(H34*0.12)+H34 -> 1.34064 | I31: =SUM(H34*0.09)+H34 -> 1.30473 | J31: =SUM(H34*0.1)+H34 -> 1.3167
B32: 30 | C32: =SUM(C34*0.32)+C34 -> 1.8318828 | D32: XXX | E32: XXX | G32: 12.7 | H32: =SUM(H34*0.12)+H34 -> 1.34064 | I32: =SUM(H34*0.09)+H34 -> 1.30473 | J32: =SUM(H34*0.1)+H34 -> 1.3167
B34: BASE | C34: =SUM(INICIO!J24) -> 1.38779 | G34: BASE | H34: =SUM(INICIO!P24) -> 1.197
B36: 3.17 | C36: 1245 | D36: S/MEL | E36: =SUM(I27*0.1)+I27 -> 1.422036 | I36: CALIDAD
B37: 4.75 | C37: 1500 | D37: S/MEL | E37: =SUM(J28*0.1)+J28 -> 1.408869 | I37: ANCHO
B38: 6.35 | C38: 1500 | D38: S/MEL | E38: =SUM(J29*0.1)+J29 -> 1.422036 | I38: ESPESOR

Sheet 12
B2: CLIENTE: | D2: =PROPER(INICIO!D25) -> Morelli/Campana/Proyectos/Accetub
B4: LISTA DE PRECIOS EN PESOS
B5: DD | C5: 1000 | D5: 1220 | E5: 1500 | G5: NEGRA | H5: 1000 | I5: 1245 | J5: 1500
B6: 16 | C6: =SUM(C16*0.07)+C16 -> 2203.644 | D6: =SUM(C16*0.04)+C16 -> 2141.8596 | E6: =SUM(C16*0.04)+C16 -> 2141.8596 | G6: 1.6 | H6: XXX | I6: XXX | J6: XXX
B7: 18 | C7: =SUM(C16*0.07)+C16 -> 2203.644 | D7: =SUM(C16*0.04)+C16 -> 2141.8596 | E7: =SUM(C16*0.04)+C16 -> 2141.8596 | G7: 2 | H7: =SUM(H16*0.14)+H16 -> 1966.2688 | I7: =SUM(H16*0.11)+H16 -> 1914.5249 | J7: XXX
B8: 12,14 y 20 | C8: =SUM(C16*0.08)+C16 -> 2224.2388 | D8: =SUM(C16*0.05)+C16 -> 2162.4544 | E8: =SUM(C16*0.05)+C16 -> 2162.4544 | G8: 2.5 | H8: =SUM(H16*0.12)+H16 -> 1931.7729 | I8: =SUM(H16*0.09)+H16 -> 1880.0289 | J8: XXX
B9: 22 | C9: =SUM(C16*0.1)+C16 -> 2265.4284 | D9: =SUM(C16*0.07)+C16 -> 2203.644 | E9: XXX | G9: 3.17 | H9: =SUM(H16*0.11)+H16 -> 1914.5249 | I9: =SUM(H16*0.08)+H16 -> 1862.781 | J9: =SUM(H16*0.08)+H16 -> 1862.781
B10: 0.65 | C10: =SUM(C16*0.12)+C16 -> 2306.618 | D10: =SUM(C16*0.09)+C16 -> 2244.8336 | E10: XXX | G10: 4,75 Y 4.00 | H10: =SUM(H16*0.1)+H16 -> 1897.2769 | I10: =SUM(H16*0.07+H16) -> 1845.533 | J10: =SUM(H16*0.07)+H16 -> 1845.533
B11: 24 | C11: =SUM(C16*0.16)+C16 -> 2388.9972 | D11: =SUM(C16*0.13)+C16 -> 2327.2128 | E11: XXX | G11: 6.35 | H11: =SUM(H16*0.11)+H16 -> 1914.5249 | I11: =SUM(H16*0.08)+H16 -> 1862.781 | J11: =SUM(H16*0.08)+H16 -> 1862.781
B12: 26 | C12: =SUM(C16*0.2)+C16 -> 2471.3764 | D12: =SUM(C16*0.15)+C16 -> 2368.4024 | E12: XXX | G12: 8 | H12: =SUM(H16*0.11)+H16 -> 1914.5249 | I12: =SUM(H16*0.08)+H16 -> 1862.781 | J12: =SUM(H16*0.08)+H16 -> 1862.781
B13: 27 | C13: =SUM(C16*0.26)+C16 -> 2594.9453 | D13: XXX | E13: XXX | G13: 9.52 | H13: =SUM(H16*0.12)+H16 -> 1931.7729 | I13: =SUM(H16*0.09)+H16 -> 1880.0289 | J13: =SUM(H16*0.1)+H16 -> 1897.2769
B14: 30 | C14: =SUM(C16*0.32)+C16 -> 2718.5141 | D14: XXX | E14: XXX | G14: 12.7 | H14: =SUM(H16*0.12)+H16 -> 1931.7729 | I14: =SUM(H16*0.09)+H16 -> 1880.0289 | J14: =SUM(H16*0.1)+H16 -> 1897.2769
B16: BASE | C16: =SUM(INICIO!K25) -> 2059.4804 | G16: BASE | H16: =SUM(INICIO!Q25) -> 1724.7972 | J16: lisy
J17: morell -11
B18: 3.17 | C18: 1245 | D18: S/MEL | E18: =SUM(I9*0.1)+I9 -> 2049.0591 | I18: CALIDAD | J18: proye 7
B19: 4.75 | C19: 1500 | D19: S/MEL | E19: =SUM(J10*0.1)+J10 -> 2030.0863 | I19: ANCHO
B20: 6.35 | C20: 1500 | D20: S/MEL | E20: =SUM(J11*0.1)+J11 -> 2049.0591 | I20: ESPESOR
B22: LISTA DE PRECIOS EN DÓLARES
B23: DD | C23: 1000 | D23: 1220 | E23: 1500 | G23: NEGRA | H23: 1000 | I23: 1245 | J23: 1500
B24: 16 | C24: =SUM(C34*0.07)+C34 -> 1.4710574 | D24: =SUM(C34*0.04)+C34 -> 1.4298128 | E24: =SUM(C34*0.04)+C34 -> 1.4298128 | G24: 1.6 | H24: XXX | I24: XXX | J24: XXX
B25: 18 | C25: =SUM(C34*0.07)+C34 -> 1.4710574 | D25: =SUM(C34*0.04)+C34 -> 1.4298128 | E25: =SUM(C34*0.04)+C34 -> 1.4298128 | G25: 2 | H25: =SUM(H34*0.14)+H34 -> 1.312596 | I25: =SUM(H34*0.11)+H34 -> 1.278054 | J25: XXX
B26: 12,14 y 20 | C26: =SUM(C34*0.08)+C34 -> 1.4848056 | D26: =SUM(C34*0.05)+C34 -> 1.443561 | E26: =SUM(C34*0.05)+C34 -> 1.443561 | G26: 2.5 | H26: =SUM(H34*0.12)+H34 -> 1.289568 | I26: =SUM(H34*0.09)+H34 -> 1.255026 | J26: XXX
B27: 22 | C27: =SUM(C34*0.1)+C34 -> 1.512302 | D27: =SUM(C34*0.07)+C34 -> 1.4710574 | E27: =SUM(C34*0.07)+C34 -> 1.4710574 | G27: 3.17 | H27: =SUM(H34*0.11)+H34 -> 1.278054 | I27: =SUM(H34*0.08)+H34 -> 1.243512 | J27: =SUM(H34*0.08)+H34 -> 1.243512
B28: 0.65 | C28: =SUM(C34*0.12)+C34 -> 1.5397984 | D28: =SUM(C34*0.09)+C34 -> 1.4985538 | E28: XXX | G28: 4,75 Y 4.00 | H28: =SUM(H34*0.1)+H34 -> 1.26654 | I28: =SUM(H34*0.07+H34) -> 1.231998 | J28: =SUM(H34*0.07)+H34 -> 1.231998
B29: 24 | C29: =SUM(C34*0.16)+C34 -> 1.5947912 | D29: =SUM(C34*0.13)+C34 -> 1.5535466 | E29: XXX | G29: 6.35 | H29: =SUM(H34*0.11)+H34 -> 1.278054 | I29: =SUM(H34*0.08)+H34 -> 1.243512 | J29: =SUM(H34*0.08)+H34 -> 1.243512
B30: 26 | C30: =SUM(C34*0.2)+C34 -> 1.649784 | D30: =SUM(C34*0.15)+C34 -> 1.581043 | E30: XXX | G30: 8 | H30: =SUM(H34*0.11)+H34 -> 1.278054 | I30: =SUM(H34*0.08)+H34 -> 1.243512 | J30: =SUM(H34*0.08)+H34 -> 1.243512
B31: 27 | C31: =SUM(C34*0.26)+C34 -> 1.7322732 | D31: XXX | E31: XXX | G31: 9.52 | H31: =SUM(H34*0.12)+H34 -> 1.289568 | I31: =SUM(H34*0.09)+H34 -> 1.255026 | J31: =SUM(H34*0.09)+H34 -> 1.255026
B32: 30 | C32: =SUM(C34*0.32)+C34 -> 1.8147624 | D32: XXX | E32: XXX | G32: 12.7 | H32: =SUM(H34*0.12)+H34 -> 1.289568 | I32: =SUM(H34*0.09)+H34 -> 1.255026 | J32: =SUM(H34*0.09)+H34 -> 1.255026
B34: BASE | C34: =SUM(INICIO!J25) -> 1.37482 | G34: BASE | H34: =SUM(INICIO!P25) -> 1.1514
B36: 3.17 | C36: 1245 | D36: S/MEL | E36: =SUM(I27*0.1)+I27 -> 1.3678632 | I36: CALIDAD
B37: 4.75 | C37: 1500 | D37: S/MEL | E37: =SUM(J28*0.1)+J28 -> 1.3551978 | I37: ANCHO
B38: 6.35 | C38: 1500 | D38: S/MEL | E38: =SUM(J29*0.1)+J29 -> 1.3678632 | I38: ESPESOR

Sheet 13
A1: 1692.72
B2: CLIENTE: | D2: =PROPER(INICIO!D26) -> Hornos Del Sur/Carbone/Msequipment
B4: LISTA DE PRECIOS EN PESOS
B5: DD | C5: 1000 | D5: 1220 | E5: 1500 | G5: NEGRA | H5: 1000 | I5: 1245 | J5: 1500
B6: 16 | C6: =SUM(C16*0.07)+C16 -> 2245.2222 | D6: =SUM(C16*0.04)+C16 -> 2182.272 | E6: =SUM(C16*0.04)+C16 -> 2182.272 | G6: 1.6 | H6: XXX | I6: XXX | J6: XXX
B7: 18 | C7: =SUM(C16*0.07)+C16 -> 2245.2222 | D7: =SUM(C16*0.04)+C16 -> 2182.272 | E7: =SUM(C16*0.04)+C16 -> 2182.272 | G7: 2 | H7: =SUM(H16*0.14)+H16 -> 2044.1408 | I7: =SUM(H16*0.11)+H16 -> 1990.3477 | J7: XXX
B8: 12,14 y 20 | C8: =SUM(C16*0.08)+C16 -> 2266.2056 | D8: =SUM(C16*0.05)+C16 -> 2203.2554 | E8: =SUM(C16*0.05)+C16 -> 2203.2554 | G8: 2.5 | H8: =SUM(H16*0.12)+H16 -> 2008.2787 | I8: =SUM(H16*0.09)+H16 -> 1954.4855 | J8: XXX
B9: 22 | C9: =SUM(C16*0.1)+C16 -> 2308.1723 | D9: =SUM(C16*0.07)+C16 -> 2245.2222 | E9: =SUM(C16*0.07)+C16 -> 2245.2222 | G9: 3.17 | H9: =SUM(H16*0.11)+H16 -> 1990.3477 | I9: =SUM(H16*0.08)+H16 -> 1936.5545 | J9: =SUM(H16*0.08)+H16 -> 1936.5545
B10: 0.65 | C10: =SUM(C16*0.12)+C16 -> 2350.1391 | D10: =SUM(C16*0.09)+C16 -> 2287.1889 | E10: XXX | G10: 4,75 Y 4.00 | H10: =SUM(H16*0.1)+H16 -> 1972.4166 | I10: =SUM(H16*0.07+H16) -> 1918.6234 | J10: =SUM(H16*0.07)+H16 -> 1918.6234
B11: 24 | C11: =SUM(C16*0.16)+C16 -> 2434.0726 | D11: =SUM(C16*0.13)+C16 -> 2371.1225 | E11: XXX | G11: 6.35 | H11: =SUM(H16*0.11)+H16 -> 1990.3477 | I11: =SUM(H16*0.08)+H16 -> 1936.5545 | J11: =SUM(H16*0.08)+H16 -> 1936.5545
B12: 26 | C12: =SUM(C16*0.2)+C16 -> 2518.0062 | D12: =SUM(C16*0.15)+C16 -> 2413.0893 | E12: XXX | G12: 8 | H12: =SUM(H16*0.11)+H16 -> 1990.3477 | I12: =SUM(H16*0.08)+H16 -> 1936.5545 | J12: =SUM(H16*0.08)+H16 -> 1936.5545
B13: 27 | C13: =SUM(C16*0.26)+C16 -> 2643.9065 | D13: XXX | E13: XXX | G13: 9.52 | H13: =SUM(H16*0.12)+H16 -> 2008.2787 | I13: =SUM(H16*0.09)+H16 -> 1954.4855 | J13: =SUM(H16*0.1)+H16 -> 1972.4166
B14: 30 | C14: =SUM(C16*0.32)+C16 -> 2769.8068 | D14: XXX | E14: XXX | G14: 12.7 | H14: =SUM(H16*0.12)+H16 -> 2008.2787 | I14: =SUM(H16*0.09)+H16 -> 1954.4855 | J14: =SUM(H16*0.1)+H16 -> 1972.4166
B16: BASE | C16: =SUM(INICIO!K26) -> 2098.3385 | G16: BASE | H16: =SUM(INICIO!Q26) -> 1793.106
J17: carbone -8%
B18: 3.17 | C18: 1245 | D18: S/MEL | E18: =SUM(I9*0.1)+I9 -> 2130.2099 | I18: CALIDAD | J18: MSeq 10%
B19: 4.75 | C19: 1500 | D19: S/MEL | E19: =SUM(J10*0.1)+J10 -> 2110.4858 | I19: ANCHO
B20: 6.35 | C20: 1500 | D20: S/MEL | E20: =SUM(J11*0.1)+J11 -> 2130.2099 | I20: ESPESOR
B22: LISTA DE PRECIOS EN DÓLARES
B23: DD | C23: 1000 | D23: 1220 | E23: 1500 | G23: NEGRA | H23: 1000 | I23: 1245 | J23: 1500
B24: 16 | C24: =SUM(C34*0.07)+C34 -> 1.4988132 | D24: =SUM(C34*0.04)+C34 -> 1.4567904 | E24: =SUM(C34*0.04)+C34 -> 1.4567904 | G24: 1.6 | H24: XXX | I24: XXX | J24: XXX
B25: 18 | C25: =SUM(C34*0.07)+C34 -> 1.4988132 | D25: =SUM(C34*0.04)+C34 -> 1.4567904 | E25: =SUM(C34*0.04)+C34 -> 1.4567904 | G25: 2 | H25: =SUM(H34*0.14)+H34 -> 1.36458 | I25: =SUM(H34*0.11)+H34 -> 1.32867 | J25: XXX
B26: 12,14 y 20 | C26: =SUM(C34*0.08)+C34 -> 1.5128208 | D26: =SUM(C34*0.05)+C34 -> 1.470798 | E26: =SUM(C34*0.05)+C34 -> 1.470798 | G26: 2.5 | H26: =SUM(H34*0.12)+H34 -> 1.34064 | I26: =SUM(H34*0.09)+H34 -> 1.30473 | J26: XXX
B27: 22 | C27: =SUM(C34*0.1)+C34 -> 1.540836 | D27: =SUM(C34*0.07)+C34 -> 1.4988132 | E27: =SUM(C34*0.07)+C34 -> 1.4988132 | G27: 3.17 | H27: =SUM(H34*0.11)+H34 -> 1.32867 | I27: =SUM(H34*0.08)+H34 -> 1.29276 | J27: =SUM(H34*0.08)+H34 -> 1.29276
B28: 0.65 | C28: =SUM(C34*0.12)+C34 -> 1.5688512 | D28: =SUM(C34*0.09)+C34 -> 1.5268284 | E28: XXX | G28: 4,75 Y 4.00 | H28: =SUM(H34*0.1)+H34 -> 1.3167 | I28: =SUM(H34*0.07+H34) -> 1.28079 | J28: =SUM(H34*0.07)+H34 -> 1.28079
B29: 24 | C29: =SUM(C34*0.16)+C34 -> 1.6248816 | D29: =SUM(C34*0.13)+C34 -> 1.5828588 | E29: XXX | G29: 6.35 | H29: =SUM(H34*0.11)+H34 -> 1.32867 | I29: =SUM(H34*0.08)+H34 -> 1.29276 | J29: =SUM(H34*0.08)+H34 -> 1.29276
B30: 26 | C30: =SUM(C34*0.2)+C34 -> 1.680912 | D30: =SUM(C34*0.15)+C34 -> 1.610874 | E30: XXX | G30: 8 | H30: =SUM(H34*0.11)+H34 -> 1.32867 | I30: =SUM(H34*0.08)+H34 -> 1.29276 | J30: =SUM(H34*0.08)+H34 -> 1.29276
B31: 27 | C31: =SUM(C34*0.26)+C34 -> 1.7649576 | D31: XXX | E31: XXX | G31: 9.52 | H31: =SUM(H34*0.12)+H34 -> 1.34064 | I31: =SUM(H34*0.09)+H34 -> 1.30473 | J31: =SUM(H34*0.1)+H34 -> 1.3167
B32: 30 | C32: =SUM(C34*0.32)+C34 -> 1.8490032 | D32: XXX | E32: XXX | G32: 12.7 | H32: =SUM(H34*0.12)+H34 -> 1.34064 | I32: =SUM(H34*0.09)+H34 -> 1.30473 | J32: =SUM(H34*0.1)+H34 -> 1.3167
B34: BASE | C34: =SUM(INICIO!J26) -> 1.40076 | G34: BASE | H34: =SUM(INICIO!P26) -> 1.197
B36: 3.17 | C36: 1245 | D36: S/MEL | E36: =SUM(I27*0.1)+I27 -> 1.422036 | I36: CALIDAD
B37: 4.75 | C37: 1500 | D37: S/MEL | E37: =SUM(J28*0.1)+J28 -> 1.408869 | I37: ANCHO
B38: 6.35 | C38: 1500 | D38: S/MEL | E38: =SUM(J29*0.1)+J29 -> 1.422036 | I38: ESPESOR

Sheet 14
B2: CLIENTE: | D2: =PROPER(INICIO!D27) -> Rominic/Norberto
B4: LISTA DE PRECIOS EN PESOS
B5: DD | C5: 1000 | D5: 1220 | E5: 1500 | G5: NEGRA | H5: 1000 | I5: 1245 | J5: 1500
B6: 16 | C6: =SUM(C16*0.07)+C16 -> 2577.8477 | D6: =SUM(C16*0.04)+C16 -> 2505.5716 | E6: =SUM(C16*0.04)+C16 -> 2505.5716 | G6: 1.6 | H6: XXX | I6: XXX | J6: XXX
B7: 18 | C7: =SUM(C16*0.07)+C16 -> 2577.8477 | D7: =SUM(C16*0.04)+C16 -> 2505.5716 | E7: =SUM(C16*0.04)+C16 -> 2505.5716 | G7: 2 | H7: =SUM(H16*0.14)+H16 -> 2336.161 | I7: =SUM(H16*0.11)+H16 -> 2274.683 | J7: XXX
B8: 12,14 y 20 | C8: =SUM(C16*0.08)+C16 -> 2601.9397 | D8: =SUM(C16*0.05)+C16 -> 2529.6636 | E8: =SUM(C16*0.05)+C16 -> 2529.6636 | G8: 2.5 | H8: =SUM(H16*0.12)+H16 -> 2295.1757 | I8: =SUM(H16*0.09)+H16 -> 2233.6978 | J8: XXX
B9: 22 | C9: =SUM(C16*0.1)+C16 -> 2650.1238 | D9: =SUM(C16*0.07)+C16 -> 2577.8477 | E9: =SUM(C16*0.07)+C16 -> 2577.8477 | G9: 3.17 | H9: =SUM(H16*0.11)+H16 -> 2274.683 | I9: =SUM(H16*0.08)+H16 -> 2213.2051 | J9: =SUM(H16*0.08)+H16 -> 2213.2051
B10: 0.65 | C10: =SUM(C16*0.12)+C16 -> 2698.3079 | D10: =SUM(C16*0.09)+C16 -> 2626.0317 | E10: XXX | G10: 4,75 Y 4.00 | H10: =SUM(H16*0.1)+H16 -> 2254.1904 | I10: =SUM(H16*0.07+H16) -> 2192.7125 | J10: =SUM(H16*0.07)+H16 -> 2192.7125
B11: 24 | C11: =SUM(C16*0.16)+C16 -> 2794.676 | D11: =SUM(C16*0.13)+C16 -> 2722.3999 | E11: XXX | G11: 6.35 | H11: =SUM(H16*0.11)+H16 -> 2274.683 | I11: =SUM(H16*0.08)+H16 -> 2213.2051 | J11: =SUM(H16*0.08)+H16 -> 2213.2051
B12: 26 | C12: =SUM(C16*0.2)+C16 -> 2891.0441 | D12: =SUM(C16*0.15)+C16 -> 2770.584 | E12: XXX | G12: 8 | H12: =SUM(H16*0.11)+H16 -> 2274.683 | I12: =SUM(H16*0.08)+H16 -> 2213.2051 | J12: =SUM(H16*0.08)+H16 -> 2213.2051
B13: 27 | C13: =SUM(C16*0.26)+C16 -> 3035.5963 | D13: XXX | E13: XXX | G13: 9.52 | H13: =SUM(H16*0.12)+H16 -> 2295.1757 | I13: =SUM(H16*0.09)+H16 -> 2233.6978 | J13: =SUM(H16*0.1)+H16 -> 2254.1904
B14: 30 | C14: =SUM(C16*0.32)+C16 -> 3180.1485 | D14: XXX | E14: XXX | G14: 12.7 | H14: =SUM(H16*0.12)+H16 -> 2295.1757 | I14: =SUM(H16*0.09)+H16 -> 2233.6978 | J14: =SUM(H16*0.1)+H16 -> 2254.1904
B16: BASE | C16: =SUM(INICIO!K27) -> 2409.2034 | G16: BASE | H16: =SUM(INICIO!Q27) -> 2049.264 | J16: dec 8,5
B18: 3.17 | C18: 1245 | D18: S/MEL | E18: =SUM(I9*0.1)+I9 -> 2434.5256 | I18: CALIDAD
B19: 4.75 | C19: 1500 | D19: S/MEL | E19: =SUM(J10*0.1)+J10 -> 2411.9837 | I19: ANCHO
B20: 6.35 | C20: 1500 | D20: S/MEL | E20: =SUM(J11*0.1)+J11 -> 2434.5256 | I20: ESPESOR
B22: LISTA DE PRECIOS EN DÓLARES
B23: DD | C23: 1000 | D23: 1220 | E23: 1500 | G23: NEGRA | H23: 1000 | I23: 1245 | J23: 1500
B24: 16 | C24: =SUM(C34*0.07)+C34 -> 1.7208596 | D24: =SUM(C34*0.04)+C34 -> 1.6726112 | E24: =SUM(C34*0.04)+C34 -> 1.6726112 | G24: 1.6 | H24: XXX | I24: XXX | J24: XXX
B25: 18 | C25: =SUM(C34*0.07)+C34 -> 1.7208596 | D25: =SUM(C34*0.04)+C34 -> 1.6726112 | E25: =SUM(C34*0.04)+C34 -> 1.6726112 | G25: 2 | H25: =SUM(H34*0.14)+H34 -> 1.55952 | I25: =SUM(H34*0.11)+H34 -> 1.51848 | J25: XXX
B26: 12,14 y 20 | C26: =SUM(C34*0.08)+C34 -> 1.7369424 | D26: =SUM(C34*0.05)+C34 -> 1.688694 | E26: =SUM(C34*0.05)+C34 -> 1.688694 | G26: 2.5 | H26: =SUM(H34*0.12)+H34 -> 1.53216 | I26: =SUM(H34*0.09)+H34 -> 1.49112 | J26: XXX
B27: 22 | C27: =SUM(C34*0.1)+C34 -> 1.769108 | D27: =SUM(C34*0.07)+C34 -> 1.7208596 | E27: =SUM(C34*0.07)+C34 -> 1.7208596 | G27: 3.17 | H27: =SUM(H34*0.11)+H34 -> 1.51848 | I27: =SUM(H34*0.08)+H34 -> 1.47744 | J27: =SUM(H34*0.08)+H34 -> 1.47744
B28: 0.65 | C28: =SUM(C34*0.12)+C34 -> 1.8012736 | D28: =SUM(C34*0.09)+C34 -> 1.7530252 | E28: XXX | G28: 4,75 Y 4.00 | H28: =SUM(H34*0.1)+H34 -> 1.5048 | I28: =SUM(H34*0.07+H34) -> 1.46376 | J28: =SUM(H34*0.07)+H34 -> 1.46376
B29: 24 | C29: =SUM(C34*0.16)+C34 -> 1.8656048 | D29: =SUM(C34*0.13)+C34 -> 1.8173564 | E29: XXX | G29: 6.35 | H29: =SUM(H34*0.11)+H34 -> 1.51848 | I29: =SUM(H34*0.08)+H34 -> 1.47744 | J29: =SUM(H34*0.08)+H34 -> 1.47744
B30: 26 | C30: =SUM(C34*0.2)+C34 -> 1.929936 | D30: =SUM(C34*0.15)+C34 -> 1.849522 | E30: XXX | G30: 8 | H30: =SUM(H34*0.11)+H34 -> 1.51848 | I30: =SUM(H34*0.08)+H34 -> 1.47744 | J30: =SUM(H34*0.08)+H34 -> 1.47744
B31: 27 | C31: =SUM(C34*0.26)+C34 -> 2.0264328 | D31: XXX | E31: XXX | G31: 9.52 | H31: =SUM(H34*0.12)+H34 -> 1.53216 | I31: =SUM(H34*0.09)+H34 -> 1.49112 | J31: =SUM(H34*0.1)+H34 -> 1.5048
B32: 30 | C32: =SUM(C34*0.32)+C34 -> 2.1229296 | D32: XXX | E32: XXX | G32: 12.7 | H32: =SUM(H34*0.12)+H34 -> 1.53216 | I32: =SUM(H34*0.09)+H34 -> 1.49112 | J32: =SUM(H34*0.1)+H34 -> 1.5048
B34: BASE | C34: =SUM(INICIO!J27) -> 1.60828 | G34: BASE | H34: =SUM(INICIO!P27) -> 1.368
B36: 3.17 | C36: 1245 | D36: S/MEL | E36: =SUM(I27*0.1)+I27 -> 1.625184 | I36: CALIDAD
B37: 4.75 | C37: 1500 | D37: S/MEL | E37: =SUM(J28*0.1)+J28 -> 1.610136 | I37: ANCHO
B38: 6.35 | C38: 1500 | D38: S/MEL | E38: =SUM(J29*0.1)+J29 -> 1.625184 | I38: ESPESOR

Sheet 15
B2: CLIENTE: | D2: =PROPER(INICIO!D28) -> Gestec/Arlem/Figue/Denti
B4: LISTA DE PRECIOS EN PESOS
B5: DD | C5: 1000 | D5: 1220 | E5: 1500 | G5: NEGRA | H5: 1000 | I5: 1245 | J5: 1500
B6: 16 | C6: =SUM(C16*0.07)+C16 -> 2577.8477 | D6: =SUM(C16*0.04)+C16 -> 2505.5716 | E6: =SUM(C16*0.04)+C16 -> 2505.5716 | G6: 1.6 | H6: XXX | I6: XXX | J6: XXX
B7: 18 | C7: =SUM(C16*0.07)+C16 -> 2577.8477 | D7: =SUM(C16*0.04)+C16 -> 2505.5716 | E7: =SUM(C16*0.04)+C16 -> 2505.5716 | G7: 2 | H7: =SUM(H16*0.14)+H16 -> 2336.161 | I7: =SUM(H16*0.11)+H16 -> 2274.683 | J7: XXX
B8: 12,14 y 20 | C8: =SUM(C16*0.08)+C16 -> 2601.9397 | D8: =SUM(C16*0.05)+C16 -> 2529.6636 | E8: =SUM(C16*0.05)+C16 -> 2529.6636 | G8: 2.5 | H8: =SUM(H16*0.12)+H16 -> 2295.1757 | I8: =SUM(H16*0.09)+H16 -> 2233.6978 | J8: XXX
B9: 22 | C9: =SUM(C16*0.1)+C16 -> 2650.1238 | D9: =SUM(C16*0.07)+C16 -> 2577.8477 | E9: =SUM(C16*0.07)+C16 -> 2577.8477 | G9: 3.17 | H9: =SUM(H16*0.11)+H16 -> 2274.683 | I9: =SUM(H16*0.08)+H16 -> 2213.2051 | J9: =SUM(H16*0.08)+H16 -> 2213.2051
B10: 0.65 | C10: =SUM(C16*0.12)+C16 -> 2698.3079 | D10: =SUM(C16*0.09)+C16 -> 2626.0317 | E10: XXX | G10: 4,75 Y 4.00 | H10: =SUM(H16*0.1)+H16 -> 2254.1904 | I10: =SUM(H16*0.07+H16) -> 2192.7125 | J10: =SUM(H16*0.07)+H16 -> 2192.7125
B11: 24 | C11: =SUM(C16*0.16)+C16 -> 2794.676 | D11: =SUM(C16*0.13)+C16 -> 2722.3999 | E11: XXX | G11: 6.35 | H11: =SUM(H16*0.11)+H16 -> 2274.683 | I11: =SUM(H16*0.08)+H16 -> 2213.2051 | J11: =SUM(H16*0.08)+H16 -> 2213.2051
B12: 26 | C12: =SUM(C16*0.2)+C16 -> 2891.0441 | D12: =SUM(C16*0.15)+C16 -> 2770.584 | E12: XXX | G12: 8 | H12: =SUM(H16*0.11)+H16 -> 2274.683 | I12: =SUM(H16*0.08)+H16 -> 2213.2051 | J12: =SUM(H16*0.08)+H16 -> 2213.2051
B13: 27 | C13: =SUM(C16*0.26)+C16 -> 3035.5963 | D13: XXX | E13: XXX | G13: 9.52 | H13: =SUM(H16*0.12)+H16 -> 2295.1757 | I13: =SUM(H16*0.09)+H16 -> 2233.6978 | J13: =SUM(H16*0.1)+H16 -> 2254.1904
B14: 30 | C14: =SUM(C16*0.32)+C16 -> 3180.1485 | D14: XXX | E14: XXX | G14: 12.7 | H14: =SUM(H16*0.12)+H16 -> 2295.1757 | I14: =SUM(H16*0.09)+H16 -> 2233.6978 | J14: =SUM(H16*0.1)+H16 -> 2254.1904
B16: BASE | C16: =SUM(INICIO!K28) -> 2409.2034 | G16: BASE | H16: =SUM(INICIO!Q28) -> 2049.264
B18: 3.17 | C18: 1245 | D18: S/MEL | E18: =SUM(I9*0.1)+I9 -> 2434.5256 | I18: CALIDAD
B19: 4.75 | C19: 1500 | D19: S/MEL | E19: =SUM(J10*0.1)+J10 -> 2411.9837 | I19: ANCHO
B20: 6.35 | C20: 1500 | D20: S/MEL | E20: =SUM(J11*0.1)+J11 -> 2434.5256 | I20: ESPESOR
B22: LISTA DE PRECIOS EN DÓLARES
B23: DD | C23: 1000 | D23: 1220 | E23: 1500 | G23: NEGRA | H23: 1000 | I23: 1245 | J23: 1500
B24: 16 | C24: =SUM(C34*0.07)+C34 -> 1.7208596 | D24: =SUM(C34*0.04)+C34 -> 1.6726112 | E24: =SUM(C34*0.04)+C34 -> 1.6726112 | G24: 1.6 | H24: XXX | I24: XXX | J24: XXX
B25: 18 | C25: =SUM(C34*0.07)+C34 -> 1.7208596 | D25: =SUM(C34*0.04)+C34 -> 1.6726112 | E25: =SUM(C34*0.04)+C34 -> 1.6726112 | G25: 2 | H25: =SUM(H34*0.14)+H34 -> 1.55952 | I25: =SUM(H34*0.11)+H34 -> 1.51848 | J25: XXX
B26: 12,14 y 20 | C26: =SUM(C34*0.08)+C34 -> 1.7369424 | D26: =SUM(C34*0.05)+C34 -> 1.688694 | E26: =SUM(C34*0.05)+C34 -> 1.688694 | G26: 2.5 | H26: =SUM(H34*0.12)+H34 -> 1.53216 | I26: =SUM(H34*0.09)+H34 -> 1.49112 | J26: XXX
B27: 22 | C27: =SUM(C34*0.1)+C34 -> 1.769108 | D27: =SUM(C34*0.07)+C34 -> 1.7208596 | E27: =SUM(C34*0.07)+C34 -> 1.7208596 | G27: 3.17 | H27: =SUM(H34*0.11)+H34 -> 1.51848 | I27: =SUM(H34*0.08)+H34 -> 1.47744 | J27: =SUM(H34*0.08)+H34 -> 1.47744
B28: 0.65 | C28: =SUM(C34*0.12)+C34 -> 1.8012736 | D28: =SUM(C34*0.09)+C34 -> 1.7530252 | E28: XXX | G28: 4,75 Y 4.00 | H28: =SUM(H34*0.1)+H34 -> 1.5048 | I28: =SUM(H34*0.07+H34) -> 1.46376 | J28: =SUM(H34*0.07)+H34 -> 1.46376
B29: 24 | C29: =SUM(C34*0.16)+C34 -> 1.8656048 | D29: =SUM(C34*0.13)+C34 -> 1.8173564 | E29: XXX | G29: 6.35 | H29: =SUM(H34*0.11)+H34 -> 1.51848 | I29: =SUM(H34*0.08)+H34 -> 1.47744 | J29: =SUM(H34*0.08)+H34 -> 1.47744
B30: 26 | C30: =SUM(C34*0.2)+C34 -> 1.929936 | D30: =SUM(C34*0.15)+C34 -> 1.849522 | E30: XXX | G30: 8 | H30: =SUM(H34*0.11)+H34 -> 1.51848 | I30: =SUM(H34*0.08)+H34 -> 1.47744 | J30: =SUM(H34*0.08)+H34 -> 1.47744
B31: 27 | C31: =SUM(C34*0.26)+C34 -> 2.0264328 | D31: XXX | E31: XXX | G31: 9.52 | H31: =SUM(H34*0.12)+H34 -> 1.53216 | I31: =SUM(H34*0.09)+H34 -> 1.49112 | J31: =SUM(H34*0.1)+H34 -> 1.5048
B32: 30 | C32: =SUM(C34*0.32)+C34 -> 2.1229296 | D32: XXX | E32: XXX | G32: 12.7 | H32: =SUM(H34*0.12)+H34 -> 1.53216 | I32: =SUM(H34*0.09)+H34 -> 1.49112 | J32: =SUM(H34*0.1)+H34 -> 1.5048
B34: BASE | C34: =SUM(INICIO!J28) -> 1.60828 | G34: BASE | H34: =SUM(INICIO!P28) -> 1.368
B36: 3.17 | C36: 1245 | D36: S/MEL | E36: =SUM(I27*0.1)+I27 -> 1.625184 | I36: CALIDAD
B37: 4.75 | C37: 1500 | D37: S/MEL | E37: =SUM(J28*0.1)+J28 -> 1.610136 | I37: ANCHO
B38: 6.35 | C38: 1500 | D38: S/MEL | E38: =SUM(J29*0.1)+J29 -> 1.625184 | I38: ESPESOR

Sheet 16
B2: CLIENTE: | D2: =PROPER(INICIO!D29) -> Tectool / Fioreti/Buero
B4: LISTA DE PRECIOS EN PESOS
B5: DD | C5: 1000 | D5: 1220 | E5: 1500 | G5: NEGRA | H5: 1000 | I5: 1245 | J5: 1500
B6: 16 | C6: =SUM(C16*0.07)+C16 -> 2203.644 | D6: =SUM(C16*0.04)+C16 -> 2141.8596 | E6: =SUM(C16*0.04)+C16 -> 2141.8596 | G6: 1.6 | H6: XXX | I6: XXX | J6: XXX
B7: 18 | C7: =SUM(C16*0.07)+C16 -> 2203.644 | D7: =SUM(C16*0.04)+C16 -> 2141.8596 | E7: =SUM(C16*0.04)+C16 -> 2141.8596 | G7: 2 | H7: =SUM(H16*0.14)+H16 -> 1966.2688 | I7: =SUM(H16*0.11)+H16 -> 1914.5249 | J7: XXX
B8: 12,14 y 20 | C8: =SUM(C16*0.08)+C16 -> 2224.2388 | D8: =SUM(C16*0.05)+C16 -> 2162.4544 | E8: =SUM(C16*0.05)+C16 -> 2162.4544 | G8: 2.5 | H8: =SUM(H16*0.12)+H16 -> 1931.7729 | I8: =SUM(H16*0.09)+H16 -> 1880.0289 | J8: XXX
B9: 22 | C9: =SUM(C16*0.1)+C16 -> 2265.4284 | D9: =SUM(C16*0.07)+C16 -> 2203.644 | E9: =SUM(C16*0.07)+C16 -> 2203.644 | G9: 3.17 | H9: =SUM(H16*0.11)+H16 -> 1914.5249 | I9: =SUM(H16*0.08)+H16 -> 1862.781 | J9: =SUM(H16*0.08)+H16 -> 1862.781
B10: 0.65 | C10: =SUM(C16*0.12)+C16 -> 2306.618 | D10: =SUM(C16*0.09)+C16 -> 2244.8336 | E10: XXX | G10: 4,75 Y 4.00 | H10: =SUM(H16*0.1)+H16 -> 1897.2769 | I10: =SUM(H16*0.07+H16) -> 1845.533 | J10: =SUM(H16*0.07)+H16 -> 1845.533
B11: 24 | C11: =SUM(C16*0.16)+C16 -> 2388.9972 | D11: =SUM(C16*0.13)+C16 -> 2327.2128 | E11: XXX | G11: 6.35 | H11: =SUM(H16*0.11)+H16 -> 1914.5249 | I11: =SUM(H16*0.08)+H16 -> 1862.781 | J11: =SUM(H16*0.08)+H16 -> 1862.781
B12: 26 | C12: =SUM(C16*0.2)+C16 -> 2471.3764 | D12: =SUM(C16*0.15)+C16 -> 2368.4024 | E12: XXX | G12: 8 | H12: =SUM(H16*0.11)+H16 -> 1914.5249 | I12: =SUM(H16*0.08)+H16 -> 1862.781 | J12: =SUM(H16*0.08)+H16 -> 1862.781
B13: 27 | C13: =SUM(C16*0.26)+C16 -> 2594.9453 | D13: XXX | E13: XXX | G13: 9.52 | H13: =SUM(H16*0.12)+H16 -> 1931.7729 | I13: =SUM(H16*0.09)+H16 -> 1880.0289 | J13: =SUM(H16*0.09)+H16 -> 1880.0289
B14: 30 | C14: =SUM(C16*0.32)+C16 -> 2718.5141 | D14: XXX | E14: XXX | G14: 12.7 | H14: =SUM(H16*0.12)+H16 -> 1931.7729 | I14: =SUM(H16*0.09)+H16 -> 1880.0289 | J14: =SUM(H16*0.09)+H16 -> 1880.0289
B16: BASE | C16: =SUM(INICIO!K29) -> 2059.4804 | G16: BASE | H16: =SUM(INICIO!Q29) -> 1724.7972 | I16: sae 1,4 | J16: tectool-6% | K16: angosta 965
J17: buero8
B18: 3.17 | C18: 1245 | D18: S/MEL | E18: =SUM(I9*0.1)+I9 -> 2049.0591 | I18: CALIDAD | J18: fioreti -8
B19: 4.75 | C19: 1500 | D19: S/MEL | E19: =SUM(J10*0.1)+J10 -> 2030.0863 | I19: ANCHO
B20: 6.35 | C20: 1500 | D20: S/MEL | E20: =SUM(J11*0.1)+J11 -> 2049.0591 | I20: ESPESOR
B22: LISTA DE PRECIOS EN DÓLARES
B23: DD | C23: 1000 | D23: 1220 | E23: 1500 | G23: NEGRA | H23: 1000 | I23: 1245 | J23: 1500
B24: 16 | C24: =SUM(C34*0.07)+C34 -> 1.4710574 | D24: =SUM(C34*0.04)+C34 -> 1.4298128 | E24: =SUM(C34*0.04)+C34 -> 1.4298128 | G24: 1.6 | H24: XXX | I24: XXX | J24: XXX
B25: 18 | C25: =SUM(C34*0.07)+C34 -> 1.4710574 | D25: =SUM(C34*0.04)+C34 -> 1.4298128 | E25: =SUM(C34*0.04)+C34 -> 1.4298128 | G25: 2 | H25: =SUM(H34*0.14)+H34 -> 1.312596 | I25: =SUM(H34*0.11)+H34 -> 1.278054 | J25: XXX
B26: 12,14 y 20 | C26: =SUM(C34*0.08)+C34 -> 1.4848056 | D26: =SUM(C34*0.05)+C34 -> 1.443561 | E26: =SUM(C34*0.05)+C34 -> 1.443561 | G26: 2.5 | H26: =SUM(H34*0.12)+H34 -> 1.289568 | I26: =SUM(H34*0.09)+H34 -> 1.255026 | J26: XXX
B27: 22 | C27: =SUM(C34*0.1)+C34 -> 1.512302 | D27: =SUM(C34*0.07)+C34 -> 1.4710574 | E27: =SUM(C34*0.07)+C34 -> 1.4710574 | G27: 3.17 | H27: =SUM(H34*0.11)+H34 -> 1.278054 | I27: =SUM(H34*0.08)+H34 -> 1.243512 | J27: =SUM(H34*0.08)+H34 -> 1.243512
B28: 0.65 | C28: =SUM(C34*0.12)+C34 -> 1.5397984 | D28: =SUM(C34*0.09)+C34 -> 1.4985538 | E28: XXX | G28: 4,75 Y 4.00 | H28: =SUM(H34*0.1)+H34 -> 1.26654 | I28: =SUM(H34*0.07+H34) -> 1.231998 | J28: =SUM(H34*0.07)+H34 -> 1.231998
B29: 24 | C29: =SUM(C34*0.16)+C34 -> 1.5947912 | D29: =SUM(C34*0.13)+C34 -> 1.5535466 | E29: XXX | G29: 6.35 | H29: =SUM(H34*0.11)+H34 -> 1.278054 | I29: =SUM(H34*0.08)+H34 -> 1.243512 | J29: =SUM(H34*0.08)+H34 -> 1.243512
B30: 26 | C30: =SUM(C34*0.2)+C34 -> 1.649784 | D30: =SUM(C34*0.15)+C34 -> 1.581043 | E30: XXX | G30: 8 | H30: =SUM(H34*0.11)+H34 -> 1.278054 | I30: =SUM(H34*0.08)+H34 -> 1.243512 | J30: =SUM(H34*0.08)+H34 -> 1.243512
B31: 27 | C31: =SUM(C34*0.26)+C34 -> 1.7322732 | D31: XXX | E31: XXX | G31: 9.52 | H31: =SUM(H34*0.12)+H34 -> 1.289568 | I31: =SUM(H34*0.09)+H34 -> 1.255026 | J31: =SUM(H34*0.09)+H34 -> 1.255026
B32: 30 | C32: =SUM(C34*0.32)+C34 -> 1.8147624 | D32: XXX | E32: XXX | G32: 12.7 | H32: =SUM(H34*0.12)+H34 -> 1.289568 | I32: =SUM(H34*0.09)+H34 -> 1.255026 | J32: =SUM(H34*0.09)+H34 -> 1.255026
B34: BASE | C34: =SUM(INICIO!J29) -> 1.37482 | G34: BASE | H34: =SUM(INICIO!P29) -> 1.1514
B36: 3.17 | C36: 1245 | D36: S/MEL | E36: =SUM(I27*0.1)+I27 -> 1.3678632 | I36: CALIDAD
B37: 4.75 | C37: 1500 | D37: S/MEL | E37: =SUM(J28*0.1)+J28 -> 1.3551978 | I37: ANCHO
B38: 6.35 | C38: 1500 | D38: S/MEL | E38: =SUM(J29*0.1)+J29 -> 1.3678632 | I38: ESPESOR

Sheet 17
B2: CLIENTE: | D2: =PROPER(INICIO!D30) -> Talleres Navales/Burner/Eqa
B4: LISTA DE PRECIOS EN PESOS
B5: DD | C5: 1000 | D5: 1220 | E5: 1500 | G5: NEGRA | H5: 1000 | I5: 1245 | J5: 1500
B6: 16 | C6: =SUM(C16*0.07)+C16 -> 2286.8004 | D6: =SUM(C16*0.04)+C16 -> 2222.6845 | E6: =SUM(C16*0.04)+C16 -> 2222.6845 | G6: 1.6 | H6: XXX | I6: XXX | J6: XXX
B7: 18 | C7: =SUM(C16*0.07)+C16 -> 2286.8004 | D7: =SUM(C16*0.04)+C16 -> 2222.6845 | E7: =SUM(C16*0.04)+C16 -> 2222.6845 | G7: 2 | H7: =SUM(H16*0.14)+H16 -> 2102.5449 | I7: =SUM(H16*0.11)+H16 -> 2047.2147 | J7: XXX
B8: 12,14 y 20 | C8: =SUM(C16*0.08)+C16 -> 2308.1723 | D8: =SUM(C16*0.05)+C16 -> 2244.0564 | E8: =SUM(C16*0.05)+C16 -> 2244.0564 | G8: 2.5 | H8: =SUM(H16*0.12)+H16 -> 2065.6581 | I8: =SUM(H16*0.09)+H16 -> 2010.328 | J8: XXX
B9: 22 | C9: =SUM(C16*0.1)+C16 -> 2350.9163 | D9: =SUM(C16*0.07)+C16 -> 2286.8004 | E9: =SUM(C16*0.07)+C16 -> 2286.8004 | G9: 3.17 | H9: =SUM(H16*0.11)+H16 -> 2047.2147 | I9: =SUM(H16*0.08)+H16 -> 1991.8846 | J9: =SUM(H16*0.08)+H16 -> 1991.8846
B10: 0.65 | C10: =SUM(C16*0.12)+C16 -> 2393.6602 | D10: =SUM(C16*0.09)+C16 -> 2329.5443 | E10: XXX | G10: 4,75 Y 4.00 | H10: =SUM(H16*0.1)+H16 -> 2028.7714 | I10: =SUM(H16*0.07+H16) -> 1973.4412 | J10: =SUM(H16*0.07)+H16 -> 1973.4412
B11: 24 | C11: =SUM(C16*0.16)+C16 -> 2479.1481 | D11: =SUM(C16*0.13)+C16 -> 2415.0322 | E11: XXX | G11: 6.35 | H11: =SUM(H16*0.11)+H16 -> 2047.2147 | I11: =SUM(H16*0.08)+H16 -> 1991.8846 | J11: =SUM(H16*0.08)+H16 -> 1991.8846
B12: 26 | C12: =SUM(C16*0.2)+C16 -> 2564.6359 | D12: =SUM(C16*0.15)+C16 -> 2457.7761 | E12: XXX | G12: 8 | H12: =SUM(H16*0.11)+H16 -> 2047.2147 | I12: =SUM(H16*0.08)+H16 -> 1991.8846 | J12: =SUM(H16*0.08)+H16 -> 1991.8846
B13: 27 | C13: =SUM(C16*0.26)+C16 -> 2692.8677 | D13: XXX | E13: XXX | G13: 9.52 | H13: =SUM(H16*0.12)+H16 -> 2065.6581 | I13: =SUM(H16*0.09)+H16 -> 2010.328 | J13: =SUM(H16*0.1)+H16 -> 2028.7714
B14: 30 | C14: =SUM(C16*0.32)+C16 -> 2821.0995 | D14: XXX | E14: XXX | G14: 12.7 | H14: =SUM(H16*0.12)+H16 -> 2065.6581 | I14: =SUM(H16*0.09)+H16 -> 2010.328 | J14: =SUM(H16*0.1)+H16 -> 2028.7714
B16: BASE | C16: =SUM(INICIO!K30) -> 2137.1966 | G16: BASE | H16: =SUM(INICIO!Q30) -> 1844.3376 | I16: gruesa | J16: 2.03
B18: 3.17 | C18: 1245 | D18: S/MEL | E18: =SUM(I9*0.1)+I9 -> 2191.0731 | I18: CALIDAD
B19: 4.75 | C19: 1500 | D19: S/MEL | E19: =SUM(J10*0.1)+J10 -> 2170.7854 | I19: ANCHO
B20: 6.35 | C20: 1500 | D20: S/MEL | E20: =SUM(J11*0.1)+J11 -> 2191.0731 | I20: ESPESOR
B22: LISTA DE PRECIOS EN DÓLARES
B23: DD | C23: 1000 | D23: 1220 | E23: 1500 | G23: NEGRA | H23: 1000 | I23: 1245 | J23: 1500
B24: 16 | C24: =SUM(C34*0.07)+C34 -> 1.526569 | D24: =SUM(C34*0.04)+C34 -> 1.483768 | E24: =SUM(C34*0.04)+C34 -> 1.483768 | G24: 1.6 | H24: XXX | I24: XXX | J24: XXX
B25: 18 | C25: =SUM(C34*0.07)+C34 -> 1.526569 | D25: =SUM(C34*0.04)+C34 -> 1.483768 | E25: =SUM(C34*0.04)+C34 -> 1.483768 | G25: 2 | H25: =SUM(H34*0.14)+H34 -> 1.403568 | I25: =SUM(H34*0.11)+H34 -> 1.366632 | J25: XXX
B26: 12,14 y 20 | C26: =SUM(C34*0.08)+C34 -> 1.540836 | D26: =SUM(C34*0.05)+C34 -> 1.498035 | E26: =SUM(C34*0.05)+C34 -> 1.498035 | G26: 2.5 | H26: =SUM(H34*0.12)+H34 -> 1.378944 | I26: =SUM(H34*0.09)+H34 -> 1.342008 | J26: XXX
B27: 22 | C27: =SUM(C34*0.1)+C34 -> 1.56937 | D27: =SUM(C34*0.07)+C34 -> 1.526569 | E27: =SUM(C34*0.07)+C34 -> 1.526569 | G27: 3.17 | H27: =SUM(H34*0.11)+H34 -> 1.366632 | I27: =SUM(H34*0.08)+H34 -> 1.329696 | J27: =SUM(H34*0.08)+H34 -> 1.329696
B28: 0.65 | C28: =SUM(C34*0.12)+C34 -> 1.597904 | D28: =SUM(C34*0.09)+C34 -> 1.555103 | E28: XXX | G28: 4,75 Y 4.00 | H28: =SUM(H34*0.1)+H34 -> 1.35432 | I28: =SUM(H34*0.07+H34) -> 1.317384 | J28: =SUM(H34*0.07)+H34 -> 1.317384
B29: 24 | C29: =SUM(C34*0.16)+C34 -> 1.654972 | D29: =SUM(C34*0.13)+C34 -> 1.612171 | E29: XXX | G29: 6.35 | H29: =SUM(H34*0.11)+H34 -> 1.366632 | I29: =SUM(H34*0.08)+H34 -> 1.329696 | J29: =SUM(H34*0.08)+H34 -> 1.329696
B30: 26 | C30: =SUM(C34*0.2)+C34 -> 1.71204 | D30: =SUM(C34*0.15)+C34 -> 1.640705 | E30: XXX | G30: 8 | H30: =SUM(H34*0.11)+H34 -> 1.366632 | I30: =SUM(H34*0.08)+H34 -> 1.329696 | J30: =SUM(H34*0.08)+H34 -> 1.329696
B31: 27 | C31: =SUM(C34*0.26)+C34 -> 1.797642 | D31: XXX | E31: XXX | G31: 9.52 | H31: =SUM(H34*0.12)+H34 -> 1.378944 | I31: =SUM(H34*0.09)+H34 -> 1.342008 | J31: =SUM(H34*0.1)+H34 -> 1.35432
B32: 30 | C32: =SUM(C34*0.32)+C34 -> 1.883244 | D32: XXX | E32: XXX | G32: 12.7 | H32: =SUM(H34*0.12)+H34 -> 1.378944 | I32: =SUM(H34*0.09)+H34 -> 1.342008 | J32: =SUM(H34*0.1)+H34 -> 1.35432
B34: BASE | C34: =SUM(INICIO!J30) -> 1.4267 | G34: BASE | H34: =SUM(INICIO!P30) -> 1.2312
B36: 3.17 | C36: 1245 | D36: S/MEL | E36: =SUM(I27*0.1)+I27 -> 1.4626656 | I36: CALIDAD
B37: 4.75 | C37: 1500 | D37: S/MEL | E37: =SUM(J28*0.1)+J28 -> 1.4491224 | I37: ANCHO
B38: 6.35 | C38: 1500 | D38: S/MEL | E38: =SUM(J29*0.1)+J29 -> 1.4626656 | I38: ESPESOR
C41: burner
B42: 20x50x1,2 | C42: 13.92
B43: 20x20x1,2 | C43: 7.96

Sheet 18
B2: CLIENTE: | D2: =PROPER(INICIO!D31) -> Provimar/Puertas/Campana/Multilift//Am Carrocerias/Megaces
B4: LISTA DE PRECIOS EN PESOS
B5: DD | C5: 1000 | D5: 1220 | E5: 1500 | G5: NEGRA | H5: 1000 | I5: 1245 | J5: 1500
B6: 16 | C6: =SUM(C16*0.07)+C16 -> 2286.8004 | D6: =SUM(C16*0.04)+C16 -> 2222.6845 | E6: =SUM(C16*0.04)+C16 -> 2222.6845 | G6: 1.6 | H6: XXX | I6: XXX | J6: XXX
B7: 18 | C7: =SUM(C16*0.07)+C16 -> 2286.8004 | D7: =SUM(C16*0.04)+C16 -> 2222.6845 | E7: =SUM(C16*0.04)+C16 -> 2222.6845 | G7: 2 | H7: =SUM(H16*0.14)+H16 -> 2102.5449 | I7: =SUM(H16*0.11)+H16 -> 2047.2147 | J7: XXX
B8: 12,14 y 20 | C8: =SUM(C16*0.08)+C16 -> 2308.1723 | D8: =SUM(C16*0.05)+C16 -> 2244.0564 | E8: =SUM(C16*0.05)+C16 -> 2244.0564 | G8: 2.5 | H8: =SUM(H16*0.12)+H16 -> 2065.6581 | I8: =SUM(H16*0.09)+H16 -> 2010.328 | J8: XXX
B9: 22 | C9: =SUM(C16*0.1)+C16 -> 2350.9163 | D9: =SUM(C16*0.07)+C16 -> 2286.8004 | E9: =SUM(C16*0.07)+C16 -> 2286.8004 | G9: 3.17 | H9: =SUM(H16*0.11)+H16 -> 2047.2147 | I9: =SUM(H16*0.08)+H16 -> 1991.8846 | J9: =SUM(H16*0.08)+H16 -> 1991.8846
B10: 0.65 | C10: =SUM(C16*0.12)+C16 -> 2393.6602 | D10: =SUM(C16*0.09)+C16 -> 2329.5443 | E10: XXX | G10: 4,75 Y 4.00 | H10: =SUM(H16*0.11)+H16 -> 2047.2147 | I10: =SUM(H16*0.08+H16) -> 1991.8846 | J10: =SUM(H16*0.08)+H16 -> 1991.8846
B11: 24 | C11: =SUM(C16*0.16)+C16 -> 2479.1481 | D11: =SUM(C16*0.13)+C16 -> 2415.0322 | E11: XXX | G11: 6.35 | H11: =SUM(H16*0.11)+H16 -> 2047.2147 | I11: =SUM(H16*0.08)+H16 -> 1991.8846 | J11: =SUM(H16*0.08)+H16 -> 1991.8846
B12: 26 | C12: =SUM(C16*0.2)+C16 -> 2564.6359 | D12: =SUM(C16*0.15)+C16 -> 2457.7761 | E12: XXX | G12: 8 | H12: =SUM(H16*0.11)+H16 -> 2047.2147 | I12: =SUM(H16*0.08)+H16 -> 1991.8846 | J12: =SUM(H16*0.08)+H16 -> 1991.8846
B13: 27 | C13: =SUM(C16*0.26)+C16 -> 2692.8677 | D13: XXX | E13: XXX | G13: 9.52 | H13: =SUM(H16*0.12)+H16 -> 2065.6581 | I13: =SUM(H16*0.09)+H16 -> 2010.328 | J13: =SUM(H16*0.1)+H16 -> 2028.7714
B14: 30 | C14: =SUM(C16*0.32)+C16 -> 2821.0995 | D14: XXX | E14: XXX | G14: 12.7 | H14: =SUM(H16*0.12)+H16 -> 2065.6581 | I14: =SUM(H16*0.09)+H16 -> 2010.328 | J14: =SUM(H16*0.1)+H16 -> 2028.7714
B16: BASE | C16: =SUM(INICIO!K31) -> 2137.1966 | G16: BASE | H16: =SUM(INICIO!Q31) -> 1844.3376
B18: 3.17 | C18: 1245 | D18: S/MEL | E18: =SUM(I9*0.1)+I9 -> 2191.0731 | I18: CALIDAD
B19: 4.75 | C19: 1500 | D19: S/MEL | E19: =SUM(J10*0.1)+J10 -> 2191.0731 | I19: ANCHO
B20: 6.35 | C20: 1500 | D20: S/MEL | E20: =SUM(J11*0.1)+J11 -> 2191.0731 | I20: ESPESOR
B22: LISTA DE PRECIOS EN DÓLARES
B23: DD | C23: 1000 | D23: 1220 | E23: 1500 | G23: NEGRA | H23: 1000 | I23: 1245 | J23: 1500
B24: 16 | C24: =SUM(C34*0.07)+C34 -> 1.526569 | D24: =SUM(C34*0.04)+C34 -> 1.483768 | E24: =SUM(C34*0.04)+C34 -> 1.483768 | G24: 1.6 | H24: XXX | I24: XXX | J24: XXX
B25: 18 | C25: =SUM(C34*0.07)+C34 -> 1.526569 | D25: =SUM(C34*0.04)+C34 -> 1.483768 | E25: =SUM(C34*0.04)+C34 -> 1.483768 | G25: 2 | H25: =SUM(H34*0.14)+H34 -> 1.403568 | I25: =SUM(H34*0.11)+H34 -> 1.366632 | J25: XXX
B26: 12,14 y 20 | C26: =SUM(C34*0.08)+C34 -> 1.540836 | D26: =SUM(C34*0.05)+C34 -> 1.498035 | E26: =SUM(C34*0.05)+C34 -> 1.498035 | G26: 2.5 | H26: =SUM(H34*0.12)+H34 -> 1.378944 | I26: =SUM(H34*0.09)+H34 -> 1.342008 | J26: XXX
B27: 22 | C27: =SUM(C34*0.1)+C34 -> 1.56937 | D27: =SUM(C34*0.07)+C34 -> 1.526569 | E27: =SUM(C34*0.07)+C34 -> 1.526569 | G27: 3.17 | H27: =SUM(H34*0.11)+H34 -> 1.366632 | I27: =SUM(H34*0.08)+H34 -> 1.329696 | J27: =SUM(H34*0.08)+H34 -> 1.329696
B28: 0.65 | C28: =SUM(C34*0.12)+C34 -> 1.597904 | D28: =SUM(C34*0.09)+C34 -> 1.555103 | E28: XXX | G28: 4,75 Y 4.00 | H28: =SUM(H34*0.11)+H34 -> 1.366632 | I28: =SUM(H34*0.08+H34) -> 1.329696 | J28: =SUM(H34*0.08)+H34 -> 1.329696
B29: 24 | C29: =SUM(C34*0.16)+C34 -> 1.654972 | D29: =SUM(C34*0.13)+C34 -> 1.612171 | E29: XXX | G29: 6.35 | H29: =SUM(H34*0.11)+H34 -> 1.366632 | I29: =SUM(H34*0.08)+H34 -> 1.329696 | J29: =SUM(H34*0.08)+H34 -> 1.329696
B30: 26 | C30: =SUM(C34*0.2)+C34 -> 1.71204 | D30: =SUM(C34*0.15)+C34 -> 1.640705 | E30: XXX | G30: 8 | H30: =SUM(H34*0.11)+H34 -> 1.366632 | I30: =SUM(H34*0.08)+H34 -> 1.329696 | J30: =SUM(H34*0.08)+H34 -> 1.329696
B31: 27 | C31: =SUM(C34*0.26)+C34 -> 1.797642 | D31: XXX | E31: XXX | G31: 9.52 | H31: =SUM(H34*0.12)+H34 -> 1.378944 | I31: =SUM(H34*0.09)+H34 -> 1.342008 | J31: =SUM(H34*0.1)+H34 -> 1.35432
B32: 30 | C32: =SUM(C34*0.32)+C34 -> 1.883244 | D32: XXX | E32: XXX | G32: 12.7 | H32: =SUM(H34*0.12)+H34 -> 1.378944 | I32: =SUM(H34*0.09)+H34 -> 1.342008 | J32: =SUM(H34*0.1)+H34 -> 1.35432
B34: BASE | C34: =SUM(INICIO!J31) -> 1.4267 | G34: BASE | H34: =SUM(INICIO!P31) -> 1.2312
B36: 3.17 | C36: 1245 | D36: S/MEL | E36: =SUM(I27*0.1)+I27 -> 1.4626656 | I36: CALIDAD
B37: 4.75 | C37: 1500 | D37: S/MEL | E37: =SUM(J28*0.1)+J28 -> 1.4626656 | I37: ANCHO
B38: 6.35 | C38: 1500 | D38: S/MEL | E38: =SUM(J29*0.1)+J29 -> 1.4626656 | I38: ESPESOR

Sheet 19
B2: CLIENTE: | D2: =PROPER(INICIO!D32) -> Barrera/Aceba/Diegez/Fitnes
B4: LISTA DE PRECIOS EN PESOS
B5: DD | C5: 1000 | D5: 1220 | E5: 1500 | G5: NEGRA | H5: 1000 | I5: 1245 | J5: 1500
B6: 16 | C6: =SUM(C16*0.07)+C16 -> 2245.2222 | D6: =SUM(C16*0.04)+C16 -> 2182.272 | E6: =SUM(C16*0.04)+C16 -> 2182.272 | G6: 1.6 | H6: XXX | I6: XXX | J6: XXX
B7: 18 | C7: =SUM(C16*0.07)+C16 -> 2245.2222 | D7: =SUM(C16*0.04)+C16 -> 2182.272 | E7: =SUM(C16*0.04)+C16 -> 2182.272 | G7: 2 | H7: =SUM(H16*0.14)+H16 -> 2024.6728 | I7: =SUM(H16*0.11)+H16 -> 1971.392 | J7: XXX
B8: 12,14 y 20 | C8: =SUM(C16*0.08)+C16 -> 2266.2056 | D8: =SUM(C16*0.05)+C16 -> 2203.2554 | E8: =SUM(C16*0.05)+C16 -> 2203.2554 | G8: 2.5 | H8: =SUM(H16*0.12)+H16 -> 1989.1523 | I8: =SUM(H16*0.09)+H16 -> 1935.8714 | J8: XXX
B9: 22 | C9: =SUM(C16*0.1)+C16 -> 2308.1723 | D9: =SUM(C16*0.07)+C16 -> 2245.2222 | E9: =SUM(C16*0.07)+C16 -> 2245.2222 | G9: 3.17 | H9: =SUM(H16*0.11)+H16 -> 1971.392 | I9: =SUM(H16*0.08)+H16 -> 1918.1111 | J9: =SUM(H16*0.08)+H16 -> 1918.1111
B10: 0.65 | C10: =SUM(C16*0.12)+C16 -> 2350.1391 | D10: =SUM(C16*0.09)+C16 -> 2287.1889 | E10: XXX | G10: 4,75 Y 4.00 | H10: =SUM(H16*0.1)+H16 -> 1953.6317 | I10: =SUM(H16*0.07+H16) -> 1900.3508 | J10: =SUM(H16*0.07)+H16 -> 1900.3508
B11: 24 | C11: =SUM(C16*0.16)+C16 -> 2434.0726 | D11: =SUM(C16*0.13)+C16 -> 2371.1225 | E11: XXX | G11: 6.35 | H11: =SUM(H16*0.11)+H16 -> 1971.392 | I11: =SUM(H16*0.08)+H16 -> 1918.1111 | J11: =SUM(H16*0.08)+H16 -> 1918.1111
B12: 26 | C12: =SUM(C16*0.2)+C16 -> 2518.0062 | D12: =SUM(C16*0.15)+C16 -> 2413.0893 | E12: XXX | G12: 8 | H12: =SUM(H16*0.11)+H16 -> 1971.392 | I12: =SUM(H16*0.08)+H16 -> 1918.1111 | J12: =SUM(H16*0.08)+H16 -> 1918.1111
B13: 27 | C13: =SUM(C16*0.26)+C16 -> 2643.9065 | D13: XXX | E13: XXX | G13: 9.52 | H13: =SUM(H16*0.12)+H16 -> 1989.1523 | I13: =SUM(H16*0.09)+H16 -> 1935.8714 | J13: =SUM(H16*0.1)+H16 -> 1953.6317
B14: 30 | C14: =SUM(C16*0.32)+C16 -> 2769.8068 | D14: XXX | E14: XXX | G14: 12.7 | H14: =SUM(H16*0.12)+H16 -> 1989.1523 | I14: =SUM(H16*0.09)+H16 -> 1935.8714 | J14: =SUM(H16*0.1)+H16 -> 1953.6317
B16: BASE | C16: =SUM(INICIO!K32) -> 2098.3385 | G16: BASE | H16: =SUM(INICIO!Q32) -> 1776.0288 | J16: fitnes -8 | L16: aceba -10
J17: 2,9 -11%
B18: 3.17 | C18: 1245 | D18: S/MEL | E18: =SUM(I9*0.1)+I9 -> 2109.9222 | I18: CALIDAD
B19: 4.75 | C19: 1500 | D19: S/MEL | E19: =SUM(J10*0.1)+J10 -> 2090.3859 | I19: ANCHO
B20: 6.35 | C20: 1500 | D20: S/MEL | E20: =SUM(J11*0.1)+J11 -> 2109.9222 | I20: ESPESOR
B22: LISTA DE PRECIOS EN DÓLARES
B23: DD | C23: 1000 | D23: 1220 | E23: 1500 | G23: NEGRA | H23: 1000 | I23: 1245 | J23: 1500
B24: 16 | C24: =SUM(C34*0.07)+C34 -> 1.4988132 | D24: =SUM(C34*0.04)+C34 -> 1.4567904 | E24: =SUM(C34*0.04)+C34 -> 1.4567904 | G24: 1.6 | H24: XXX | I24: XXX | J24: XXX
B25: 18 | C25: =SUM(C34*0.07)+C34 -> 1.4988132 | D25: =SUM(C34*0.04)+C34 -> 1.4567904 | E25: =SUM(C34*0.04)+C34 -> 1.4567904 | G25: 2 | H25: =SUM(H34*0.14)+H34 -> 1.351584 | I25: =SUM(H34*0.11)+H34 -> 1.316016 | J25: XXX
B26: 12,14 y 20 | C26: =SUM(C34*0.08)+C34 -> 1.5128208 | D26: =SUM(C34*0.05)+C34 -> 1.470798 | E26: =SUM(C34*0.05)+C34 -> 1.470798 | G26: 2.5 | H26: =SUM(H34*0.12)+H34 -> 1.327872 | I26: =SUM(H34*0.09)+H34 -> 1.292304 | J26: XXX
B27: 22 | C27: =SUM(C34*0.1)+C34 -> 1.540836 | D27: =SUM(C34*0.07)+C34 -> 1.4988132 | E27: =SUM(C34*0.07)+C34 -> 1.4988132 | G27: 3.17 | H27: =SUM(H34*0.11)+H34 -> 1.316016 | I27: =SUM(H34*0.08)+H34 -> 1.280448 | J27: =SUM(H34*0.08)+H34 -> 1.280448
B28: 0.65 | C28: =SUM(C34*0.12)+C34 -> 1.5688512 | D28: =SUM(C34*0.09)+C34 -> 1.5268284 | E28: XXX | G28: 4,75 Y 4.00 | H28: =SUM(H34*0.1)+H34 -> 1.30416 | I28: =SUM(H34*0.07+H34) -> 1.268592 | J28: =SUM(H34*0.07)+H34 -> 1.268592
B29: 24 | C29: =SUM(C34*0.16)+C34 -> 1.6248816 | D29: =SUM(C34*0.13)+C34 -> 1.5828588 | E29: XXX | G29: 6.35 | H29: =SUM(H34*0.11)+H34 -> 1.316016 | I29: =SUM(H34*0.08)+H34 -> 1.280448 | J29: =SUM(H34*0.08)+H34 -> 1.280448
B30: 26 | C30: =SUM(C34*0.2)+C34 -> 1.680912 | D30: =SUM(C34*0.15)+C34 -> 1.610874 | E30: XXX | G30: 8 | H30: =SUM(H34*0.11)+H34 -> 1.316016 | I30: =SUM(H34*0.08)+H34 -> 1.280448 | J30: =SUM(H34*0.08)+H34 -> 1.280448
B31: 27 | C31: =SUM(C34*0.26)+C34 -> 1.7649576 | D31: XXX | E31: XXX | G31: 9.52 | H31: =SUM(H34*0.12)+H34 -> 1.327872 | I31: =SUM(H34*0.09)+H34 -> 1.292304 | J31: =SUM(H34*0.1)+H34 -> 1.30416
B32: 30 | C32: =SUM(C34*0.32)+C34 -> 1.8490032 | D32: XXX | E32: XXX | G32: 12.7 | H32: =SUM(H34*0.12)+H34 -> 1.327872 | I32: =SUM(H34*0.09)+H34 -> 1.292304 | J32: =SUM(H34*0.1)+H34 -> 1.30416
B34: BASE | C34: =SUM(INICIO!J32) -> 1.40076 | G34: BASE | H34: =SUM(INICIO!P32) -> 1.1856
B36: 3.17 | C36: 1245 | D36: S/MEL | E36: =SUM(I27*0.1)+I27 -> 1.4084928 | I36: CALIDAD
B37: 4.75 | C37: 1500 | D37: S/MEL | E37: =SUM(J28*0.1)+J28 -> 1.3954512 | I37: ANCHO
B38: 6.35 | C38: 1500 | D38: S/MEL | E38: =SUM(J29*0.1)+J29 -> 1.4084928 | I38: ESPESOR

Sheet 20
B2: CLIENTE: | D2: =PROPER(INICIO!D33) -> Covic/Acerotec/Frachia/Beta
B4: LISTA DE PRECIOS EN PESOS
B5: DD | C5: 1000 | D5: 1220 | E5: 1500 | G5: NEGRA | H5: 1000 | I5: 1245 | J5: 1500
B6: 16 | C6: =SUM(C16*0.07)+C16 -> 2328.3786 | D6: =SUM(C16*0.04)+C16 -> 2263.0969 | E6: =SUM(C16*0.04)+C16 -> 2263.0969 | G6: 1.6 | H6: XXX | I6: XXX | J6: XXX
B7: 18 | C7: =SUM(C16*0.07)+C16 -> 2328.3786 | D7: =SUM(C16*0.04)+C16 -> 2263.0969 | E7: =SUM(C16*0.04)+C16 -> 2263.0969 | G7: 2 | H7: =SUM(H16*0.14)+H16 -> 2122.0129 | I7: =SUM(H16*0.11)+H16 -> 2066.1704 | J7: XXX
B8: 12,14 y 20 | C8: =SUM(C16*0.08)+C16 -> 2350.1391 | D8: =SUM(C16*0.05)+C16 -> 2284.8575 | E8: =SUM(C16*0.05)+C16 -> 2284.8575 | G8: 2.5 | H8: =SUM(H16*0.12)+H16 -> 2084.7846 | I8: =SUM(H16*0.09)+H16 -> 2028.9421 | J8: XXX
B9: 22 | C9: =SUM(C16*0.1)+C16 -> 2393.6602 | D9: =SUM(C16*0.07)+C16 -> 2328.3786 | E9: =SUM(C16*0.07)+C16 -> 2328.3786 | G9: 3.17 | H9: =SUM(H16*0.11)+H16 -> 2066.1704 | I9: =SUM(H16*0.08)+H16 -> 2010.328 | J9: =SUM(H16*0.08)+H16 -> 2010.328
B10: 0.65 | C10: =SUM(C16*0.12)+C16 -> 2437.1813 | D10: =SUM(C16*0.09)+C16 -> 2371.8996 | E10: XXX | G10: 4,75 Y 4.00 | H10: =SUM(H16*0.1)+H16 -> 2047.5563 | I10: =SUM(H16*0.07+H16) -> 1991.7138 | J10: =SUM(H16*0.07)+H16 -> 1991.7138
B11: 24 | C11: =SUM(C16*0.16)+C16 -> 2524.2235 | D11: =SUM(C16*0.13)+C16 -> 2458.9418 | E11: XXX | G11: 6.35 | H11: =SUM(H16*0.11)+H16 -> 2066.1704 | I11: =SUM(H16*0.08)+H16 -> 2010.328 | J11: =SUM(H16*0.08)+H16 -> 2010.328
B12: 26 | C12: =SUM(C16*0.2)+C16 -> 2611.2657 | D12: =SUM(C16*0.15)+C16 -> 2502.4629 | E12: XXX | G12: 8 | H12: =SUM(H16*0.11)+H16 -> 2066.1704 | I12: =SUM(H16*0.08)+H16 -> 2010.328 | J12: =SUM(H16*0.08)+H16 -> 2010.328
B13: 27 | C13: =SUM(C16*0.26)+C16 -> 2741.8289 | D13: XXX | E13: XXX | G13: 9.52 | H13: =SUM(H16*0.12)+H16 -> 2084.7846 | I13: =SUM(H16*0.09)+H16 -> 2028.9421 | J13: =SUM(H16*0.1)+H16 -> 2047.5563
B14: 30 | C14: =SUM(C16*0.32)+C16 -> 2872.3922 | D14: XXX | E14: XXX | G14: 12.7 | H14: =SUM(H16*0.12)+H16 -> 2084.7846 | I14: =SUM(H16*0.09)+H16 -> 2028.9421 | J14: =SUM(H16*0.1)+H16 -> 2047.5563
B16: BASE | C16: =SUM(INICIO!K33) -> 2176.0547 | G16: BASE | H16: =SUM(INICIO!Q33) -> 1861.4148
B18: 3.17 | C18: 1245 | D18: S/MEL | E18: =SUM(I9*0.1)+I9 -> 2211.3608 | I18: CALIDAD
B19: 4.75 | C19: 1500 | D19: S/MEL | E19: =SUM(J10*0.1)+J10 -> 2190.8852 | I19: ANCHO
B20: 6.35 | C20: 1500 | D20: S/MEL | E20: =SUM(J11*0.1)+J11 -> 2211.3608 | I20: ESPESOR
B22: LISTA DE PRECIOS EN DÓLARES
B23: DD | C23: 1000 | D23: 1220 | E23: 1500 | G23: NEGRA | H23: 1000 | I23: 1245 | J23: 1500
B24: 16 | C24: =SUM(C34*0.07)+C34 -> 1.5543248 | D24: =SUM(C34*0.04)+C34 -> 1.5107456 | E24: =SUM(C34*0.04)+C34 -> 1.5107456 | G24: 1.6 | H24: XXX | I24: XXX | J24: XXX
B25: 18 | C25: =SUM(C34*0.07)+C34 -> 1.5543248 | D25: =SUM(C34*0.04)+C34 -> 1.5107456 | E25: =SUM(C34*0.04)+C34 -> 1.5107456 | G25: 2 | H25: =SUM(H34*0.14)+H34 -> 1.416564 | I25: =SUM(H34*0.11)+H34 -> 1.379286 | J25: XXX
B26: 12,14 y 20 | C26: =SUM(C34*0.08)+C34 -> 1.5688512 | D26: =SUM(C34*0.05)+C34 -> 1.525272 | E26: =SUM(C34*0.05)+C34 -> 1.525272 | G26: 2.5 | H26: =SUM(H34*0.12)+H34 -> 1.391712 | I26: =SUM(H34*0.09)+H34 -> 1.354434 | J26: XXX
B27: 22 | C27: =SUM(C34*0.1)+C34 -> 1.597904 | D27: =SUM(C34*0.07)+C34 -> 1.5543248 | E27: =SUM(C34*0.07)+C34 -> 1.5543248 | G27: 3.17 | H27: =SUM(H34*0.11)+H34 -> 1.379286 | I27: =SUM(H34*0.08)+H34 -> 1.342008 | J27: =SUM(H34*0.08)+H34 -> 1.342008
B28: 0.65 | C28: =SUM(C34*0.12)+C34 -> 1.6269568 | D28: =SUM(C34*0.09)+C34 -> 1.5833776 | E28: XXX | G28: 4,75 Y 4.00 | H28: =SUM(H34*0.1)+H34 -> 1.36686 | I28: =SUM(H34*0.07+H34) -> 1.329582 | J28: =SUM(H34*0.07)+H34 -> 1.329582
B29: 24 | C29: =SUM(C34*0.16)+C34 -> 1.6850624 | D29: =SUM(C34*0.13)+C34 -> 1.6414832 | E29: XXX | G29: 6.35 | H29: =SUM(H34*0.11)+H34 -> 1.379286 | I29: =SUM(H34*0.08)+H34 -> 1.342008 | J29: =SUM(H34*0.08)+H34 -> 1.342008
B30: 26 | C30: =SUM(C34*0.2)+C34 -> 1.743168 | D30: =SUM(C34*0.15)+C34 -> 1.670536 | E30: XXX | G30: 8 | H30: =SUM(H34*0.11)+H34 -> 1.379286 | I30: =SUM(H34*0.08)+H34 -> 1.342008 | J30: =SUM(H34*0.08)+H34 -> 1.342008
B31: 27 | C31: =SUM(C34*0.26)+C34 -> 1.8303264 | D31: XXX | E31: XXX | G31: 9.52 | H31: =SUM(H34*0.12)+H34 -> 1.391712 | I31: =SUM(H34*0.09)+H34 -> 1.354434 | J31: =SUM(H34*0.1)+H34 -> 1.36686
B32: 30 | C32: =SUM(C34*0.32)+C34 -> 1.9174848 | D32: XXX | E32: XXX | G32: 12.7 | H32: =SUM(H34*0.12)+H34 -> 1.391712 | I32: =SUM(H34*0.09)+H34 -> 1.354434 | J32: =SUM(H34*0.1)+H34 -> 1.36686
B34: BASE | C34: =SUM(INICIO!J33) -> 1.45264 | G34: BASE | H34: =SUM(INICIO!P33) -> 1.2426
B36: 3.17 | C36: 1245 | D36: S/MEL | E36: =SUM(I27*0.1)+I27 -> 1.4762088 | I36: CALIDAD
B37: 4.75 | C37: 1500 | D37: S/MEL | E37: =SUM(J28*0.1)+J28 -> 1.4625402 | I37: ANCHO
B38: 6.35 | C38: 1500 | D38: S/MEL | E38: =SUM(J29*0.1)+J29 -> 1.4762088 | I38: ESPESOR

Sheet 21
B2: CLIENTE: | D2: =PROPER(INICIO!D34) -> Cromwell/Met Guillon
B4: LISTA DE PRECIOS EN PESOS
B5: DD | C5: 1000 | D5: 1220 | E5: 1500 | G5: NEGRA | H5: 1000 | I5: 1245 | J5: 1500
B6: 16 | C6: =SUM(C16*0.07)+C16 -> 2328.3786 | D6: =SUM(C16*0.04)+C16 -> 2263.0969 | E6: =SUM(C16*0.04)+C16 -> 2263.0969 | G6: 1.6 | H6: XXX | I6: XXX | J6: XXX
B7: 18 | C7: =SUM(C16*0.07)+C16 -> 2328.3786 | D7: =SUM(C16*0.04)+C16 -> 2263.0969 | E7: =SUM(C16*0.04)+C16 -> 2263.0969 | G7: 2 | H7: =SUM(H16*0.14)+H16 -> 2122.0129 | I7: =SUM(H16*0.11)+H16 -> 2066.1704 | J7: XXX
B8: 12,14 y 20 | C8: =SUM(C16*0.08)+C16 -> 2350.1391 | D8: =SUM(C16*0.05)+C16 -> 2284.8575 | E8: =SUM(C16*0.05)+C16 -> 2284.8575 | G8: 2.5 | H8: =SUM(H16*0.12)+H16 -> 2084.7846 | I8: =SUM(H16*0.09)+H16 -> 2028.9421 | J8: XXX
B9: 22 | C9: =SUM(C16*0.1)+C16 -> 2393.6602 | D9: =SUM(C16*0.07)+C16 -> 2328.3786 | E9: =SUM(C16*0.07)+C16 -> 2328.3786 | G9: 3.17 | H9: =SUM(H16*0.11)+H16 -> 2066.1704 | I9: =SUM(H16*0.08)+H16 -> 2010.328 | J9: =SUM(H16*0.08)+H16 -> 2010.328
B10: 0.65 | C10: =SUM(C16*0.12)+C16 -> 2437.1813 | D10: =SUM(C16*0.09)+C16 -> 2371.8996 | E10: XXX | G10: 4,75 Y 4.00 | H10: =SUM(H16*0.1)+H16 -> 2047.5563 | I10: =SUM(H16*0.07+H16) -> 1991.7138 | J10: =SUM(H16*0.07)+H16 -> 1991.7138
B11: 24 | C11: =SUM(C16*0.16)+C16 -> 2524.2235 | D11: =SUM(C16*0.13)+C16 -> 2458.9418 | E11: XXX | G11: 6.35 | H11: =SUM(H16*0.11)+H16 -> 2066.1704 | I11: =SUM(H16*0.08)+H16 -> 2010.328 | J11: =SUM(H16*0.08)+H16 -> 2010.328
B12: 26 | C12: =SUM(C16*0.2)+C16 -> 2611.2657 | D12: =SUM(C16*0.15)+C16 -> 2502.4629 | E12: XXX | G12: 8 | H12: =SUM(H16*0.11)+H16 -> 2066.1704 | I12: =SUM(H16*0.08)+H16 -> 2010.328 | J12: =SUM(H16*0.08)+H16 -> 2010.328
B13: 27 | C13: =SUM(C16*0.26)+C16 -> 2741.8289 | D13: XXX | E13: XXX | G13: 9.52 | H13: =SUM(H16*0.12)+H16 -> 2084.7846 | I13: =SUM(H16*0.09)+H16 -> 2028.9421 | J13: =SUM(H16*0.1)+H16 -> 2047.5563
B14: 30 | C14: =SUM(C16*0.32)+C16 -> 2872.3922 | D14: XXX | E14: XXX | G14: 12.7 | H14: =SUM(H16*0.12)+H16 -> 2084.7846 | I14: =SUM(H16*0.09)+H16 -> 2028.9421 | J14: =SUM(H16*0.1)+H16 -> 2047.5563
B16: BASE | C16: =SUM(INICIO!K34) -> 2176.0547 | G16: BASE | H16: =SUM(INICIO!Q34) -> 1861.4148
B18: 3.17 | C18: 1245 | D18: S/MEL | E18: =SUM(I9*0.1)+I9 -> 2211.3608 | I18: CALIDAD
B19: 4.75 | C19: 1500 | D19: S/MEL | E19: =SUM(J10*0.1)+J10 -> 2190.8852 | I19: ANCHO
B20: 6.35 | C20: 1500 | D20: S/MEL | E20: =SUM(J11*0.1)+J11 -> 2211.3608 | I20: ESPESOR
B22: LISTA DE PRECIOS EN DÓLARES
B23: DD | C23: 1000 | D23: 1220 | E23: 1500 | G23: NEGRA | H23: 1000 | I23: 1245 | J23: 1500
B24: 16 | C24: =SUM(C34*0.07)+C34 -> 1.5543248 | D24: =SUM(C34*0.04)+C34 -> 1.5107456 | E24: =SUM(C34*0.04)+C34 -> 1.5107456 | G24: 1.6 | H24: XXX | I24: XXX | J24: XXX
B25: 18 | C25: =SUM(C34*0.07)+C34 -> 1.5543248 | D25: =SUM(C34*0.04)+C34 -> 1.5107456 | E25: =SUM(C34*0.04)+C34 -> 1.5107456 | G25: 2 | H25: =SUM(H34*0.14)+H34 -> 1.416564 | I25: =SUM(H34*0.11)+H34 -> 1.379286 | J25: XXX
B26: 12,14 y 20 | C26: =SUM(C34*0.08)+C34 -> 1.5688512 | D26: =SUM(C34*0.05)+C34 -> 1.525272 | E26: =SUM(C34*0.05)+C34 -> 1.525272 | G26: 2.5 | H26: =SUM(H34*0.12)+H34 -> 1.391712 | I26: =SUM(H34*0.09)+H34 -> 1.354434 | J26: XXX
B27: 22 | C27: =SUM(C34*0.1)+C34 -> 1.597904 | D27: =SUM(C34*0.07)+C34 -> 1.5543248 | E27: =SUM(C34*0.07)+C34 -> 1.5543248 | G27: 3.17 | H27: =SUM(H34*0.11)+H34 -> 1.379286 | I27: =SUM(H34*0.08)+H34 -> 1.342008 | J27: =SUM(H34*0.08)+H34 -> 1.342008
B28: 0.65 | C28: =SUM(C34*0.12)+C34 -> 1.6269568 | D28: =SUM(C34*0.09)+C34 -> 1.5833776 | E28: XXX | G28: 4,75 Y 4.00 | H28: =SUM(H34*0.1)+H34 -> 1.36686 | I28: =SUM(H34*0.07+H34) -> 1.329582 | J28: =SUM(H34*0.07)+H34 -> 1.329582
B29: 24 | C29: =SUM(C34*0.16)+C34 -> 1.6850624 | D29: =SUM(C34*0.13)+C34 -> 1.6414832 | E29: XXX | G29: 6.35 | H29: =SUM(H34*0.11)+H34 -> 1.379286 | I29: =SUM(H34*0.08)+H34 -> 1.342008 | J29: =SUM(H34*0.08)+H34 -> 1.342008
B30: 26 | C30: =SUM(C34*0.2)+C34 -> 1.743168 | D30: =SUM(C34*0.15)+C34 -> 1.670536 | E30: XXX | G30: 8 | H30: =SUM(H34*0.11)+H34 -> 1.379286 | I30: =SUM(H34*0.08)+H34 -> 1.342008 | J30: =SUM(H34*0.08)+H34 -> 1.342008
B31: 27 | C31: =SUM(C34*0.26)+C34 -> 1.8303264 | D31: XXX | E31: XXX | G31: 9.52 | H31: =SUM(H34*0.12)+H34 -> 1.391712 | I31: =SUM(H34*0.09)+H34 -> 1.354434 | J31: =SUM(H34*0.1)+H34 -> 1.36686
B32: 30 | C32: =SUM(C34*0.32)+C34 -> 1.9174848 | D32: XXX | E32: XXX | G32: 12.7 | H32: =SUM(H34*0.12)+H34 -> 1.391712 | I32: =SUM(H34*0.09)+H34 -> 1.354434 | J32: =SUM(H34*0.1)+H34 -> 1.36686
B34: BASE | C34: =SUM(INICIO!J34) -> 1.45264 | G34: BASE | H34: =SUM(INICIO!P34) -> 1.2426
B36: 3.17 | C36: 1245 | D36: S/MEL | E36: =SUM(I27*0.1)+I27 -> 1.4762088 | I36: CALIDAD
B37: 4.75 | C37: 1500 | D37: S/MEL | E37: =SUM(J28*0.1)+J28 -> 1.4625402 | I37: ANCHO
B38: 6.35 | C38: 1500 | D38: S/MEL | E38: =SUM(J29*0.1)+J29 -> 1.4762088 | I38: ESPESOR

Sheet 22
B2: CLIENTE: | D2: =PROPER(INICIO!D35) -> Rodel/Metic Design/Servitec
B4: LISTA DE PRECIOS EN PESOS
B5: DD | C5: 1000 | D5: 1220 | E5: 1500 | G5: NEGRA | H5: 1000 | I5: 1245 | J5: 1500
B6: 16 | C6: =SUM(C16*0.07)+C16 -> 2515.4804 | D6: =SUM(C16*0.04)+C16 -> 2444.9529 | E6: =SUM(C16*0.04)+C16 -> 2444.9529 | G6: 1.6 | H6: XXX | I6: XXX | J6: XXX
B7: 18 | C7: =SUM(C16*0.07)+C16 -> 2515.4804 | D7: =SUM(C16*0.04)+C16 -> 2444.9529 | E7: =SUM(C16*0.04)+C16 -> 2444.9529 | G7: 2 | H7: =SUM(H16*0.14)+H16 -> 2297.2249 | I7: =SUM(H16*0.11)+H16 -> 2236.7717 | J7: XXX
B8: 12,14 y 20 | C8: =SUM(C16*0.08)+C16 -> 2538.9896 | D8: =SUM(C16*0.05)+C16 -> 2468.4621 | E8: =SUM(C16*0.05)+C16 -> 2468.4621 | G8: 2.5 | H8: =SUM(H16*0.12)+H16 -> 2256.9228 | I8: =SUM(H16*0.09)+H16 -> 2196.4695 | J8: XXX
B9: 22 | C9: =SUM(C16*0.1)+C16 -> 2586.0079 | D9: =SUM(C16*0.07)+C16 -> 2515.4804 | E9: =SUM(C16*0.07)+C16 -> 2515.4804 | G9: 3.17 | H9: =SUM(H16*0.11)+H16 -> 2236.7717 | I9: =SUM(H16*0.08)+H16 -> 2176.3184 | J9: =SUM(H16*0.08)+H16 -> 2176.3184
B10: 0.65 | C10: =SUM(C16*0.12)+C16 -> 2633.0262 | D10: =SUM(C16*0.09)+C16 -> 2562.4987 | E10: XXX | G10: 4,75 Y 4.00 | H10: =SUM(H16*0.1)+H16 -> 2216.6206 | I10: =SUM(H16*0.07+H16) -> 2156.1673 | J10: =SUM(H16*0.07)+H16 -> 2156.1673
B11: 24 | C11: =SUM(C16*0.16)+C16 -> 2727.0629 | D11: =SUM(C16*0.13)+C16 -> 2656.5354 | E11: XXX | G11: 6.35 | H11: =SUM(H16*0.11)+H16 -> 2236.7717 | I11: =SUM(H16*0.08)+H16 -> 2176.3184 | J11: =SUM(H16*0.08)+H16 -> 2176.3184
B12: 26 | C12: =SUM(C16*0.2)+C16 -> 2821.0995 | D12: =SUM(C16*0.15)+C16 -> 2703.5537 | E12: XXX | G12: 8 | H12: =SUM(H16*0.11)+H16 -> 2236.7717 | I12: =SUM(H16*0.08)+H16 -> 2176.3184 | J12: =SUM(H16*0.08)+H16 -> 2176.3184
B13: 27 | C13: =SUM(C16*0.26)+C16 -> 2962.1545 | D13: XXX | E13: XXX | G13: 9.52 | H13: =SUM(H16*0.12)+H16 -> 2256.9228 | I13: =SUM(H16*0.09)+H16 -> 2196.4695 | J13: =SUM(H16*0.1)+H16 -> 2216.6206
B14: 30 | C14: =SUM(C16*0.32)+C16 -> 3103.2095 | D14: XXX | E14: XXX | G14: 12.7 | H14: =SUM(H16*0.12)+H16 -> 2256.9228 | I14: =SUM(H16*0.09)+H16 -> 2196.4695 | J14: =SUM(H16*0.1)+H16 -> 2216.6206
B16: BASE | C16: =SUM(INICIO!K35) -> 2350.9163 | G16: BASE | H16: =SUM(INICIO!Q35) -> 2015.1096
B18: 3.17 | C18: 1245 | D18: S/MEL | E18: =SUM(I9*0.1)+I9 -> 2393.9502 | I18: CALIDAD
B19: 4.75 | C19: 1500 | D19: S/MEL | E19: =SUM(J10*0.1)+J10 -> 2371.784 | I19: ANCHO
B20: 6.35 | C20: 1500 | D20: S/MEL | E20: =SUM(J11*0.1)+J11 -> 2393.9502 | I20: ESPESOR
B22: LISTA DE PRECIOS EN DÓLARES
B23: DD | C23: 1000 | D23: 1220 | E23: 1500 | G23: NEGRA | H23: 1000 | I23: 1245 | J23: 1500
B24: 16 | C24: =SUM(C34*0.07)+C34 -> 1.6792259 | D24: =SUM(C34*0.04)+C34 -> 1.6321448 | E24: =SUM(C34*0.04)+C34 -> 1.6321448 | G24: 1.6 | H24: XXX | I24: XXX | J24: XXX
B25: 18 | C25: =SUM(C34*0.07)+C34 -> 1.6792259 | D25: =SUM(C34*0.04)+C34 -> 1.6321448 | E25: =SUM(C34*0.04)+C34 -> 1.6321448 | G25: 2 | H25: =SUM(H34*0.14)+H34 -> 1.533528 | I25: =SUM(H34*0.11)+H34 -> 1.493172 | J25: XXX
B26: 12,14 y 20 | C26: =SUM(C34*0.08)+C34 -> 1.6949196 | D26: =SUM(C34*0.05)+C34 -> 1.6478385 | E26: =SUM(C34*0.05)+C34 -> 1.6478385 | G26: 2.5 | H26: =SUM(H34*0.12)+H34 -> 1.506624 | I26: =SUM(H34*0.09)+H34 -> 1.466268 | J26: XXX
B27: 22 | C27: =SUM(C34*0.1)+C34 -> 1.726307 | D27: =SUM(C34*0.07)+C34 -> 1.6792259 | E27: =SUM(C34*0.07)+C34 -> 1.6792259 | G27: 3.17 | H27: =SUM(H34*0.11)+H34 -> 1.493172 | I27: =SUM(H34*0.08)+H34 -> 1.452816 | J27: =SUM(H34*0.08)+H34 -> 1.452816
B28: 0.65 | C28: =SUM(C34*0.12)+C34 -> 1.7576944 | D28: =SUM(C34*0.09)+C34 -> 1.7106133 | E28: XXX | G28: 4,75 Y 4.00 | H28: =SUM(H34*0.1)+H34 -> 1.47972 | I28: =SUM(H34*0.07+H34) -> 1.439364 | J28: =SUM(H34*0.07)+H34 -> 1.439364
B29: 24 | C29: =SUM(C34*0.16)+C34 -> 1.8204692 | D29: =SUM(C34*0.13)+C34 -> 1.7733881 | E29: XXX | G29: 6.35 | H29: =SUM(H34*0.11)+H34 -> 1.493172 | I29: =SUM(H34*0.08)+H34 -> 1.452816 | J29: =SUM(H34*0.08)+H34 -> 1.452816
B30: 26 | C30: =SUM(C34*0.2)+C34 -> 1.883244 | D30: =SUM(C34*0.15)+C34 -> 1.8047755 | E30: XXX | G30: 8 | H30: =SUM(H34*0.11)+H34 -> 1.493172 | I30: =SUM(H34*0.08)+H34 -> 1.452816 | J30: =SUM(H34*0.08)+H34 -> 1.452816
B31: 27 | C31: =SUM(C34*0.26)+C34 -> 1.9774062 | D31: XXX | E31: XXX | G31: 9.52 | H31: =SUM(H34*0.12)+H34 -> 1.506624 | I31: =SUM(H34*0.09)+H34 -> 1.466268 | J31: =SUM(H34*0.1)+H34 -> 1.47972
B32: 30 | C32: =SUM(C34*0.32)+C34 -> 2.0715684 | D32: XXX | E32: XXX | G32: 12.7 | H32: =SUM(H34*0.12)+H34 -> 1.506624 | I32: =SUM(H34*0.09)+H34 -> 1.466268 | J32: =SUM(H34*0.1)+H34 -> 1.47972
B34: BASE | C34: =SUM(INICIO!J35) -> 1.56937 | G34: BASE | H34: =SUM(INICIO!P35) -> 1.3452
B36: 3.17 | C36: 1245 | D36: S/MEL | E36: =SUM(I27*0.1)+I27 -> 1.5980976 | I36: CALIDAD
B37: 4.75 | C37: 1500 | D37: S/MEL | E37: =SUM(J28*0.1)+J28 -> 1.5833004 | I37: ANCHO
B38: 6.35 | C38: 1500 | D38: S/MEL | E38: =SUM(J29*0.1)+J29 -> 1.5980976 | I38: ESPESOR

Sheet 23
B2: CLIENTE: | D2: =PROPER(INICIO!D36) -> Obregon/Peope
B4: LISTA DE PRECIOS EN PESOS
B5: DD | C5: 1000 | D5: 1220 | E5: 1500 | G5: NEGRA | H5: 1000 | I5: 1245 | J5: 1500
B6: 16 | C6: =SUM(C16*0.07)+C16 -> 2245.2222 | D6: =SUM(C16*0.04)+C16 -> 2182.272 | E6: =SUM(C16*0.04)+C16 -> 2182.272 | G6: 1.6 | H6: XXX | I6: XXX | J6: XXX
B7: 18 | C7: =SUM(C16*0.07)+C16 -> 2245.2222 | D7: =SUM(C16*0.04)+C16 -> 2182.272 | E7: =SUM(C16*0.04)+C16 -> 2182.272 | G7: 2 | H7: =SUM(H16*0.14)+H16 -> 2044.1408 | I7: =SUM(H16*0.11)+H16 -> 1990.3477 | J7: XXX
B8: 12,14 y 20 | C8: =SUM(C16*0.08)+C16 -> 2266.2056 | D8: =SUM(C16*0.05)+C16 -> 2203.2554 | E8: =SUM(C16*0.05)+C16 -> 2203.2554 | G8: 2.5 | H8: =SUM(H16*0.12)+H16 -> 2008.2787 | I8: =SUM(H16*0.09)+H16 -> 1954.4855 | J8: XXX
B9: 22 | C9: =SUM(C16*0.1)+C16 -> 2308.1723 | D9: =SUM(C16*0.07)+C16 -> 2245.2222 | E9: =SUM(C16*0.07)+C16 -> 2245.2222 | G9: 3.17 | H9: =SUM(H16*0.11)+H16 -> 1990.3477 | I9: =SUM(H16*0.08)+H16 -> 1936.5545 | J9: =SUM(H16*0.08)+H16 -> 1936.5545
B10: 0.65 | C10: =SUM(C16*0.12)+C16 -> 2350.1391 | D10: =SUM(C16*0.09)+C16 -> 2287.1889 | E10: XXX | G10: 4,75 Y 4.00 | H10: =SUM(H16*0.1)+H16 -> 1972.4166 | I10: =SUM(H16*0.07+H16) -> 1918.6234 | J10: =SUM(H16*0.07)+H16 -> 1918.6234
B11: 24 | C11: =SUM(C16*0.16)+C16 -> 2434.0726 | D11: =SUM(C16*0.13)+C16 -> 2371.1225 | E11: XXX | G11: 6.35 | H11: =SUM(H16*0.11)+H16 -> 1990.3477 | I11: =SUM(H16*0.08)+H16 -> 1936.5545 | J11: =SUM(H16*0.08)+H16 -> 1936.5545
B12: 26 | C12: =SUM(C16*0.2)+C16 -> 2518.0062 | D12: =SUM(C16*0.15)+C16 -> 2413.0893 | E12: XXX | G12: 8 | H12: =SUM(H16*0.11)+H16 -> 1990.3477 | I12: =SUM(H16*0.08)+H16 -> 1936.5545 | J12: =SUM(H16*0.08)+H16 -> 1936.5545
B13: 27 | C13: =SUM(C16*0.26)+C16 -> 2643.9065 | D13: XXX | E13: XXX | G13: 9.52 | H13: =SUM(H16*0.12)+H16 -> 2008.2787 | I13: =SUM(H16*0.09)+H16 -> 1954.4855 | J13: =SUM(H16*0.09)+H16 -> 1954.4855
B14: 30 | C14: =SUM(C16*0.32)+C16 -> 2769.8068 | D14: XXX | E14: XXX | G14: 12.7 | H14: =SUM(H16*0.12)+H16 -> 2008.2787 | I14: =SUM(H16*0.09)+H16 -> 1954.4855 | J14: =SUM(H16*0.09)+H16 -> 1954.4855
B16: BASE | C16: =SUM(INICIO!K36) -> 2098.3385 | G16: BASE | H16: =SUM(INICIO!Q36) -> 1793.106 | J16: peop -5
B18: 3.17 | C18: 1245 | D18: S/MEL | E18: =SUM(I9*0.1)+I9 -> 2130.2099 | I18: CALIDAD
B19: 4.75 | C19: 1500 | D19: S/MEL | E19: =SUM(J10*0.1)+J10 -> 2110.4858 | I19: ANCHO
B20: 6.35 | C20: 1500 | D20: S/MEL | E20: =SUM(J11*0.1)+J11 -> 2130.2099 | I20: ESPESOR
B22: LISTA DE PRECIOS EN DÓLARES
B23: DD | C23: 1000 | D23: 1220 | E23: 1500 | G23: NEGRA | H23: 1000 | I23: 1245 | J23: 1500
B24: 16 | C24: =SUM(C34*0.07)+C34 -> 1.4988132 | D24: =SUM(C34*0.04)+C34 -> 1.4567904 | E24: =SUM(C34*0.04)+C34 -> 1.4567904 | G24: 1.6 | H24: XXX | I24: XXX | J24: XXX
B25: 18 | C25: =SUM(C34*0.07)+C34 -> 1.4988132 | D25: =SUM(C34*0.04)+C34 -> 1.4567904 | E25: =SUM(C34*0.04)+C34 -> 1.4567904 | G25: 2 | H25: =SUM(H34*0.14)+H34 -> 1.36458 | I25: =SUM(H34*0.11)+H34 -> 1.32867 | J25: XXX
B26: 12,14 y 20 | C26: =SUM(C34*0.08)+C34 -> 1.5128208 | D26: =SUM(C34*0.05)+C34 -> 1.470798 | E26: =SUM(C34*0.05)+C34 -> 1.470798 | G26: 2.5 | H26: =SUM(H34*0.12)+H34 -> 1.34064 | I26: =SUM(H34*0.09)+H34 -> 1.30473 | J26: XXX
B27: 22 | C27: =SUM(C34*0.1)+C34 -> 1.540836 | D27: =SUM(C34*0.07)+C34 -> 1.4988132 | E27: =SUM(C34*0.07)+C34 -> 1.4988132 | G27: 3.17 | H27: =SUM(H34*0.11)+H34 -> 1.32867 | I27: =SUM(H34*0.08)+H34 -> 1.29276 | J27: =SUM(H34*0.08)+H34 -> 1.29276
B28: 0.65 | C28: =SUM(C34*0.12)+C34 -> 1.5688512 | D28: =SUM(C34*0.09)+C34 -> 1.5268284 | E28: XXX | G28: 4,75 Y 4.00 | H28: =SUM(H34*0.1)+H34 -> 1.3167 | I28: =SUM(H34*0.07+H34) -> 1.28079 | J28: =SUM(H34*0.07)+H34 -> 1.28079
B29: 24 | C29: =SUM(C34*0.16)+C34 -> 1.6248816 | D29: =SUM(C34*0.13)+C34 -> 1.5828588 | E29: XXX | G29: 6.35 | H29: =SUM(H34*0.11)+H34 -> 1.32867 | I29: =SUM(H34*0.08)+H34 -> 1.29276 | J29: =SUM(H34*0.08)+H34 -> 1.29276
B30: 26 | C30: =SUM(C34*0.2)+C34 -> 1.680912 | D30: =SUM(C34*0.15)+C34 -> 1.610874 | E30: XXX | G30: 8 | H30: =SUM(H34*0.11)+H34 -> 1.32867 | I30: =SUM(H34*0.08)+H34 -> 1.29276 | J30: =SUM(H34*0.08)+H34 -> 1.29276
B31: 27 | C31: =SUM(C34*0.26)+C34 -> 1.7649576 | D31: XXX | E31: XXX | G31: 9.52 | H31: =SUM(H34*0.12)+H34 -> 1.34064 | I31: =SUM(H34*0.09)+H34 -> 1.30473 | J31: =SUM(H34*0.09)+H34 -> 1.30473
B32: 30 | C32: =SUM(C34*0.32)+C34 -> 1.8490032 | D32: XXX | E32: XXX | G32: 12.7 | H32: =SUM(H34*0.12)+H34 -> 1.34064 | I32: =SUM(H34*0.09)+H34 -> 1.30473 | J32: =SUM(H34*0.09)+H34 -> 1.30473
B34: BASE | C34: =SUM(INICIO!J36) -> 1.40076 | G34: BASE | H34: =SUM(INICIO!P36) -> 1.197
B36: 3.17 | C36: 1245 | D36: S/MEL | E36: =SUM(I27*0.1)+I27 -> 1.422036 | I36: CALIDAD
B37: 4.75 | C37: 1500 | D37: S/MEL | E37: =SUM(J28*0.1)+J28 -> 1.408869 | I37: ANCHO
B38: 6.35 | C38: 1500 | D38: S/MEL | E38: =SUM(J29*0.1)+J29 -> 1.422036 | I38: ESPESOR

Sheet 24
B2: CLIENTE: | D2: =PROPER(INICIO!D37) -> Carpintero/Oximetal/Met Gh/Rotofrance/Calden/Brauer
B4: LISTA DE PRECIOS EN PESOS
B5: DD | C5: 1000 | D5: 1220 | E5: 1500 | G5: NEGRA | H5: 1000 | I5: 1245 | J5: 1500
B6: 16 | C6: =SUM(C16*0.07)+C16 -> 2203.644 | D6: =SUM(C16*0.04)+C16 -> 2141.8596 | E6: =SUM(C16*0.04)+C16 -> 2141.8596 | G6: 1.6 | H6: XXX | I6: XXX | J6: XXX
B7: 18 | C7: =SUM(C16*0.07)+C16 -> 2203.644 | D7: =SUM(C16*0.04)+C16 -> 2141.8596 | E7: =SUM(C16*0.04)+C16 -> 2141.8596 | G7: 2 | H7: =SUM(H16*0.14)+H16 -> 1966.2688 | I7: =SUM(H16*0.11)+H16 -> 1914.5249 | J7: XXX
B8: 12,14 y 20 | C8: =SUM(C16*0.08)+C16 -> 2224.2388 | D8: =SUM(C16*0.05)+C16 -> 2162.4544 | E8: =SUM(C16*0.05)+C16 -> 2162.4544 | G8: 2.5 | H8: =SUM(H16*0.12)+H16 -> 1931.7729 | I8: =SUM(H16*0.09)+H16 -> 1880.0289 | J8: XXX
B9: 22 | C9: =SUM(C16*0.1)+C16 -> 2265.4284 | D9: =SUM(C16*0.07)+C16 -> 2203.644 | E9: =SUM(C16*0.07)+C16 -> 2203.644 | G9: 3.17 | H9: =SUM(H16*0.11)+H16 -> 1914.5249 | I9: =SUM(H16*0.08)+H16 -> 1862.781 | J9: =SUM(H16*0.08)+H16 -> 1862.781
B10: 0.65 | C10: =SUM(C16*0.12)+C16 -> 2306.618 | D10: =SUM(C16*0.09)+C16 -> 2244.8336 | E10: XXX | G10: 4,75 Y 4.00 | H10: =SUM(H16*0.1)+H16 -> 1897.2769 | I10: =SUM(H16*0.07+H16) -> 1845.533 | J10: =SUM(H16*0.07)+H16 -> 1845.533
B11: 24 | C11: =SUM(C16*0.16)+C16 -> 2388.9972 | D11: =SUM(C16*0.13)+C16 -> 2327.2128 | E11: XXX | G11: 6.35 | H11: =SUM(H16*0.11)+H16 -> 1914.5249 | I11: =SUM(H16*0.08)+H16 -> 1862.781 | J11: =SUM(H16*0.08)+H16 -> 1862.781
B12: 26 | C12: =SUM(C16*0.2)+C16 -> 2471.3764 | D12: =SUM(C16*0.15)+C16 -> 2368.4024 | E12: XXX | G12: 8 | H12: =SUM(H16*0.11)+H16 -> 1914.5249 | I12: =SUM(H16*0.08)+H16 -> 1862.781 | J12: =SUM(H16*0.08)+H16 -> 1862.781
B13: 27 | C13: =SUM(C16*0.26)+C16 -> 2594.9453 | D13: XXX | E13: XXX | G13: 9.52 | H13: =SUM(H16*0.12)+H16 -> 1931.7729 | I13: =SUM(H16*0.09)+H16 -> 1880.0289 | J13: =SUM(H16*0.1)+H16 -> 1897.2769
B14: 30 | C14: =SUM(C16*0.32)+C16 -> 2718.5141 | D14: XXX | E14: XXX | G14: 12.7 | H14: =SUM(H16*0.12)+H16 -> 1931.7729 | I14: =SUM(H16*0.09)+H16 -> 1880.0289 | J14: =SUM(H16*0.1)+H16 -> 1897.2769
B16: BASE | C16: =SUM(INICIO!K37) -> 2059.4804 | G16: BASE | H16: =SUM(INICIO!Q37) -> 1724.7972 | K16: dec -12
J17: gh -8%
B18: 3.17 | C18: 1245 | D18: S/MEL | E18: =SUM(I9*0.1)+I9 -> 2049.0591 | I18: CALIDAD | J18: carpi cal9 frio 9 | K18: ,93 ang
B19: 4.75 | C19: 1500 | D19: S/MEL | E19: =SUM(J10*0.1)+J10 -> 2030.0863 | I19: ANCHO
B20: 6.35 | C20: 1500 | D20: S/MEL | E20: =SUM(J11*0.1)+J11 -> 2049.0591 | I20: ESPESOR
B22: LISTA DE PRECIOS EN DÓLARES
B23: DD | C23: 1000 | D23: 1220 | E23: 1500 | G23: NEGRA | H23: 1000 | I23: 1245 | J23: 1500
B24: 16 | C24: =SUM(C34*0.07)+C34 -> 1.4710574 | D24: =SUM(C34*0.04)+C34 -> 1.4298128 | E24: =SUM(C34*0.04)+C34 -> 1.4298128 | G24: 1.6 | H24: XXX | I24: XXX | J24: XXX
B25: 18 | C25: =SUM(C34*0.07)+C34 -> 1.4710574 | D25: =SUM(C34*0.04)+C34 -> 1.4298128 | E25: =SUM(C34*0.04)+C34 -> 1.4298128 | G25: 2 | H25: =SUM(H34*0.14)+H34 -> 1.312596 | I25: =SUM(H34*0.11)+H34 -> 1.278054 | J25: XXX
B26: 12,14 y 20 | C26: =SUM(C34*0.08)+C34 -> 1.4848056 | D26: =SUM(C34*0.05)+C34 -> 1.443561 | E26: =SUM(C34*0.05)+C34 -> 1.443561 | G26: 2.5 | H26: =SUM(H34*0.12)+H34 -> 1.289568 | I26: =SUM(H34*0.09)+H34 -> 1.255026 | J26: XXX
B27: 22 | C27: =SUM(C34*0.1)+C34 -> 1.512302 | D27: =SUM(C34*0.07)+C34 -> 1.4710574 | E27: =SUM(C34*0.07)+C34 -> 1.4710574 | G27: 3.17 | H27: =SUM(H34*0.11)+H34 -> 1.278054 | I27: =SUM(H34*0.08)+H34 -> 1.243512 | J27: =SUM(H34*0.08)+H34 -> 1.243512
B28: 0.65 | C28: =SUM(C34*0.12)+C34 -> 1.5397984 | D28: =SUM(C34*0.09)+C34 -> 1.4985538 | E28: XXX | G28: 4,75 Y 4.00 | H28: =SUM(H34*0.1)+H34 -> 1.26654 | I28: =SUM(H34*0.07+H34) -> 1.231998 | J28: =SUM(H34*0.07)+H34 -> 1.231998
B29: 24 | C29: =SUM(C34*0.16)+C34 -> 1.5947912 | D29: =SUM(C34*0.13)+C34 -> 1.5535466 | E29: XXX | G29: 6.35 | H29: =SUM(H34*0.11)+H34 -> 1.278054 | I29: =SUM(H34*0.08)+H34 -> 1.243512 | J29: =SUM(H34*0.08)+H34 -> 1.243512
B30: 26 | C30: =SUM(C34*0.2)+C34 -> 1.649784 | D30: =SUM(C34*0.15)+C34 -> 1.581043 | E30: XXX | G30: 8 | H30: =SUM(H34*0.11)+H34 -> 1.278054 | I30: =SUM(H34*0.08)+H34 -> 1.243512 | J30: =SUM(H34*0.08)+H34 -> 1.243512
B31: 27 | C31: =SUM(C34*0.26)+C34 -> 1.7322732 | D31: XXX | E31: XXX | G31: 9.52 | H31: =SUM(H34*0.12)+H34 -> 1.289568 | I31: =SUM(H34*0.09)+H34 -> 1.255026 | J31: =SUM(H34*0.1)+H34 -> 1.26654
B32: 30 | C32: =SUM(C34*0.32)+C34 -> 1.8147624 | D32: XXX | E32: XXX | G32: 12.7 | H32: =SUM(H34*0.12)+H34 -> 1.289568 | I32: =SUM(H34*0.09)+H34 -> 1.255026 | J32: =SUM(H34*0.1)+H34 -> 1.26654
B34: BASE | C34: =SUM(INICIO!J37) -> 1.37482 | G34: BASE | H34: =SUM(INICIO!P37) -> 1.1514
B36: 3.17 | C36: 1245 | D36: S/MEL | E36: =SUM(I27*0.1)+I27 -> 1.3678632 | I36: CALIDAD
B37: 4.75 | C37: 1500 | D37: S/MEL | E37: =SUM(J28*0.1)+J28 -> 1.3551978 | I37: ANCHO
B38: 6.35 | C38: 1500 | D38: S/MEL | E38: =SUM(J29*0.1)+J29 -> 1.3678632 | I38: ESPESOR

Sheet Hoja1

Sheet 25
B2: CLIENTE: | D2: =PROPER(INICIO!D38) -> Hiergath/Galarza
B4: LISTA DE PRECIOS EN PESOS
B5: DD | C5: 1000 | D5: 1220 | E5: 1500 | G5: NEGRA | H5: 1000 | I5: 1245 | J5: 1500
B6: 16 | C6: =SUM(C16*0.07)+C16 -> 2286.8004 | D6: =SUM(C16*0.04)+C16 -> 2222.6845 | E6: =SUM(C16*0.04)+C16 -> 2222.6845 | G6: 1.6 | H6: XXX | I6: XXX | J6: XXX
B7: 18 | C7: =SUM(C16*0.07)+C16 -> 2286.8004 | D7: =SUM(C16*0.04)+C16 -> 2222.6845 | E7: =SUM(C16*0.04)+C16 -> 2222.6845 | G7: 2 | H7: =SUM(H16*0.14)+H16 -> 2122.0129 | I7: =SUM(H16*0.11)+H16 -> 2066.1704 | J7: XXX
B8: 12,14 y 20 | C8: =SUM(C16*0.08)+C16 -> 2308.1723 | D8: =SUM(C16*0.05)+C16 -> 2244.0564 | E8: =SUM(C16*0.05)+C16 -> 2244.0564 | G8: 2.5 | H8: =SUM(H16*0.12)+H16 -> 2084.7846 | I8: =SUM(H16*0.09)+H16 -> 2028.9421 | J8: XXX
B9: 22 | C9: =SUM(C16*0.1)+C16 -> 2350.9163 | D9: =SUM(C16*0.07)+C16 -> 2286.8004 | E9: =SUM(C16*0.07)+C16 -> 2286.8004 | G9: 3.17 | H9: =SUM(H16*0.11)+H16 -> 2066.1704 | I9: =SUM(H16*0.08)+H16 -> 2010.328 | J9: =SUM(H16*0.08)+H16 -> 2010.328
B10: 0.65 | C10: =SUM(C16*0.12)+C16 -> 2393.6602 | D10: =SUM(C16*0.09)+C16 -> 2329.5443 | E10: XXX | G10: 4,75 Y 4.00 | H10: =SUM(H16*0.1)+H16 -> 2047.5563 | I10: =SUM(H16*0.07+H16) -> 1991.7138 | J10: =SUM(H16*0.07)+H16 -> 1991.7138
B11: 24 | C11: =SUM(C16*0.16)+C16 -> 2479.1481 | D11: =SUM(C16*0.13)+C16 -> 2415.0322 | E11: XXX | G11: 6.35 | H11: =SUM(H16*0.11)+H16 -> 2066.1704 | I11: =SUM(H16*0.08)+H16 -> 2010.328 | J11: =SUM(H16*0.08)+H16 -> 2010.328
B12: 26 | C12: =SUM(C16*0.2)+C16 -> 2564.6359 | D12: =SUM(C16*0.15)+C16 -> 2457.7761 | E12: XXX | G12: 8 | H12: =SUM(H16*0.11)+H16 -> 2066.1704 | I12: =SUM(H16*0.08)+H16 -> 2010.328 | J12: =SUM(H16*0.08)+H16 -> 2010.328
B13: 27 | C13: =SUM(C16*0.26)+C16 -> 2692.8677 | D13: XXX | E13: XXX | G13: 9.52 | H13: =SUM(H16*0.12)+H16 -> 2084.7846 | I13: =SUM(H16*0.09)+H16 -> 2028.9421 | J13: =SUM(H16*0.1)+H16 -> 2047.5563
B14: 30 | C14: =SUM(C16*0.32)+C16 -> 2821.0995 | D14: XXX | E14: XXX | G14: 12.7 | H14: =SUM(H16*0.12)+H16 -> 2084.7846 | I14: =SUM(H16*0.09)+H16 -> 2028.9421 | J14: =SUM(H16*0.1)+H16 -> 2047.5563
B16: BASE | C16: =SUM(INICIO!K38) -> 2137.1966 | G16: BASE | H16: =SUM(INICIO!Q38) -> 1861.4148
B18: 3.17 | C18: 1245 | D18: S/MEL | E18: =SUM(I9*0.1)+I9 -> 2211.3608 | I18: CALIDAD
B19: 4.75 | C19: 1500 | D19: S/MEL | E19: =SUM(J10*0.1)+J10 -> 2190.8852 | I19: ANCHO
B20: 6.35 | C20: 1500 | D20: S/MEL | E20: =SUM(J11*0.1)+J11 -> 2211.3608 | I20: ESPESOR
B22: LISTA DE PRECIOS EN DÓLARES
B23: DD | C23: 1000 | D23: 1220 | E23: 1500 | G23: NEGRA | H23: 1000 | I23: 1245 | J23: 1500
B24: 16 | C24: =SUM(C34*0.07)+C34 -> 1.526569 | D24: =SUM(C34*0.04)+C34 -> 1.483768 | E24: =SUM(C34*0.04)+C34 -> 1.483768 | G24: 1.6 | H24: XXX | I24: XXX | J24: XXX
B25: 18 | C25: =SUM(C34*0.07)+C34 -> 1.526569 | D25: =SUM(C34*0.04)+C34 -> 1.483768 | E25: =SUM(C34*0.04)+C34 -> 1.483768 | G25: 2 | H25: =SUM(H34*0.14)+H34 -> 1.416564 | I25: =SUM(H34*0.11)+H34 -> 1.379286 | J25: XXX
B26: 12,14 y 20 | C26: =SUM(C34*0.08)+C34 -> 1.540836 | D26: =SUM(C34*0.05)+C34 -> 1.498035 | E26: =SUM(C34*0.05)+C34 -> 1.498035 | G26: 2.5 | H26: =SUM(H34*0.12)+H34 -> 1.391712 | I26: =SUM(H34*0.09)+H34 -> 1.354434 | J26: XXX
B27: 22 | C27: =SUM(C34*0.1)+C34 -> 1.56937 | D27: =SUM(C34*0.07)+C34 -> 1.526569 | E27: =SUM(C34*0.07)+C34 -> 1.526569 | G27: 3.17 | H27: =SUM(H34*0.11)+H34 -> 1.379286 | I27: =SUM(H34*0.08)+H34 -> 1.342008 | J27: =SUM(H34*0.08)+H34 -> 1.342008
B28: 0.65 | C28: =SUM(C34*0.12)+C34 -> 1.597904 | D28: =SUM(C34*0.09)+C34 -> 1.555103 | E28: XXX | G28: 4,75 Y 4.00 | H28: =SUM(H34*0.1)+H34 -> 1.36686 | I28: =SUM(H34*0.07+H34) -> 1.329582 | J28: =SUM(H34*0.07)+H34 -> 1.329582
B29: 24 | C29: =SUM(C34*0.16)+C34 -> 1.654972 | D29: =SUM(C34*0.13)+C34 -> 1.612171 | E29: XXX | G29: 6.35 | H29: =SUM(H34*0.11)+H34 -> 1.379286 | I29: =SUM(H34*0.08)+H34 -> 1.342008 | J29: =SUM(H34*0.08)+H34 -> 1.342008
B30: 26 | C30: =SUM(C34*0.2)+C34 -> 1.71204 | D30: =SUM(C34*0.15)+C34 -> 1.640705 | E30: XXX | G30: 8 | H30: =SUM(H34*0.11)+H34 -> 1.379286 | I30: =SUM(H34*0.08)+H34 -> 1.342008 | J30: =SUM(H34*0.08)+H34 -> 1.342008
B31: 27 | C31: =SUM(C34*0.26)+C34 -> 1.797642 | D31: XXX | E31: XXX | G31: 9.52 | H31: =SUM(H34*0.12)+H34 -> 1.391712 | I31: =SUM(H34*0.09)+H34 -> 1.354434 | J31: =SUM(H34*0.1)+H34 -> 1.36686
B32: 30 | C32: =SUM(C34*0.32)+C34 -> 1.883244 | D32: XXX | E32: XXX | G32: 12.7 | H32: =SUM(H34*0.12)+H34 -> 1.391712 | I32: =SUM(H34*0.09)+H34 -> 1.354434 | J32: =SUM(H34*0.1)+H34 -> 1.36686
B34: BASE | C34: =SUM(INICIO!J38) -> 1.4267 | G34: BASE | H34: =SUM(INICIO!P38) -> 1.2426
B36: 3.17 | C36: 1245 | D36: S/MEL | E36: =SUM(I27*0.1)+I27 -> 1.4762088 | I36: CALIDAD
B37: 4.75 | C37: 1500 | D37: S/MEL | E37: =SUM(J28*0.1)+J28 -> 1.4625402 | I37: ANCHO
B38: 6.35 | C38: 1500 | D38: S/MEL | E38: =SUM(J29*0.1)+J29 -> 1.4762088 | I38: ESPESOR

Sheet 26
B2: CLIENTE: | D2: =PROPER(INICIO!D39) -> Sarro/Lumac/Rimauro
B4: LISTA DE PRECIOS EN PESOS
B5: DD | C5: 1000 | D5: 1220 | E5: 1500 | G5: NEGRA | H5: 1000 | I5: 1245 | J5: 1500
B6: 16 | C6: =SUM(C16*0.07)+C16 -> 2328.3786 | D6: =SUM(C16*0.04)+C16 -> 2263.0969 | E6: =SUM(C16*0.04)+C16 -> 2263.0969 | G6: 1.6 | H6: XXX | I6: XXX | J6: XXX
B7: 18 | C7: =SUM(C16*0.07)+C16 -> 2328.3786 | D7: =SUM(C16*0.04)+C16 -> 2263.0969 | E7: =SUM(C16*0.04)+C16 -> 2263.0969 | G7: 2 | H7: =SUM(H16*0.14)+H16 -> 2141.4809 | I7: =SUM(H16*0.11)+H16 -> 2085.1261 | J7: XXX
B8: 12,14 y 20 | C8: =SUM(C16*0.08)+C16 -> 2350.1391 | D8: =SUM(C16*0.05)+C16 -> 2284.8575 | E8: =SUM(C16*0.05)+C16 -> 2284.8575 | G8: 2.5 | H8: =SUM(H16*0.12)+H16 -> 2103.911 | I8: =SUM(H16*0.09)+H16 -> 2047.5563 | J8: XXX
B9: 22 | C9: =SUM(C16*0.1)+C16 -> 2393.6602 | D9: =SUM(C16*0.07)+C16 -> 2328.3786 | E9: =SUM(C16*0.07)+C16 -> 2328.3786 | G9: 3.17 | H9: =SUM(H16*0.11)+H16 -> 2085.1261 | I9: =SUM(H16*0.08)+H16 -> 2028.7714 | J9: =SUM(H16*0.08)+H16 -> 2028.7714
B10: 0.65 | C10: =SUM(C16*0.12)+C16 -> 2437.1813 | D10: =SUM(C16*0.09)+C16 -> 2371.8996 | E10: XXX | G10: 4,75 Y 4.00 | H10: =SUM(H16*0.1)+H16 -> 2066.3412 | I10: =SUM(H16*0.07+H16) -> 2009.9864 | J10: =SUM(H16*0.07)+H16 -> 2009.9864
B11: 24 | C11: =SUM(C16*0.16)+C16 -> 2524.2235 | D11: =SUM(C16*0.13)+C16 -> 2458.9418 | E11: XXX | G11: 6.35 | H11: =SUM(H16*0.11)+H16 -> 2085.1261 | I11: =SUM(H16*0.08)+H16 -> 2028.7714 | J11: =SUM(H16*0.08)+H16 -> 2028.7714
B12: 26 | C12: =SUM(C16*0.2)+C16 -> 2611.2657 | D12: =SUM(C16*0.15)+C16 -> 2502.4629 | E12: XXX | G12: 8 | H12: =SUM(H16*0.11)+H16 -> 2085.1261 | I12: =SUM(H16*0.08)+H16 -> 2028.7714 | J12: =SUM(H16*0.08)+H16 -> 2028.7714
B13: 27 | C13: =SUM(C16*0.26)+C16 -> 2741.8289 | D13: XXX | E13: XXX | G13: 9.52 | H13: =SUM(H16*0.12)+H16 -> 2103.911 | I13: =SUM(H16*0.09)+H16 -> 2047.5563 | J13: =SUM(H16*0.1)+H16 -> 2066.3412
B14: 30 | C14: =SUM(C16*0.32)+C16 -> 2872.3922 | D14: XXX | E14: XXX | G14: 12.7 | H14: =SUM(H16*0.12)+H16 -> 2103.911 | I14: =SUM(H16*0.09)+H16 -> 2047.5563 | J14: =SUM(H16*0.1)+H16 -> 2066.3412
B16: BASE | C16: =SUM(INICIO!K39) -> 2176.0547 | G16: BASE | H16: =SUM(INICIO!Q39) -> 1878.492
B18: 3.17 | C18: 1245 | D18: S/MEL | E18: =SUM(I9*0.1)+I9 -> 2231.6485 | I18: CALIDAD
B19: 4.75 | C19: 1500 | D19: S/MEL | E19: =SUM(J10*0.1)+J10 -> 2210.9851 | I19: ANCHO
B20: 6.35 | C20: 1500 | D20: S/MEL | E20: =SUM(J11*0.1)+J11 -> 2231.6485 | I20: ESPESOR
B22: LISTA DE PRECIOS EN DÓLARES
B23: DD | C23: 1000 | D23: 1220 | E23: 1500 | G23: NEGRA | H23: 1000 | I23: 1245 | J23: 1500
B24: 16 | C24: =SUM(C34*0.07)+C34 -> 1.5543248 | D24: =SUM(C34*0.04)+C34 -> 1.5107456 | E24: =SUM(C34*0.04)+C34 -> 1.5107456 | G24: 1.6 | H24: XXX | I24: XXX | J24: XXX
B25: 18 | C25: =SUM(C34*0.07)+C34 -> 1.5543248 | D25: =SUM(C34*0.04)+C34 -> 1.5107456 | E25: =SUM(C34*0.04)+C34 -> 1.5107456 | G25: 2 | H25: =SUM(H34*0.14)+H34 -> 1.42956 | I25: =SUM(H34*0.11)+H34 -> 1.39194 | J25: XXX
B26: 12,14 y 20 | C26: =SUM(C34*0.08)+C34 -> 1.5688512 | D26: =SUM(C34*0.05)+C34 -> 1.525272 | E26: =SUM(C34*0.05)+C34 -> 1.525272 | G26: 2.5 | H26: =SUM(H34*0.12)+H34 -> 1.40448 | I26: =SUM(H34*0.09)+H34 -> 1.36686 | J26: XXX
B27: 22 | C27: =SUM(C34*0.1)+C34 -> 1.597904 | D27: =SUM(C34*0.07)+C34 -> 1.5543248 | E27: =SUM(C34*0.07)+C34 -> 1.5543248 | G27: 3.17 | H27: =SUM(H34*0.11)+H34 -> 1.39194 | I27: =SUM(H34*0.08)+H34 -> 1.35432 | J27: =SUM(H34*0.08)+H34 -> 1.35432
B28: 0.65 | C28: =SUM(C34*0.12)+C34 -> 1.6269568 | D28: =SUM(C34*0.09)+C34 -> 1.5833776 | E28: XXX | G28: 4,75 Y 4.00 | H28: =SUM(H34*0.1)+H34 -> 1.3794 | I28: =SUM(H34*0.07+H34) -> 1.34178 | J28: =SUM(H34*0.07)+H34 -> 1.34178
B29: 24 | C29: =SUM(C34*0.16)+C34 -> 1.6850624 | D29: =SUM(C34*0.13)+C34 -> 1.6414832 | E29: XXX | G29: 6.35 | H29: =SUM(H34*0.11)+H34 -> 1.39194 | I29: =SUM(H34*0.08)+H34 -> 1.35432 | J29: =SUM(H34*0.08)+H34 -> 1.35432
B30: 26 | C30: =SUM(C34*0.2)+C34 -> 1.743168 | D30: =SUM(C34*0.15)+C34 -> 1.670536 | E30: XXX | G30: 8 | H30: =SUM(H34*0.11)+H34 -> 1.39194 | I30: =SUM(H34*0.08)+H34 -> 1.35432 | J30: =SUM(H34*0.08)+H34 -> 1.35432
B31: 27 | C31: =SUM(C34*0.26)+C34 -> 1.8303264 | D31: XXX | E31: XXX | G31: 9.52 | H31: =SUM(H34*0.12)+H34 -> 1.40448 | I31: =SUM(H34*0.09)+H34 -> 1.36686 | J31: =SUM(H34*0.1)+H34 -> 1.3794
B32: 30 | C32: =SUM(C34*0.32)+C34 -> 1.9174848 | D32: XXX | E32: XXX | G32: 12.7 | H32: =SUM(H34*0.12)+H34 -> 1.40448 | I32: =SUM(H34*0.09)+H34 -> 1.36686 | J32: =SUM(H34*0.1)+H34 -> 1.3794
B34: BASE | C34: =SUM(INICIO!J39) -> 1.45264 | G34: BASE | H34: =SUM(INICIO!P39) -> 1.254
B36: 3.17 | C36: 1245 | D36: S/MEL | E36: =SUM(I27*0.1)+I27 -> 1.489752 | I36: CALIDAD
B37: 4.75 | C37: 1500 | D37: S/MEL | E37: =SUM(J28*0.1)+J28 -> 1.475958 | I37: ANCHO
B38: 6.35 | C38: 1500 | D38: S/MEL | E38: =SUM(J29*0.1)+J29 -> 1.489752 | I38: ESPESOR

Sheet 27
B2: CLIENTE: | D2: =PROPER(INICIO!D40) -> Radice/Dodero/Secaire
B4: LISTA DE PRECIOS EN PESOS
B5: DD | C5: 1000 | D5: 1220 | E5: 1500 | G5: NEGRA | H5: 1000 | I5: 1245 | J5: 1500
B6: 16 | C6: =SUM(C16*0.07)+C16 -> 2328.3786 | D6: =SUM(C16*0.04)+C16 -> 2263.0969 | E6: =SUM(C16*0.04)+C16 -> 2263.0969 | G6: 1.6 | H6: XXX | I6: XXX | J6: XXX
B7: 18 | C7: =SUM(C16*0.07)+C16 -> 2328.3786 | D7: =SUM(C16*0.04)+C16 -> 2263.0969 | E7: =SUM(C16*0.04)+C16 -> 2263.0969 | G7: 2 | H7: =SUM(H16*0.14)+H16 -> 2044.1408 | I7: =SUM(H16*0.11)+H16 -> 1990.3477 | J7: XXX
B8: 12,14 y 20 | C8: =SUM(C16*0.08)+C16 -> 2350.1391 | D8: =SUM(C16*0.05)+C16 -> 2284.8575 | E8: =SUM(C16*0.05)+C16 -> 2284.8575 | G8: 2.5 | H8: =SUM(H16*0.12)+H16 -> 2008.2787 | I8: =SUM(H16*0.09)+H16 -> 1954.4855 | J8: XXX
B9: 22 | C9: =SUM(C16*0.1)+C16 -> 2393.6602 | D9: =SUM(C16*0.07)+C16 -> 2328.3786 | E9: =SUM(C16*0.07)+C16 -> 2328.3786 | G9: 3.17 | H9: =SUM(H16*0.11)+H16 -> 1990.3477 | I9: =SUM(H16*0.08)+H16 -> 1936.5545 | J9: =SUM(H16*0.08)+H16 -> 1936.5545
B10: 0.65 | C10: =SUM(C16*0.12)+C16 -> 2437.1813 | D10: =SUM(C16*0.09)+C16 -> 2371.8996 | E10: XXX | G10: 4,75 Y 4.00 | H10: =SUM(H16*0.1)+H16 -> 1972.4166 | I10: =SUM(H16*0.07+H16) -> 1918.6234 | J10: =SUM(H16*0.07)+H16 -> 1918.6234
B11: 24 | C11: =SUM(C16*0.16)+C16 -> 2524.2235 | D11: =SUM(C16*0.13)+C16 -> 2458.9418 | E11: XXX | G11: 6.35 | H11: =SUM(H16*0.11)+H16 -> 1990.3477 | I11: =SUM(H16*0.08)+H16 -> 1936.5545 | J11: =SUM(H16*0.08)+H16 -> 1936.5545
B12: 26 | C12: =SUM(C16*0.2)+C16 -> 2611.2657 | D12: =SUM(C16*0.15)+C16 -> 2502.4629 | E12: XXX | G12: 8 | H12: =SUM(H16*0.11)+H16 -> 1990.3477 | I12: =SUM(H16*0.08)+H16 -> 1936.5545 | J12: =SUM(H16*0.08)+H16 -> 1936.5545
B13: 27 | C13: =SUM(C16*0.26)+C16 -> 2741.8289 | D13: XXX | E13: XXX | G13: 9.52 | H13: =SUM(H16*0.12)+H16 -> 2008.2787 | I13: =SUM(H16*0.09)+H16 -> 1954.4855 | J13: =SUM(H16*0.1)+H16 -> 1972.4166
B14: 30 | C14: =SUM(C16*0.32)+C16 -> 2872.3922 | D14: XXX | E14: XXX | G14: 12.7 | H14: =SUM(H16*0.12)+H16 -> 2008.2787 | I14: =SUM(H16*0.09)+H16 -> 1954.4855 | J14: =SUM(H16*0.1)+H16 -> 1972.4166
B16: BASE | C16: =SUM(INICIO!K40) -> 2176.0547 | G16: BASE | H16: =SUM(INICIO!Q40) -> 1793.106 | J16: radice-10
B18: 3.17 | C18: 1245 | D18: S/MEL | E18: =SUM(I9*0.1)+I9 -> 2130.2099 | I18: CALIDAD
B19: 4.75 | C19: 1500 | D19: S/MEL | E19: =SUM(J10*0.1)+J10 -> 2110.4858 | I19: ANCHO
B20: 6.35 | C20: 1500 | D20: S/MEL | E20: =SUM(J11*0.1)+J11 -> 2130.2099 | I20: ESPESOR
B22: LISTA DE PRECIOS EN DÓLARES
B23: DD | C23: 1000 | D23: 1220 | E23: 1500 | G23: NEGRA | H23: 1000 | I23: 1245 | J23: 1500
B24: 16 | C24: =SUM(C34*0.07)+C34 -> 1.5543248 | D24: =SUM(C34*0.04)+C34 -> 1.5107456 | E24: =SUM(C34*0.04)+C34 -> 1.5107456 | G24: 1.6 | H24: XXX | I24: XXX | J24: XXX
B25: 18 | C25: =SUM(C34*0.07)+C34 -> 1.5543248 | D25: =SUM(C34*0.04)+C34 -> 1.5107456 | E25: =SUM(C34*0.04)+C34 -> 1.5107456 | G25: 2 | H25: =SUM(H34*0.14)+H34 -> 1.36458 | I25: =SUM(H34*0.11)+H34 -> 1.32867 | J25: XXX
B26: 12,14 y 20 | C26: =SUM(C34*0.08)+C34 -> 1.5688512 | D26: =SUM(C34*0.05)+C34 -> 1.525272 | E26: =SUM(C34*0.05)+C34 -> 1.525272 | G26: 2.5 | H26: =SUM(H34*0.12)+H34 -> 1.34064 | I26: =SUM(H34*0.09)+H34 -> 1.30473 | J26: XXX
B27: 22 | C27: =SUM(C34*0.1)+C34 -> 1.597904 | D27: =SUM(C34*0.07)+C34 -> 1.5543248 | E27: =SUM(C34*0.07)+C34 -> 1.5543248 | G27: 3.17 | H27: =SUM(H34*0.11)+H34 -> 1.32867 | I27: =SUM(H34*0.08)+H34 -> 1.29276 | J27: =SUM(H34*0.08)+H34 -> 1.29276
B28: 0.65 | C28: =SUM(C34*0.12)+C34 -> 1.6269568 | D28: =SUM(C34*0.09)+C34 -> 1.5833776 | E28: XXX | G28: 4,75 Y 4.00 | H28: =SUM(H34*0.1)+H34 -> 1.3167 | I28: =SUM(H34*0.07+H34) -> 1.28079 | J28: =SUM(H34*0.07)+H34 -> 1.28079
B29: 24 | C29: =SUM(C34*0.16)+C34 -> 1.6850624 | D29: =SUM(C34*0.13)+C34 -> 1.6414832 | E29: XXX | G29: 6.35 | H29: =SUM(H34*0.11)+H34 -> 1.32867 | I29: =SUM(H34*0.08)+H34 -> 1.29276 | J29: =SUM(H34*0.08)+H34 -> 1.29276
B30: 26 | C30: =SUM(C34*0.2)+C34 -> 1.743168 | D30: =SUM(C34*0.15)+C34 -> 1.670536 | E30: XXX | G30: 8 | H30: =SUM(H34*0.11)+H34 -> 1.32867 | I30: =SUM(H34*0.08)+H34 -> 1.29276 | J30: =SUM(H34*0.08)+H34 -> 1.29276
B31: 27 | C31: =SUM(C34*0.26)+C34 -> 1.8303264 | D31: XXX | E31: XXX | G31: 9.52 | H31: =SUM(H34*0.12)+H34 -> 1.34064 | I31: =SUM(H34*0.09)+H34 -> 1.30473 | J31: =SUM(H34*0.1)+H34 -> 1.3167
B32: 30 | C32: =SUM(C34*0.32)+C34 -> 1.9174848 | D32: XXX | E32: XXX | G32: 12.7 | H32: =SUM(H34*0.12)+H34 -> 1.34064 | I32: =SUM(H34*0.09)+H34 -> 1.30473 | J32: =SUM(H34*0.1)+H34 -> 1.3167
B34: BASE | C34: =SUM(INICIO!J40) -> 1.45264 | G34: BASE | H34: =SUM(INICIO!P40) -> 1.197
B36: 3.17 | C36: 1245 | D36: S/MEL | E36: =SUM(I27*0.1)+I27 -> 1.422036 | I36: CALIDAD
B37: 4.75 | C37: 1500 | D37: S/MEL | E37: =SUM(J28*0.1)+J28 -> 1.408869 | I37: ANCHO
B38: 6.35 | C38: 1500 | D38: S/MEL | E38: =SUM(J29*0.1)+J29 -> 1.422036 | I38: ESPESOR

Sheet 28
B2: CLIENTE: | D2: =PROPER(INICIO!D41) -> Acerec/Escapes/Solomita
B4: LISTA DE PRECIOS EN PESOS
B5: DD | C5: 1000 | D5: 1220 | E5: 1500 | G5: NEGRA | H5: 1000 | I5: 1245 | J5: 1500
B6: 16 | C6: =SUM(C16*0.07)+C16 -> 2245.2222 | D6: =SUM(C16*0.04)+C16 -> 2182.272 | E6: =SUM(C16*0.04)+C16 -> 2182.272 | G6: 1.6 | H6: XXX | I6: XXX | J6: XXX
B7: 18 | C7: =SUM(C16*0.07)+C16 -> 2245.2222 | D7: =SUM(C16*0.04)+C16 -> 2182.272 | E7: =SUM(C16*0.04)+C16 -> 2182.272 | G7: 2 | H7: =SUM(H16*0.14)+H16 -> 2063.6088 | I7: =SUM(H16*0.11)+H16 -> 2009.3034 | J7: XXX
B8: 12,14 y 20 | C8: =SUM(C16*0.08)+C16 -> 2266.2056 | D8: =SUM(C16*0.05)+C16 -> 2203.2554 | E8: =SUM(C16*0.05)+C16 -> 2203.2554 | G8: 2.5 | H8: =SUM(H16*0.12)+H16 -> 2027.4052 | I8: =SUM(H16*0.09)+H16 -> 1973.0997 | J8: XXX
B9: 22 | C9: =SUM(C16*0.1)+C16 -> 2308.1723 | D9: =SUM(C16*0.07)+C16 -> 2245.2222 | E9: =SUM(C16*0.07)+C16 -> 2245.2222 | G9: 3.17 | H9: =SUM(H16*0.11)+H16 -> 2009.3034 | I9: =SUM(H16*0.08)+H16 -> 1954.9979 | J9: =SUM(H16*0.08)+H16 -> 1954.9979
B10: 0.65 | C10: =SUM(C16*0.12)+C16 -> 2350.1391 | D10: =SUM(C16*0.09)+C16 -> 2287.1889 | E10: XXX | G10: 4,75 Y 4.00 | H10: =SUM(H16*0.1)+H16 -> 1991.2015 | I10: =SUM(H16*0.07+H16) -> 1936.896 | J10: =SUM(H16*0.07)+H16 -> 1936.896
B11: 24 | C11: =SUM(C16*0.16)+C16 -> 2434.0726 | D11: =SUM(C16*0.13)+C16 -> 2371.1225 | E11: XXX | G11: 6.35 | H11: =SUM(H16*0.11)+H16 -> 2009.3034 | I11: =SUM(H16*0.08)+H16 -> 1954.9979 | J11: =SUM(H16*0.08)+H16 -> 1954.9979
B12: 26 | C12: =SUM(C16*0.2)+C16 -> 2518.0062 | D12: =SUM(C16*0.15)+C16 -> 2413.0893 | E12: XXX | G12: 8 | H12: =SUM(H16*0.11)+H16 -> 2009.3034 | I12: =SUM(H16*0.08)+H16 -> 1954.9979 | J12: =SUM(H16*0.08)+H16 -> 1954.9979
B13: 27 | C13: =SUM(C16*0.26)+C16 -> 2643.9065 | D13: XXX | E13: XXX | G13: 9.52 | H13: =SUM(H16*0.12)+H16 -> 2027.4052 | I13: =SUM(H16*0.09)+H16 -> 1973.0997 | J13: =SUM(H16*0.1)+H16 -> 1991.2015
B14: 30 | C14: =SUM(C16*0.32)+C16 -> 2769.8068 | D14: XXX | E14: XXX | G14: 12.7 | H14: =SUM(H16*0.12)+H16 -> 2027.4052 | I14: =SUM(H16*0.09)+H16 -> 1973.0997 | J14: =SUM(H16*0.1)+H16 -> 1991.2015
B16: BASE | C16: =SUM(INICIO!K41) -> 2098.3385 | G16: BASE | H16: =SUM(INICIO!Q41) -> 1810.1832
B18: 3.17 | C18: 1245 | D18: S/MEL | E18: =SUM(I9*0.1)+I9 -> 2150.4976 | I18: CALIDAD
B19: 4.75 | C19: 1500 | D19: S/MEL | E19: =SUM(J10*0.1)+J10 -> 2130.5856 | I19: ANCHO
B20: 6.35 | C20: 1500 | D20: S/MEL | E20: =SUM(J11*0.1)+J11 -> 2150.4976 | I20: ESPESOR
B22: LISTA DE PRECIOS EN DÓLARES
B23: DD | C23: 1000 | D23: 1220 | E23: 1500 | G23: NEGRA | H23: 1000 | I23: 1245 | J23: 1500
B24: 16 | C24: =SUM(C34*0.07)+C34 -> 1.4988132 | D24: =SUM(C34*0.04)+C34 -> 1.4567904 | E24: =SUM(C34*0.04)+C34 -> 1.4567904 | G24: 1.6 | H24: XXX | I24: XXX | J24: XXX
B25: 18 | C25: =SUM(C34*0.07)+C34 -> 1.4988132 | D25: =SUM(C34*0.04)+C34 -> 1.4567904 | E25: =SUM(C34*0.04)+C34 -> 1.4567904 | G25: 2 | H25: =SUM(H34*0.14)+H34 -> 1.377576 | I25: =SUM(H34*0.11)+H34 -> 1.341324 | J25: XXX
B26: 12,14 y 20 | C26: =SUM(C34*0.08)+C34 -> 1.5128208 | D26: =SUM(C34*0.05)+C34 -> 1.470798 | E26: =SUM(C34*0.05)+C34 -> 1.470798 | G26: 2.5 | H26: =SUM(H34*0.12)+H34 -> 1.353408 | I26: =SUM(H34*0.09)+H34 -> 1.317156 | J26: XXX
B27: 22 | C27: =SUM(C34*0.1)+C34 -> 1.540836 | D27: =SUM(C34*0.07)+C34 -> 1.4988132 | E27: =SUM(C34*0.07)+C34 -> 1.4988132 | G27: 3.17 | H27: =SUM(H34*0.11)+H34 -> 1.341324 | I27: =SUM(H34*0.08)+H34 -> 1.305072 | J27: =SUM(H34*0.08)+H34 -> 1.305072
B28: 0.65 | C28: =SUM(C34*0.12)+C34 -> 1.5688512 | D28: =SUM(C34*0.09)+C34 -> 1.5268284 | E28: XXX | G28: 4,75 Y 4.00 | H28: =SUM(H34*0.1)+H34 -> 1.32924 | I28: =SUM(H34*0.07+H34) -> 1.292988 | J28: =SUM(H34*0.07)+H34 -> 1.292988
B29: 24 | C29: =SUM(C34*0.16)+C34 -> 1.6248816 | D29: =SUM(C34*0.13)+C34 -> 1.5828588 | E29: XXX | G29: 6.35 | H29: =SUM(H34*0.11)+H34 -> 1.341324 | I29: =SUM(H34*0.08)+H34 -> 1.305072 | J29: =SUM(H34*0.08)+H34 -> 1.305072
B30: 26 | C30: =SUM(C34*0.2)+C34 -> 1.680912 | D30: =SUM(C34*0.15)+C34 -> 1.610874 | E30: XXX | G30: 8 | H30: =SUM(H34*0.11)+H34 -> 1.341324 | I30: =SUM(H34*0.08)+H34 -> 1.305072 | J30: =SUM(H34*0.08)+H34 -> 1.305072
B31: 27 | C31: =SUM(C34*0.26)+C34 -> 1.7649576 | D31: XXX | E31: XXX | G31: 9.52 | H31: =SUM(H34*0.12)+H34 -> 1.353408 | I31: =SUM(H34*0.09)+H34 -> 1.317156 | J31: =SUM(H34*0.1)+H34 -> 1.32924
B32: 30 | C32: =SUM(C34*0.32)+C34 -> 1.8490032 | D32: XXX | E32: XXX | G32: 12.7 | H32: =SUM(H34*0.12)+H34 -> 1.353408 | I32: =SUM(H34*0.09)+H34 -> 1.317156 | J32: =SUM(H34*0.1)+H34 -> 1.32924
B34: BASE | C34: =SUM(INICIO!J41) -> 1.40076 | G34: BASE | H34: =SUM(INICIO!P41) -> 1.2084
B36: 3.17 | C36: 1245 | D36: S/MEL | E36: =SUM(I27*0.1)+I27 -> 1.4355792 | I36: CALIDAD
B37: 4.75 | C37: 1500 | D37: S/MEL | E37: =SUM(J28*0.1)+J28 -> 1.4222868 | I37: ANCHO
B38: 6.35 | C38: 1500 | D38: S/MEL | E38: =SUM(J29*0.1)+J29 -> 1.4355792 | I38: ESPESOR

Sheet 29
B2: CLIENTE: | D2: =PROPER(INICIO!D42) -> Binetti/Titanium/Carlos
B4: LISTA DE PRECIOS EN PESOS
B5: DD | C5: 1000 | D5: 1220 | E5: 1500 | G5: NEGRA | H5: 1000 | I5: 1245 | J5: 1500
B6: 16 | C6: =SUM(C16*0.07)+C16 -> 2245.2222 | D6: =SUM(C16*0.04)+C16 -> 2182.272 | E6: =SUM(C16*0.04)+C16 -> 2182.272 | G6: 1.6 | H6: =SUM(H16*0.17)+H16 -> 2097.934 | I6: XXX | J6: XXX
B7: 18 | C7: =SUM(C16*0.07)+C16 -> 2245.2222 | D7: =SUM(C16*0.04)+C16 -> 2182.272 | E7: =SUM(C16*0.04)+C16 -> 2182.272 | G7: 2 | H7: =SUM(H16*0.14)+H16 -> 2044.1408 | I7: =SUM(H16*0.11)+H16 -> 1990.3477 | J7: XXX
B8: 12,14 y 20 | C8: =SUM(C16*0.08)+C16 -> 2266.2056 | D8: =SUM(C16*0.05)+C16 -> 2203.2554 | E8: =SUM(C16*0.05)+C16 -> 2203.2554 | G8: 2.5 | H8: =SUM(H16*0.12)+H16 -> 2008.2787 | I8: =SUM(H16*0.09)+H16 -> 1954.4855 | J8: XXX
B9: 22 | C9: =SUM(C16*0.1)+C16 -> 2308.1723 | D9: =SUM(C16*0.07)+C16 -> 2245.2222 | E9: =SUM(C16*0.07)+C16 -> 2245.2222 | G9: 3.17 | H9: =SUM(H16*0.11)+H16 -> 1990.3477 | I9: =SUM(H16*0.08)+H16 -> 1936.5545 | J9: =SUM(H16*0.08)+H16 -> 1936.5545
B10: 0.65 | C10: =SUM(C16*0.12)+C16 -> 2350.1391 | D10: =SUM(C16*0.09)+C16 -> 2287.1889 | E10: XXX | G10: 4,75 Y 4.00 | H10: =SUM(H16*0.1)+H16 -> 1972.4166 | I10: =SUM(H16*0.07+H16) -> 1918.6234 | J10: =SUM(H16*0.07)+H16 -> 1918.6234
B11: 24 | C11: =SUM(C16*0.16)+C16 -> 2434.0726 | D11: =SUM(C16*0.13)+C16 -> 2371.1225 | E11: XXX | G11: 6.35 | H11: =SUM(H16*0.11)+H16 -> 1990.3477 | I11: =SUM(H16*0.08)+H16 -> 1936.5545 | J11: =SUM(H16*0.08)+H16 -> 1936.5545
B12: 26 | C12: =SUM(C16*0.2)+C16 -> 2518.0062 | D12: =SUM(C16*0.15)+C16 -> 2413.0893 | E12: XXX | G12: 8 | H12: =SUM(H16*0.11)+H16 -> 1990.3477 | I12: =SUM(H16*0.08)+H16 -> 1936.5545 | J12: =SUM(H16*0.08)+H16 -> 1936.5545
B13: 27 | C13: =SUM(C16*0.26)+C16 -> 2643.9065 | D13: XXX | E13: XXX | G13: 9.52 | H13: =SUM(H16*0.12)+H16 -> 2008.2787 | I13: =SUM(H16*0.09)+H16 -> 1954.4855 | J13: =SUM(H16*0.1)+H16 -> 1972.4166
B14: 30 | C14: =SUM(C16*0.32)+C16 -> 2769.8068 | D14: XXX | E14: XXX | G14: 12.7 | H14: =SUM(H16*0.12)+H16 -> 2008.2787 | I14: =SUM(H16*0.09)+H16 -> 1954.4855 | J14: =SUM(H16*0.1)+H16 -> 1972.4166
B16: BASE | C16: =SUM(INICIO!K42) -> 2098.3385 | G16: BASE | H16: =SUM(INICIO!Q42) -> 1793.106 | I16: dec 2,9 | J16: 1.57
J17: .-10
B18: 3.17 | C18: 1245 | D18: S/MEL | E18: =SUM(I9*0.1)+I9 -> 2130.2099 | I18: CALIDAD
B19: 4.75 | C19: 1500 | D19: S/MEL | E19: =SUM(J10*0.1)+J10 -> 2110.4858 | I19: ANCHO
B20: 6.35 | C20: 1500 | D20: S/MEL | E20: =SUM(J11*0.1)+J11 -> 2130.2099 | I20: ESPESOR
B22: LISTA DE PRECIOS EN DÓLARES
B23: DD | C23: 1000 | D23: 1220 | E23: 1500 | G23: NEGRA | H23: 1000 | I23: 1245 | J23: 1500
B24: 16 | C24: =SUM(C34*0.07)+C34 -> 1.4988132 | D24: =SUM(C34*0.04)+C34 -> 1.4567904 | E24: =SUM(C34*0.04)+C34 -> 1.4567904 | G24: 1.6 | H24: XXX | I24: XXX | J24: XXX
B25: 18 | C25: =SUM(C34*0.07)+C34 -> 1.4988132 | D25: =SUM(C34*0.04)+C34 -> 1.4567904 | E25: =SUM(C34*0.04)+C34 -> 1.4567904 | G25: 2 | H25: =SUM(H34*0.14)+H34 -> 1.36458 | I25: =SUM(H34*0.11)+H34 -> 1.32867 | J25: XXX
B26: 12,14 y 20 | C26: =SUM(C34*0.08)+C34 -> 1.5128208 | D26: =SUM(C34*0.05)+C34 -> 1.470798 | E26: =SUM(C34*0.05)+C34 -> 1.470798 | G26: 2.5 | H26: =SUM(H34*0.12)+H34 -> 1.34064 | I26: =SUM(H34*0.09)+H34 -> 1.30473 | J26: XXX
B27: 22 | C27: =SUM(C34*0.1)+C34 -> 1.540836 | D27: =SUM(C34*0.07)+C34 -> 1.4988132 | E27: =SUM(C34*0.07)+C34 -> 1.4988132 | G27: 3.17 | H27: =SUM(H34*0.11)+H34 -> 1.32867 | I27: =SUM(H34*0.08)+H34 -> 1.29276 | J27: =SUM(H34*0.08)+H34 -> 1.29276
B28: 0.65 | C28: =SUM(C34*0.12)+C34 -> 1.5688512 | D28: =SUM(C34*0.09)+C34 -> 1.5268284 | E28: XXX | G28: 4,75 Y 4.00 | H28: =SUM(H34*0.1)+H34 -> 1.3167 | I28: =SUM(H34*0.07+H34) -> 1.28079 | J28: =SUM(H34*0.07)+H34 -> 1.28079
B29: 24 | C29: =SUM(C34*0.16)+C34 -> 1.6248816 | D29: =SUM(C34*0.13)+C34 -> 1.5828588 | E29: XXX | G29: 6.35 | H29: =SUM(H34*0.11)+H34 -> 1.32867 | I29: =SUM(H34*0.08)+H34 -> 1.29276 | J29: =SUM(H34*0.08)+H34 -> 1.29276
B30: 26 | C30: =SUM(C34*0.2)+C34 -> 1.680912 | D30: =SUM(C34*0.15)+C34 -> 1.610874 | E30: XXX | G30: 8 | H30: =SUM(H34*0.11)+H34 -> 1.32867 | I30: =SUM(H34*0.08)+H34 -> 1.29276 | J30: =SUM(H34*0.08)+H34 -> 1.29276
B31: 27 | C31: =SUM(C34*0.26)+C34 -> 1.7649576 | D31: XXX | E31: XXX | G31: 9.52 | H31: =SUM(H34*0.12)+H34 -> 1.34064 | I31: =SUM(H34*0.09)+H34 -> 1.30473 | J31: =SUM(H34*0.1)+H34 -> 1.3167
B32: 30 | C32: =SUM(C34*0.32)+C34 -> 1.8490032 | D32: XXX | E32: XXX | G32: 12.7 | H32: =SUM(H34*0.12)+H34 -> 1.34064 | I32: =SUM(H34*0.09)+H34 -> 1.30473 | J32: =SUM(H34*0.1)+H34 -> 1.3167
B34: BASE | C34: =SUM(INICIO!J42) -> 1.40076 | G34: BASE | H34: =SUM(INICIO!P42) -> 1.197
B36: 3.17 | C36: 1245 | D36: S/MEL | E36: =SUM(I27*0.1)+I27 -> 1.422036 | I36: CALIDAD
B37: 4.75 | C37: 1500 | D37: S/MEL | E37: =SUM(J28*0.1)+J28 -> 1.408869 | I37: ANCHO
B38: 6.35 | C38: 1500 | D38: S/MEL | E38: =SUM(J29*0.1)+J29 -> 1.422036 | I38: ESPESOR
B41: galv | C41: 1000 | D41: 1220
B42: 16 14 | D42: 1.627
B43: 18 | D43: 1.639
B44: 20 | D44: 1.653
B45: 22 | D45: 1.672
B46: 24
B47: 25 | D47: 1.692
B48: 26

Sheet 30
A1: t
B2: CLIENTE: | D2: =PROPER(INICIO!D43) -> Cuatro Ases/Secaire/Petenelo/Maresca
B4: LISTA DE PRECIOS EN PESOS
B5: DD | C5: 1000 | D5: 1220 | E5: 1500 | G5: NEGRA | H5: 1000 | I5: 1245 | J5: 1500
B6: 16 | C6: =SUM(C16*0.07)+C16 -> 2245.2222 | D6: =SUM(C16*0.04)+C16 -> 2182.272 | E6: =SUM(C16*0.04)+C16 -> 2182.272 | G6: 1.6 | H6: XXX | I6: XXX | J6: XXX
B7: 18 | C7: =SUM(C16*0.07)+C16 -> 2245.2222 | D7: =SUM(C16*0.04)+C16 -> 2182.272 | E7: =SUM(C16*0.04)+C16 -> 2182.272 | G7: 2 | H7: =SUM(H16*0.14)+H16 -> 2044.1408 | I7: =SUM(H16*0.11)+H16 -> 1990.3477 | J7: XXX
B8: 12,14 y 20 | C8: =SUM(C16*0.08)+C16 -> 2266.2056 | D8: =SUM(C16*0.05)+C16 -> 2203.2554 | E8: =SUM(C16*0.05)+C16 -> 2203.2554 | G8: 2.5 | H8: =SUM(H16*0.12)+H16 -> 2008.2787 | I8: =SUM(H16*0.09)+H16 -> 1954.4855 | J8: XXX
B9: 22 | C9: =SUM(C16*0.1)+C16 -> 2308.1723 | D9: =SUM(C16*0.07)+C16 -> 2245.2222 | E9: =SUM(C16*0.07)+C16 -> 2245.2222 | G9: 3.17 | H9: =SUM(H16*0.11)+H16 -> 1990.3477 | I9: =SUM(H16*0.08)+H16 -> 1936.5545 | J9: =SUM(H16*0.08)+H16 -> 1936.5545
B10: 0.65 | C10: =SUM(C16*0.12)+C16 -> 2350.1391 | D10: =SUM(C16*0.09)+C16 -> 2287.1889 | E10: XXX | G10: 4,75 Y 4.00 | H10: =SUM(H16*0.1)+H16 -> 1972.4166 | I10: =SUM(H16*0.07+H16) -> 1918.6234 | J10: =SUM(H16*0.07)+H16 -> 1918.6234
B11: 24 | C11: =SUM(C16*0.16)+C16 -> 2434.0726 | D11: =SUM(C16*0.13)+C16 -> 2371.1225 | E11: XXX | G11: 6.35 | H11: =SUM(H16*0.11)+H16 -> 1990.3477 | I11: =SUM(H16*0.08)+H16 -> 1936.5545 | J11: =SUM(H16*0.08)+H16 -> 1936.5545 | L11: angosta 955
B12: 26 | C12: =SUM(C16*0.2)+C16 -> 2518.0062 | D12: =SUM(C16*0.15)+C16 -> 2413.0893 | E12: XXX | G12: 8 | H12: =SUM(H16*0.11)+H16 -> 1990.3477 | I12: =SUM(H16*0.08)+H16 -> 1936.5545 | J12: =SUM(H16*0.08)+H16 -> 1936.5545 | L12: dec 2,9 950
B13: 27 | C13: =SUM(C16*0.26)+C16 -> 2643.9065 | D13: XXX | E13: XXX | G13: 9.52 | H13: =SUM(H16*0.12)+H16 -> 2008.2787 | I13: =SUM(H16*0.09)+H16 -> 1954.4855 | J13: =SUM(H16*0.1)+H16 -> 1972.4166
B14: 30 | C14: =SUM(C16*0.32)+C16 -> 2769.8068 | D14: XXX | E14: XXX | G14: 12.7 | H14: =SUM(H16*0.12)+H16 -> 2008.2787 | I14: =SUM(H16*0.09)+H16 -> 1954.4855 | J14: =SUM(H16*0.1)+H16 -> 1972.4166
B16: BASE | C16: =SUM(INICIO!K43) -> 2098.3385 | G16: BASE | H16: =SUM(INICIO!Q43) -> 1793.106 | J16: maresca -8
J17: pamela -10
B18: 3.17 | C18: 1245 | D18: S/MEL | E18: =SUM(I9*0.1)+I9 -> 2130.2099 | I18: CALIDAD
B19: 4.75 | C19: 1500 | D19: S/MEL | E19: =SUM(J10*0.1)+J10 -> 2110.4858 | I19: ANCHO
B20: 6.35 | C20: 1500 | D20: S/MEL | E20: =SUM(J11*0.1)+J11 -> 2130.2099 | I20: ESPESOR
B22: LISTA DE PRECIOS EN DÓLARES
B23: DD | C23: 1000 | D23: 1220 | E23: 1500 | G23: NEGRA | H23: 1000 | I23: 1245 | J23: 1500
B24: 16 | C24: =SUM(C34*0.07)+C34 -> 1.4988132 | D24: =SUM(C34*0.04)+C34 -> 1.4567904 | E24: =SUM(C34*0.04)+C34 -> 1.4567904 | G24: 1.6 | H24: XXX | I24: XXX | J24: XXX
B25: 18 | C25: =SUM(C34*0.07)+C34 -> 1.4988132 | D25: =SUM(C34*0.04)+C34 -> 1.4567904 | E25: =SUM(C34*0.04)+C34 -> 1.4567904 | G25: 2 | H25: =SUM(H34*0.14)+H34 -> 1.36458 | I25: =SUM(H34*0.11)+H34 -> 1.32867 | J25: XXX
B26: 12,14 y 20 | C26: =SUM(C34*0.08)+C34 -> 1.5128208 | D26: =SUM(C34*0.05)+C34 -> 1.470798 | E26: =SUM(C34*0.05)+C34 -> 1.470798 | G26: 2.5 | H26: =SUM(H34*0.12)+H34 -> 1.34064 | I26: =SUM(H34*0.09)+H34 -> 1.30473 | J26: XXX
B27: 22 | C27: =SUM(C34*0.1)+C34 -> 1.540836 | D27: =SUM(C34*0.07)+C34 -> 1.4988132 | E27: =SUM(C34*0.07)+C34 -> 1.4988132 | G27: 3.17 | H27: =SUM(H34*0.11)+H34 -> 1.32867 | I27: =SUM(H34*0.08)+H34 -> 1.29276 | J27: =SUM(H34*0.08)+H34 -> 1.29276
B28: 0.65 | C28: =SUM(C34*0.12)+C34 -> 1.5688512 | D28: =SUM(C34*0.09)+C34 -> 1.5268284 | E28: XXX | G28: 4,75 Y 4.00 | H28: =SUM(H34*0.1)+H34 -> 1.3167 | I28: =SUM(H34*0.07+H34) -> 1.28079 | J28: =SUM(H34*0.07)+H34 -> 1.28079
B29: 24 | C29: =SUM(C34*0.16)+C34 -> 1.6248816 | D29: =SUM(C34*0.13)+C34 -> 1.5828588 | E29: XXX | G29: 6.35 | H29: =SUM(H34*0.11)+H34 -> 1.32867 | I29: =SUM(H34*0.08)+H34 -> 1.29276 | J29: =SUM(H34*0.08)+H34 -> 1.29276
B30: 26 | C30: =SUM(C34*0.2)+C34 -> 1.680912 | D30: =SUM(C34*0.15)+C34 -> 1.610874 | E30: XXX | G30: 8 | H30: =SUM(H34*0.11)+H34 -> 1.32867 | I30: =SUM(H34*0.08)+H34 -> 1.29276 | J30: =SUM(H34*0.08)+H34 -> 1.29276
B31: 27 | C31: =SUM(C34*0.26)+C34 -> 1.7649576 | D31: XXX | E31: XXX | G31: 9.52 | H31: =SUM(H34*0.12)+H34 -> 1.34064 | I31: =SUM(H34*0.09)+H34 -> 1.30473 | J31: =SUM(H34*0.1)+H34 -> 1.3167
B32: 30 | C32: =SUM(C34*0.32)+C34 -> 1.8490032 | D32: XXX | E32: XXX | G32: 12.7 | H32: =SUM(H34*0.12)+H34 -> 1.34064 | I32: =SUM(H34*0.09)+H34 -> 1.30473 | J32: =SUM(H34*0.1)+H34 -> 1.3167
B34: BASE | C34: =SUM(INICIO!J43) -> 1.40076 | G34: BASE | H34: =SUM(INICIO!P43) -> 1.197
B36: 3.17 | C36: 1245 | D36: S/MEL | E36: =SUM(I27*0.1)+I27 -> 1.422036 | I36: CALIDAD
B37: 4.75 | C37: 1500 | D37: S/MEL | E37: =SUM(J28*0.1)+J28 -> 1.408869 | I37: ANCHO
B38: 6.35 | C38: 1500 | D38: S/MEL | E38: =SUM(J29*0.1)+J29 -> 1.422036 | I38: ESPESOR

Sheet 31
B2: CLIENTE: | D2: =PROPER(INICIO!D44) -> Colo
B4: LISTA DE PRECIOS EN PESOS
B5: DD | C5: 1000 | D5: 1220 | E5: 1500 | G5: NEGRA | H5: 1000 | I5: 1245 | J5: 1500
B6: 16 | C6: =SUM(C16*0.07)+C16 -> 2203.644 | D6: =SUM(C16*0.04)+C16 -> 2141.8596 | E6: =SUM(C16*0.04)+C16 -> 2141.8596 | G6: 1.6 | H6: XXX | I6: XXX | J6: XXX
B7: 18 | C7: =SUM(C16*0.07)+C16 -> 2203.644 | D7: =SUM(C16*0.04)+C16 -> 2141.8596 | E7: =SUM(C16*0.04)+C16 -> 2141.8596 | G7: 2 | H7: =SUM(H16*0.14)+H16 -> 1985.7368 | I7: =SUM(H16*0.11)+H16 -> 1933.4806 | J7: XXX
B8: 12,14 y 20 | C8: =SUM(C16*0.08)+C16 -> 2224.2388 | D8: =SUM(C16*0.05)+C16 -> 2162.4544 | E8: =SUM(C16*0.05)+C16 -> 2162.4544 | G8: 2.5 | H8: =SUM(H16*0.12)+H16 -> 1950.8993 | I8: =SUM(H16*0.09)+H16 -> 1898.6431 | J8: XXX
B9: 22 | C9: =SUM(C16*0.1)+C16 -> 2265.4284 | D9: =SUM(C16*0.07)+C16 -> 2203.644 | E9: =SUM(C16*0.07)+C16 -> 2203.644 | G9: 3.17 | H9: =SUM(H16*0.11)+H16 -> 1933.4806 | I9: =SUM(H16*0.08)+H16 -> 1881.2244 | J9: =SUM(H16*0.08)+H16 -> 1881.2244
B10: 0.65 | C10: =SUM(C16*0.12)+C16 -> 2306.618 | D10: =SUM(C16*0.09)+C16 -> 2244.8336 | E10: XXX | G10: 4,75 Y 4.00 | H10: =SUM(H16*0.1)+H16 -> 1916.0618 | I10: =SUM(H16*0.07+H16) -> 1863.8056 | J10: =SUM(H16*0.07)+H16 -> 1863.8056
B11: 24 | C11: =SUM(C16*0.16)+C16 -> 2388.9972 | D11: =SUM(C16*0.13)+C16 -> 2327.2128 | E11: XXX | G11: 6.35 | H11: =SUM(H16*0.11)+H16 -> 1933.4806 | I11: =SUM(H16*0.08)+H16 -> 1881.2244 | J11: =SUM(H16*0.08)+H16 -> 1881.2244
B12: 26 | C12: =SUM(C16*0.2)+C16 -> 2471.3764 | D12: =SUM(C16*0.15)+C16 -> 2368.4024 | E12: XXX | G12: 8 | H12: =SUM(H16*0.11)+H16 -> 1933.4806 | I12: =SUM(H16*0.08)+H16 -> 1881.2244 | J12: =SUM(H16*0.08)+H16 -> 1881.2244
B13: 27 | C13: =SUM(C16*0.26)+C16 -> 2594.9453 | D13: XXX | E13: XXX | G13: 9.52 | H13: =SUM(H16*0.12)+H16 -> 1950.8993 | I13: =SUM(H16*0.09)+H16 -> 1898.6431 | J13: =SUM(H16*0.09)+H16 -> 1898.6431
B14: 30 | C14: =SUM(C16*0.32)+C16 -> 2718.5141 | D14: XXX | E14: XXX | G14: 12.7 | H14: =SUM(H16*0.12)+H16 -> 1950.8993 | I14: =SUM(H16*0.09)+H16 -> 1898.6431 | J14: =SUM(H16*0.09)+H16 -> 1898.6431
B16: BASE | C16: =SUM(INICIO!K44) -> 2059.4804 | G16: BASE | H16: =SUM(INICIO!Q44) -> 1741.8744 | I16: colo -10%
B18: 3.17 | C18: 1245 | D18: S/MEL | E18: =SUM(I9*0.1)+I9 -> 2069.3468 | I18: CALIDAD
B19: 4.75 | C19: 1500 | D19: S/MEL | E19: =SUM(J10*0.1)+J10 -> 2050.1862 | I19: ANCHO
B20: 6.35 | C20: 1500 | D20: S/MEL | E20: =SUM(J11*0.1)+J11 -> 2069.3468 | I20: ESPESOR
B22: LISTA DE PRECIOS EN DÓLARES
B23: DD | C23: 1000 | D23: 1220 | E23: 1500 | G23: NEGRA | H23: 1000 | I23: 1245 | J23: 1500
B24: 16 | C24: =SUM(C34*0.07)+C34 -> 1.4710574 | D24: =SUM(C34*0.04)+C34 -> 1.4298128 | E24: =SUM(C34*0.04)+C34 -> 1.4298128 | G24: 1.6 | H24: XXX | I24: XXX | J24: XXX
B25: 18 | C25: =SUM(C34*0.07)+C34 -> 1.4710574 | D25: =SUM(C34*0.04)+C34 -> 1.4298128 | E25: =SUM(C34*0.04)+C34 -> 1.4298128 | G25: 2 | H25: =SUM(H34*0.14)+H34 -> 1.325592 | I25: =SUM(H34*0.11)+H34 -> 1.290708 | J25: XXX
B26: 12,14 y 20 | C26: =SUM(C34*0.08)+C34 -> 1.4848056 | D26: =SUM(C34*0.05)+C34 -> 1.443561 | E26: =SUM(C34*0.05)+C34 -> 1.443561 | G26: 2.5 | H26: =SUM(H34*0.12)+H34 -> 1.302336 | I26: =SUM(H34*0.09)+H34 -> 1.267452 | J26: XXX
B27: 22 | C27: =SUM(C34*0.1)+C34 -> 1.512302 | D27: =SUM(C34*0.07)+C34 -> 1.4710574 | E27: =SUM(C34*0.07)+C34 -> 1.4710574 | G27: 3.17 | H27: =SUM(H34*0.11)+H34 -> 1.290708 | I27: =SUM(H34*0.08)+H34 -> 1.255824 | J27: =SUM(H34*0.08)+H34 -> 1.255824
B28: 0.65 | C28: =SUM(C34*0.12)+C34 -> 1.5397984 | D28: =SUM(C34*0.09)+C34 -> 1.4985538 | E28: XXX | G28: 4,75 Y 4.00 | H28: =SUM(H34*0.1)+H34 -> 1.27908 | I28: =SUM(H34*0.07+H34) -> 1.244196 | J28: =SUM(H34*0.07)+H34 -> 1.244196
B29: 24 | C29: =SUM(C34*0.16)+C34 -> 1.5947912 | D29: =SUM(C34*0.13)+C34 -> 1.5535466 | E29: XXX | G29: 6.35 | H29: =SUM(H34*0.11)+H34 -> 1.290708 | I29: =SUM(H34*0.08)+H34 -> 1.255824 | J29: =SUM(H34*0.08)+H34 -> 1.255824
B30: 26 | C30: =SUM(C34*0.2)+C34 -> 1.649784 | D30: =SUM(C34*0.15)+C34 -> 1.581043 | E30: XXX | G30: 8 | H30: =SUM(H34*0.11)+H34 -> 1.290708 | I30: =SUM(H34*0.08)+H34 -> 1.255824 | J30: =SUM(H34*0.08)+H34 -> 1.255824
B31: 27 | C31: =SUM(C34*0.26)+C34 -> 1.7322732 | D31: XXX | E31: XXX | G31: 9.52 | H31: =SUM(H34*0.12)+H34 -> 1.302336 | I31: =SUM(H34*0.09)+H34 -> 1.267452 | J31: =SUM(H34*0.09)+H34 -> 1.267452
B32: 30 | C32: =SUM(C34*0.32)+C34 -> 1.8147624 | D32: XXX | E32: XXX | G32: 12.7 | H32: =SUM(H34*0.12)+H34 -> 1.302336 | I32: =SUM(H34*0.09)+H34 -> 1.267452 | J32: =SUM(H34*0.09)+H34 -> 1.267452
B34: BASE | C34: =SUM(INICIO!J44) -> 1.37482 | G34: BASE | H34: =SUM(INICIO!P44) -> 1.1628
B36: 3.17 | C36: 1245 | D36: S/MEL | E36: =SUM(I27*0.1)+I27 -> 1.3814064 | I36: CALIDAD
B37: 4.75 | C37: 1500 | D37: S/MEL | E37: =SUM(J28*0.1)+J28 -> 1.3686156 | I37: ANCHO
B38: 6.35 | C38: 1500 | D38: S/MEL | E38: =SUM(J29*0.1)+J29 -> 1.3814064 | I38: ESPESOR
B40: galv | C40: 1000 | D40: 1220
B41: 16-14 | C41: =SUM(C51*0.07)+C51 -> 0
B42: 18
B43: 20 | C43: =SUM(C51*0.08)+C51 -> 0
B44: 22 | C44: =SUM(C53*0.07)+C53 -> 0
B45: 25 | C45: =SUM(C53*0.08)+C53 -> 0

Sheet 32
B2: CLIENTE: | D2: =PROPER(INICIO!D45) -> Dalma/Fornari
B4: LISTA DE PRECIOS EN PESOS
B5: DD | C5: 1000 | D5: 1220 | E5: 1500 | G5: NEGRA | H5: 1000 | I5: 1245 | J5: 1500
B6: 16 | C6: =SUM(C16*0.07)+C16 -> 2328.3786 | D6: =SUM(C16*0.04)+C16 -> 2263.0969 | E6: =SUM(C16*0.04)+C16 -> 2263.0969 | G6: 1.6 | H6: XXX | I6: XXX | J6: XXX
B7: 18 | C7: =SUM(C16*0.07)+C16 -> 2328.3786 | D7: =SUM(C16*0.04)+C16 -> 2263.0969 | E7: =SUM(C16*0.04)+C16 -> 2263.0969 | G7: 2 | H7: =SUM(H16*0.14)+H16 -> 2122.0129 | I7: =SUM(H16*0.11)+H16 -> 2066.1704 | J7: XXX
B8: 12,14 y 20 | C8: =SUM(C16*0.08)+C16 -> 2350.1391 | D8: =SUM(C16*0.05)+C16 -> 2284.8575 | E8: =SUM(C16*0.05)+C16 -> 2284.8575 | G8: 2.5 | H8: =SUM(H16*0.12)+H16 -> 2084.7846 | I8: =SUM(H16*0.09)+H16 -> 2028.9421 | J8: XXX
B9: 22 | C9: =SUM(C16*0.1)+C16 -> 2393.6602 | D9: =SUM(C16*0.07)+C16 -> 2328.3786 | E9: =SUM(C16*0.07)+C16 -> 2328.3786 | G9: 3.17 | H9: =SUM(H16*0.11)+H16 -> 2066.1704 | I9: =SUM(H16*0.08)+H16 -> 2010.328 | J9: =SUM(H16*0.08)+H16 -> 2010.328
B10: 0.65 | C10: =SUM(C16*0.12)+C16 -> 2437.1813 | D10: =SUM(C16*0.09)+C16 -> 2371.8996 | E10: XXX | G10: 4,75 Y 4.00 | H10: =SUM(H16*0.1)+H16 -> 2047.5563 | I10: =SUM(H16*0.07+H16) -> 1991.7138 | J10: =SUM(H16*0.07)+H16 -> 1991.7138
B11: 24 | C11: =SUM(C16*0.16)+C16 -> 2524.2235 | D11: =SUM(C16*0.13)+C16 -> 2458.9418 | E11: XXX | G11: 6.35 | H11: =SUM(H16*0.11)+H16 -> 2066.1704 | I11: =SUM(H16*0.08)+H16 -> 2010.328 | J11: =SUM(H16*0.08)+H16 -> 2010.328
B12: 26 | C12: =SUM(C16*0.2)+C16 -> 2611.2657 | D12: =SUM(C16*0.15)+C16 -> 2502.4629 | E12: XXX | G12: 8 | H12: =SUM(H16*0.11)+H16 -> 2066.1704 | I12: =SUM(H16*0.08)+H16 -> 2010.328 | J12: =SUM(H16*0.08)+H16 -> 2010.328
B13: 27 | C13: =SUM(C16*0.26)+C16 -> 2741.8289 | D13: XXX | E13: XXX | G13: 9.52 | H13: =SUM(H16*0.12)+H16 -> 2084.7846 | I13: =SUM(H16*0.09)+H16 -> 2028.9421 | J13: =SUM(H16*0.1)+H16 -> 2047.5563
B14: 30 | C14: =SUM(C16*0.32)+C16 -> 2872.3922 | D14: XXX | E14: XXX | G14: 12.7 | H14: =SUM(H16*0.12)+H16 -> 2084.7846 | I14: =SUM(H16*0.09)+H16 -> 2028.9421 | J14: =SUM(H16*0.1)+H16 -> 2047.5563
B16: BASE | C16: =SUM(INICIO!K45) -> 2176.0547 | G16: BASE | H16: =SUM(INICIO!Q45) -> 1861.4148
B18: 3.17 | C18: 1245 | D18: S/MEL | E18: =SUM(I9*0.1)+I9 -> 2211.3608 | I18: CALIDAD
B19: 4.75 | C19: 1500 | D19: S/MEL | E19: =SUM(J10*0.1)+J10 -> 2190.8852 | I19: ANCHO
B20: 6.35 | C20: 1500 | D20: S/MEL | E20: =SUM(J11*0.1)+J11 -> 2211.3608 | I20: ESPESOR
B22: LISTA DE PRECIOS EN DÓLARES
B23: DD | C23: 1000 | D23: 1220 | E23: 1500 | G23: NEGRA | H23: 1000 | I23: 1245 | J23: 1500
B24: 16 | C24: =SUM(C34*0.07)+C34 -> 1.5543248 | D24: =SUM(C34*0.04)+C34 -> 1.5107456 | E24: =SUM(C34*0.04)+C34 -> 1.5107456 | G24: 1.6 | H24: XXX | I24: XXX | J24: XXX
B25: 18 | C25: =SUM(C34*0.07)+C34 -> 1.5543248 | D25: =SUM(C34*0.04)+C34 -> 1.5107456 | E25: =SUM(C34*0.04)+C34 -> 1.5107456 | G25: 2 | H25: =SUM(H34*0.14)+H34 -> 1.416564 | I25: =SUM(H34*0.11)+H34 -> 1.379286 | J25: XXX
B26: 12,14 y 20 | C26: =SUM(C34*0.08)+C34 -> 1.5688512 | D26: =SUM(C34*0.05)+C34 -> 1.525272 | E26: =SUM(C34*0.05)+C34 -> 1.525272 | G26: 2.5 | H26: =SUM(H34*0.12)+H34 -> 1.391712 | I26: =SUM(H34*0.09)+H34 -> 1.354434 | J26: XXX
B27: 22 | C27: =SUM(C34*0.1)+C34 -> 1.597904 | D27: =SUM(C34*0.07)+C34 -> 1.5543248 | E27: =SUM(C34*0.07)+C34 -> 1.5543248 | G27: 3.17 | H27: =SUM(H34*0.11)+H34 -> 1.379286 | I27: =SUM(H34*0.08)+H34 -> 1.342008 | J27: =SUM(H34*0.08)+H34 -> 1.342008
B28: 0.65 | C28: =SUM(C34*0.12)+C34 -> 1.6269568 | D28: =SUM(C34*0.09)+C34 -> 1.5833776 | E28: XXX | G28: 4,75 Y 4.00 | H28: =SUM(H34*0.1)+H34 -> 1.36686 | I28: =SUM(H34*0.07+H34) -> 1.329582 | J28: =SUM(H34*0.07)+H34 -> 1.329582
B29: 24 | C29: =SUM(C34*0.16)+C34 -> 1.6850624 | D29: =SUM(C34*0.13)+C34 -> 1.6414832 | E29: XXX | G29: 6.35 | H29: =SUM(H34*0.11)+H34 -> 1.379286 | I29: =SUM(H34*0.08)+H34 -> 1.342008 | J29: =SUM(H34*0.08)+H34 -> 1.342008
B30: 26 | C30: =SUM(C34*0.2)+C34 -> 1.743168 | D30: =SUM(C34*0.15)+C34 -> 1.670536 | E30: XXX | G30: 8 | H30: =SUM(H34*0.11)+H34 -> 1.379286 | I30: =SUM(H34*0.08)+H34 -> 1.342008 | J30: =SUM(H34*0.08)+H34 -> 1.342008
B31: 27 | C31: =SUM(C34*0.26)+C34 -> 1.8303264 | D31: XXX | E31: XXX | G31: 9.52 | H31: =SUM(H34*0.12)+H34 -> 1.391712 | I31: =SUM(H34*0.09)+H34 -> 1.354434 | J31: =SUM(H34*0.1)+H34 -> 1.36686
B32: 30 | C32: =SUM(C34*0.32)+C34 -> 1.9174848 | D32: XXX | E32: XXX | G32: 12.7 | H32: =SUM(H34*0.12)+H34 -> 1.391712 | I32: =SUM(H34*0.09)+H34 -> 1.354434 | J32: =SUM(H34*0.1)+H34 -> 1.36686
B34: BASE | C34: =SUM(INICIO!J45) -> 1.45264 | G34: BASE | H34: =SUM(INICIO!P45) -> 1.2426
B36: 3.17 | C36: 1245 | D36: S/MEL | E36: =SUM(I27*0.1)+I27 -> 1.4762088 | I36: CALIDAD
B37: 4.75 | C37: 1500 | D37: S/MEL | E37: =SUM(J28*0.1)+J28 -> 1.4625402 | I37: ANCHO
B38: 6.35 | C38: 1500 | D38: S/MEL | E38: =SUM(J29*0.1)+J29 -> 1.4762088 | I38: ESPESOR
B41: caño | C41: u$s
B42: 60x100x1/8 | C42: 68.19
B43: 40x80x2,5 | C43: 44.35
B44: 30x1,6 | C44: 12.43
B45: 60x100x2,5 | C45: 54.5

Sheet 33
B2: CLIENTE: | D2: =PROPER(INICIO!D46) -> Itexa
B4: LISTA DE PRECIOS EN PESOS
B5: DD | C5: 1000 | D5: 1220 | E5: 1500 | G5: NEGRA | H5: 1000 | I5: 1245 | J5: 1500
B6: 16 | C6: =SUM(C16*0.07)+C16 -> 2245.2222 | D6: =SUM(C16*0.04)+C16 -> 2182.272 | E6: =SUM(C16*0.04)+C16 -> 2182.272 | F6: =E6*90/100 -> 1964.0448 | G6: 1.6 | H6: XXX | I6: XXX | J6: XXX
B7: 18 | C7: =SUM(C16*0.07)+C16 -> 2245.2222 | D7: =SUM(C16*0.04)+C16 -> 2182.272 | E7: =SUM(C16*0.04)+C16 -> 2182.272 | G7: 2 | H7: =SUM(H16*0.14)+H16 -> 2044.1408 | I7: =SUM(H16*0.11)+H16 -> 1990.3477 | J7: XXX
B8: 12,14 y 20 | C8: =SUM(C16*0.08)+C16 -> 2266.2056 | D8: =SUM(C16*0.05)+C16 -> 2203.2554 | E8: =SUM(C16*0.05)+C16 -> 2203.2554 | G8: 2.5 | H8: =SUM(H16*0.12)+H16 -> 2008.2787 | I8: =SUM(H16*0.09)+H16 -> 1954.4855 | J8: XXX
B9: 22 | C9: =SUM(C16*0.1)+C16 -> 2308.1723 | D9: =SUM(C16*0.07)+C16 -> 2245.2222 | E9: =SUM(C16*0.07)+C16 -> 2245.2222 | G9: 3.17 | H9: =SUM(H16*0.11)+H16 -> 1990.3477 | I9: =SUM(H16*0.08)+H16 -> 1936.5545 | J9: =SUM(H16*0.08)+H16 -> 1936.5545
B10: 0.65 | C10: =SUM(C16*0.12)+C16 -> 2350.1391 | D10: =SUM(C16*0.09)+C16 -> 2287.1889 | E10: XXX | G10: 4,75 Y 4.00 | H10: =SUM(H16*0.11)+H16 -> 1990.3477 | I10: =SUM(H16*0.08+H16) -> 1936.5545 | J10: =SUM(H16*0.08)+H16 -> 1936.5545 | K10: =J10*90/100 -> 1742.899
B11: 24 | C11: =SUM(C16*0.16)+C16 -> 2434.0726 | D11: =SUM(C16*0.13)+C16 -> 2371.1225 | E11: XXX | G11: 6.35 | H11: =SUM(H16*0.11)+H16 -> 1990.3477 | I11: =SUM(H16*0.08)+H16 -> 1936.5545 | J11: =SUM(H16*0.08)+H16 -> 1936.5545 | K11: =J11*90/100 -> 1742.899
B12: 26 | C12: =SUM(C16*0.2)+C16 -> 2518.0062 | D12: =SUM(C16*0.15)+C16 -> 2413.0893 | E12: XXX | G12: 8 | H12: =SUM(H16*0.11)+H16 -> 1990.3477 | I12: =SUM(H16*0.08)+H16 -> 1936.5545 | J12: =SUM(H16*0.08)+H16 -> 1936.5545 | K12: =J12*90/100 -> 1742.899
B13: 27 | C13: =SUM(C16*0.26)+C16 -> 2643.9065 | D13: XXX | E13: XXX | G13: 9.52 | H13: =SUM(H16*0.12)+H16 -> 2008.2787 | I13: =SUM(H16*0.09)+H16 -> 1954.4855 | J13: =SUM(H16*0.09)+H16 -> 1954.4855 | K13: =J13*90/100 -> 1759.037
B14: 30 | C14: =SUM(C16*0.32)+C16 -> 2769.8068 | D14: XXX | E14: XXX | G14: 12.7 | H14: =SUM(H16*0.12)+H16 -> 2008.2787 | I14: =SUM(H16*0.09)+H16 -> 1954.4855 | J14: =SUM(H16*0.09)+H16 -> 1954.4855 | K14: =J14*90/100 -> 1759.037
B16: BASE | C16: =SUM(INICIO!K46) -> 2098.3385 | G16: BASE | H16: =SUM(INICIO!Q46) -> 1793.106 | I16: gruesa | J16: 1.55
B18: 3.17 | C18: 1245 | D18: S/MEL | E18: =SUM(I9*0.1)+I9 -> 2130.2099 | I18: CALIDAD | J18: -0.1
B19: 4.75 | C19: 1500 | D19: S/MEL | E19: =SUM(J10*0.1)+J10 -> 2130.2099 | I19: ANCHO
B20: 6.35 | C20: 1500 | D20: S/MEL | E20: =SUM(J11*0.1)+J11 -> 2130.2099 | I20: ESPESOR
B22: LISTA DE PRECIOS EN DÓLARES
B23: DD | C23: 1000 | D23: 1220 | E23: 1500 | G23: NEGRA | H23: 1000 | I23: 1245 | J23: 1500
B24: 16 | C24: =SUM(C34*0.07)+C34 -> 1.4988132 | D24: =SUM(C34*0.04)+C34 -> 1.4567904 | E24: =SUM(C34*0.04)+C34 -> 1.4567904 | G24: 1.6 | H24: XXX | I24: XXX | J24: XXX
B25: 18 | C25: =SUM(C34*0.07)+C34 -> 1.4988132 | D25: =SUM(C34*0.04)+C34 -> 1.4567904 | E25: =SUM(C34*0.04)+C34 -> 1.4567904 | G25: 2 | H25: =SUM(H34*0.14)+H34 -> 1.36458 | I25: =SUM(H34*0.11)+H34 -> 1.32867 | J25: XXX
B26: 12,14 y 20 | C26: =SUM(C34*0.08)+C34 -> 1.5128208 | D26: =SUM(C34*0.05)+C34 -> 1.470798 | E26: =SUM(C34*0.05)+C34 -> 1.470798 | G26: 2.5 | H26: =SUM(H34*0.12)+H34 -> 1.34064 | I26: =SUM(H34*0.09)+H34 -> 1.30473 | J26: XXX
B27: 22 | C27: =SUM(C34*0.1)+C34 -> 1.540836 | D27: =SUM(C34*0.07)+C34 -> 1.4988132 | E27: =SUM(C34*0.07)+C34 -> 1.4988132 | G27: 3.17 | H27: =SUM(H34*0.11)+H34 -> 1.32867 | I27: =SUM(H34*0.08)+H34 -> 1.29276 | J27: =SUM(H34*0.08)+H34 -> 1.29276
B28: 0.65 | C28: =SUM(C34*0.12)+C34 -> 1.5688512 | D28: =SUM(C34*0.09)+C34 -> 1.5268284 | E28: XXX | G28: 4,75 Y 4.00 | H28: =SUM(H34*0.11)+H34 -> 1.32867 | I28: =SUM(H34*0.08+H34) -> 1.29276 | J28: =SUM(H34*0.08)+H34 -> 1.29276
B29: 24 | C29: =SUM(C34*0.16)+C34 -> 1.6248816 | D29: =SUM(C34*0.13)+C34 -> 1.5828588 | E29: XXX | G29: 6.35 | H29: =SUM(H34*0.11)+H34 -> 1.32867 | I29: =SUM(H34*0.08)+H34 -> 1.29276 | J29: =SUM(H34*0.08)+H34 -> 1.29276
B30: 26 | C30: =SUM(C34*0.2)+C34 -> 1.680912 | D30: =SUM(C34*0.15)+C34 -> 1.610874 | E30: XXX | G30: 8 | H30: =SUM(H34*0.11)+H34 -> 1.32867 | I30: =SUM(H34*0.08)+H34 -> 1.29276 | J30: =SUM(H34*0.08)+H34 -> 1.29276
B31: 27 | C31: =SUM(C34*0.26)+C34 -> 1.7649576 | D31: XXX | E31: XXX | G31: 9.52 | H31: =SUM(H34*0.12)+H34 -> 1.34064 | I31: =SUM(H34*0.09)+H34 -> 1.30473 | J31: =SUM(H34*0.09)+H34 -> 1.30473
B32: 30 | C32: =SUM(C34*0.32)+C34 -> 1.8490032 | D32: XXX | E32: XXX | G32: 12.7 | H32: =SUM(H34*0.12)+H34 -> 1.34064 | I32: =SUM(H34*0.09)+H34 -> 1.30473 | J32: =SUM(H34*0.09)+H34 -> 1.30473
B34: BASE | C34: =SUM(INICIO!J46) -> 1.40076 | G34: BASE | H34: =SUM(INICIO!P46) -> 1.197
B36: 3.17 | C36: 1245 | D36: S/MEL | E36: =SUM(I27*0.1)+I27 -> 1.422036 | I36: CALIDAD
B37: 4.75 | C37: 1500 | D37: S/MEL | E37: =SUM(J28*0.1)+J28 -> 1.422036 | I37: ANCHO
B38: 6.35 | C38: 1500 | D38: S/MEL | E38: =SUM(J29*0.1)+J29 -> 1.422036 | I38: ESPESOR

Sheet 34
B2: CLIENTE: | D2: =PROPER(INICIO!D47) -> Cb Accesorios/Fursan/Casasco
B4: LISTA DE PRECIOS EN PESOS
B5: DD | C5: 1000 | D5: 1220 | E5: 1500 | G5: NEGRA | H5: 1000 | I5: 1245 | J5: 1500
B6: 16 | C6: =SUM(C16*0.07)+C16 -> 2245.2222 | D6: =SUM(C16*0.04)+C16 -> 2182.272 | E6: =SUM(C16*0.04)+C16 -> 2182.272 | G6: 1.6 | H6: XXX | I6: XXX | J6: XXX
B7: 18 | C7: =SUM(C16*0.07)+C16 -> 2245.2222 | D7: =SUM(C16*0.04)+C16 -> 2182.272 | E7: =SUM(C16*0.04)+C16 -> 2182.272 | G7: 2 | H7: =SUM(H16*0.14)+H16 -> 2044.1408 | I7: =SUM(H16*0.11)+H16 -> 1990.3477 | J7: XXX
B8: 12,14 y 20 | C8: =SUM(C16*0.08)+C16 -> 2266.2056 | D8: =SUM(C16*0.05)+C16 -> 2203.2554 | E8: =SUM(C16*0.05)+C16 -> 2203.2554 | G8: 2.5 | H8: =SUM(H16*0.12)+H16 -> 2008.2787 | I8: =SUM(H16*0.09)+H16 -> 1954.4855 | J8: XXX
B9: 22 | C9: =SUM(C16*0.1)+C16 -> 2308.1723 | D9: =SUM(C16*0.07)+C16 -> 2245.2222 | E9: =SUM(C16*0.07)+C16 -> 2245.2222 | G9: 3.17 | H9: =SUM(H16*0.11)+H16 -> 1990.3477 | I9: =SUM(H16*0.08)+H16 -> 1936.5545 | J9: =SUM(H16*0.08)+H16 -> 1936.5545
B10: 0.65 | C10: =SUM(C16*0.12)+C16 -> 2350.1391 | D10: =SUM(C16*0.09)+C16 -> 2287.1889 | E10: XXX | G10: 4,75 Y 4.00 | H10: =SUM(H16*0.11)+H16 -> 1990.3477 | I10: =SUM(H16*0.08+H16) -> 1936.5545 | J10: =SUM(H16*0.08)+H16 -> 1936.5545
B11: 24 | C11: =SUM(C16*0.16)+C16 -> 2434.0726 | D11: =SUM(C16*0.13)+C16 -> 2371.1225 | E11: XXX | G11: 6.35 | H11: =SUM(H16*0.11)+H16 -> 1990.3477 | I11: =SUM(H16*0.08)+H16 -> 1936.5545 | J11: =SUM(H16*0.08)+H16 -> 1936.5545
B12: 26 | C12: =SUM(C16*0.2)+C16 -> 2518.0062 | D12: =SUM(C16*0.15)+C16 -> 2413.0893 | E12: XXX | G12: 8 | H12: =SUM(H16*0.11)+H16 -> 1990.3477 | I12: =SUM(H16*0.08)+H16 -> 1936.5545 | J12: =SUM(H16*0.08)+H16 -> 1936.5545
B13: 27 | C13: =SUM(C16*0.26)+C16 -> 2643.9065 | D13: XXX | E13: XXX | G13: 9.52 | H13: =SUM(H16*0.12)+H16 -> 2008.2787 | I13: =SUM(H16*0.09)+H16 -> 1954.4855 | J13: =SUM(H16*0.1)+H16 -> 1972.4166
B14: 30 | C14: =SUM(C16*0.32)+C16 -> 2769.8068 | D14: XXX | E14: XXX | G14: 12.7 | H14: =SUM(H16*0.12)+H16 -> 2008.2787 | I14: =SUM(H16*0.09)+H16 -> 1954.4855 | J14: =SUM(H16*0.1)+H16 -> 1972.4166
B16: BASE | C16: =SUM(INICIO!K47) -> 2098.3385 | G16: BASE | H16: =SUM(INICIO!Q47) -> 1793.106 | I16: fursan -10% | J16: dec -12%
I17: ang -10
B18: 3.17 | C18: 1245 | D18: S/MEL | E18: =SUM(I9*0.1)+I9 -> 2130.2099 | I18: CALIDAD
B19: 4.75 | C19: 1500 | D19: S/MEL | E19: =SUM(J10*0.1)+J10 -> 2130.2099 | I19: ANCHO
B20: 6.35 | C20: 1500 | D20: S/MEL | E20: =SUM(J11*0.1)+J11 -> 2130.2099 | I20: ESPESOR
B22: LISTA DE PRECIOS EN DÓLARES
B23: DD | C23: 1000 | D23: 1220 | E23: 1500 | G23: NEGRA | H23: 1000 | I23: 1245 | J23: 1500
B24: 16 | C24: =SUM(C34*0.07)+C34 -> 1.4988132 | D24: =SUM(C34*0.04)+C34 -> 1.4567904 | E24: =SUM(C34*0.04)+C34 -> 1.4567904 | G24: 1.6 | H24: XXX | I24: XXX | J24: XXX
B25: 18 | C25: =SUM(C34*0.07)+C34 -> 1.4988132 | D25: =SUM(C34*0.04)+C34 -> 1.4567904 | E25: =SUM(C34*0.04)+C34 -> 1.4567904 | G25: 2 | H25: =SUM(H34*0.14)+H34 -> 1.36458 | I25: =SUM(H34*0.11)+H34 -> 1.32867 | J25: XXX
B26: 12,14 y 20 | C26: =SUM(C34*0.08)+C34 -> 1.5128208 | D26: =SUM(C34*0.05)+C34 -> 1.470798 | E26: =SUM(C34*0.05)+C34 -> 1.470798 | G26: 2.5 | H26: =SUM(H34*0.12)+H34 -> 1.34064 | I26: =SUM(H34*0.09)+H34 -> 1.30473 | J26: XXX
B27: 22 | C27: =SUM(C34*0.1)+C34 -> 1.540836 | D27: =SUM(C34*0.07)+C34 -> 1.4988132 | E27: =SUM(C34*0.07)+C34 -> 1.4988132 | G27: 3.17 | H27: =SUM(H34*0.11)+H34 -> 1.32867 | I27: =SUM(H34*0.08)+H34 -> 1.29276 | J27: =SUM(H34*0.08)+H34 -> 1.29276
B28: 0.65 | C28: =SUM(C34*0.12)+C34 -> 1.5688512 | D28: =SUM(C34*0.09)+C34 -> 1.5268284 | E28: XXX | G28: 4,75 Y 4.00 | H28: =SUM(H34*0.1)+H34 -> 1.3167 | I28: =SUM(H34*0.07+H34) -> 1.28079 | J28: =SUM(H34*0.07)+H34 -> 1.28079
